Workbook

Sheet Dashboard
A1: Commercial & CRM Operations Dashboard
A2: Sales pipeline, channel efficiency, rep performance and funnel health | Data snapshot: 2026-09-01
A3: Won Revenue | C3: Open Pipeline | E3: Weighted Pipeline | G3: Win Rate | I3: Avg Won Deal | K3: Stale Open Leads | M3: Excel Model
A4: =SUM(CRM_Data!$V$2:$V$1801) -> 9775630 | C4: =SUMIFS(CRM_Data!$L$2:$L$1801,CRM_Data!$U$2:$U$1801,"Open") -> 13011200 | E4: =SUM(CRM_Data!$W$2:$W$1801) -> 7830015 | G4: =IFERROR(COUNTIF(CRM_Data!$U$2:$U$1801,"Won")/(COUNTIF(CRM_Data!$U$2:$U$1801,"Won")+COUNTIF(CRM_Data!$U$2:$U$1801,"Lost")),0) -> 0.26046176 | I4: =IFERROR(SUM(CRM_Data!$V$2:$V$1801)/COUNTIF(CRM_Data!$U$2:$U$1801,"Won"),0) -> 27079.307 | K4: =COUNTIF(CRM_Data!$Z$2:$Z$1801,"STALE") -> 358 | M4: Auditable formulas

Sheet CRM_Data
A1: Lead_ID | B1: Created_Date | C1: Owner | D1: Region | E1: Raw_Source | F1: Product_Code | G1: Industry | H1: Company_Size | I1: Deal_Stage | J1: Last_Stage_Date | K1: Close_Date | L1: Expected_Value_USD | M1: Discount_Pct | N1: Stage_Probability | O1: Lost_Reason | P1: Funnel_Level | Q1: Source_Clean | R1: Product_Name | S1: Product_Category | T1: Deal_Segment | U1: Outcome | V1: Actual_Revenue_USD | W1: Weighted_Pipeline_USD | X1: Sales_Cycle_Days | Y1: Age_Days | Z1: SLA_Flag | AA1: Created_Month | AB1: Close_Month | AC1: Created_Quarter | AD1: Lead_Score | AE1: Forecast_Category
A2: L00001 | B2: 45791 | C2: Ha Vo | D2: North | E2: Google Organic | F2: CS-CLOUD | G2: Education | H2: SMB | I2: Negotiation | J2: 46168 | L2: 25800 | M2: 0 | N2: 0.85 | P2: 5 | Q2: =IFERROR(VLOOKUP(E2,Lookups!$A$5:$B$24,2,FALSE),"Other") -> Organic Search | R2: =IFERROR(VLOOKUP(F2,Lookups!$D$5:$F$10,2,FALSE),"Unknown Product") -> Service Cloud | S2: =IFERROR(VLOOKUP(F2,Lookups!$D$5:$F$10,3,FALSE),"Unknown") -> Customer Service | T2: =IF(L2>=50000,"Enterprise",IF(L2>=20000,"Mid-Market","SMB")) -> Mid-Market | U2: =IF(I2="Closed Won","Won",IF(I2="Closed Lost","Lost","Open")) -> Open | V2: =IF(U2="Won",L2*(1-M2),0) -> 0 | W2: =IF(U2="Open",L2*N2,0) -> 21930 | X2: =IF(U2="Open","",IFERROR(K2-B2,"")) | Y2: =IF(U2="Open",Lookups!$B$2-B2,X2) -> 475 | Z2: =IF(AND(U2="Open",Y2>30),"STALE","OK") -> STALE | AA2: =TEXT(B2,"yyyy-mm") -> 2025-05 | AB2: =IF(K2="","",TEXT(K2,"yyyy-mm")) | AC2: ="Q"&ROUNDUP(MONTH(B2)/3,0)&"-"&YEAR(B2) -> Q2-2025 | AD2: =MIN(100,IF(H2="Enterprise",30,IF(H2="Mid-Market",22,14))+IF(T2="Enterprise",25,IF(T2="Mid-Market",18,10))+IF(Q2="Referral",25,IF(Q2="Organic Search",20,IF(Q2="Email",18,14)))+IF(G2="Technology",10,5)) -> 57 | AE2: =IF(U2<>"Open",U2,IF(N2>=0.8,"Commit",IF(N2>=0.5,"Best Case","Pipeline"))) -> Commit
A3: L00002 | B3: 46150 | C3: Quynh Vu | D3: North | E3: Google Ads | F3: CRM-CORE | G3: Education | H3: Mid-Market | I3: Proposal | J3: 46237 | L3: 9200 | M3: 0.05 | N3: 0.65 | P3: 4 | Q3: =IFERROR(VLOOKUP(E3,Lookups!$A$5:$B$24,2,FALSE),"Other") -> Paid Search | R3: =IFERROR(VLOOKUP(F3,Lookups!$D$5:$F$10,2,FALSE),"Unknown Product") -> NexaCRM Core | S3: =IFERROR(VLOOKUP(F3,Lookups!$D$5:$F$10,3,FALSE),"Unknown") -> CRM | T3: =IF(L3>=50000,"Enterprise",IF(L3>=20000,"Mid-Market","SMB")) -> SMB | U3: =IF(I3="Closed Won","Won",IF(I3="Closed Lost","Lost","Open")) -> Open | V3: =IF(U3="Won",L3*(1-M3),0) -> 0 | W3: =IF(U3="Open",L3*N3,0) -> 5980 | X3: =IF(U3="Open","",IFERROR(K3-B3,"")) | Y3: =IF(U3="Open",Lookups!$B$2-B3,X3) -> 116 | Z3: =IF(AND(U3="Open",Y3>30),"STALE","OK") -> STALE | AA3: =TEXT(B3,"yyyy-mm") -> 2026-05 | AB3: =IF(K3="","",TEXT(K3,"yyyy-mm")) | AC3: ="Q"&ROUNDUP(MONTH(B3)/3,0)&"-"&YEAR(B3) -> Q2-2026 | AD3: =MIN(100,IF(H3="Enterprise",30,IF(H3="Mid-Market",22,14))+IF(T3="Enterprise",25,IF(T3="Mid-Market",18,10))+IF(Q3="Referral",25,IF(Q3="Organic Search",20,IF(Q3="Email",18,14)))+IF(G3="Technology",10,5)) -> 51 | AE3: =IF(U3<>"Open",U3,IF(N3>=0.8,"Commit",IF(N3>=0.5,"Best Case","Pipeline"))) -> Best Case
A4: L00003 | B4: 46164 | C4: Chi Le | D4: South | E4: newsletter | F4: CRM-PRO | G4: Retail | H4: SMB | I4: Closed Lost | J4: 46204 | K4: 46204 | L4: 23300 | M4: 0 | N4: 0 | O4: Competitor | P4: 3 | Q4: =IFERROR(VLOOKUP(E4,Lookups!$A$5:$B$24,2,FALSE),"Other") -> Email | R4: =IFERROR(VLOOKUP(F4,Lookups!$D$5:$F$10,2,FALSE),"Unknown Product") -> NexaCRM Pro | S4: =IFERROR(VLOOKUP(F4,Lookups!$D$5:$F$10,3,FALSE),"Unknown") -> CRM | T4: =IF(L4>=50000,"Enterprise",IF(L4>=20000,"Mid-Market","SMB")) -> Mid-Market | U4: =IF(I4="Closed Won","Won",IF(I4="Closed Lost","Lost","Open")) -> Lost | V4: =IF(U4="Won",L4*(1-M4),0) -> 0 | W4: =IF(U4="Open",L4*N4,0) -> 0 | X4: =IF(U4="Open","",IFERROR(K4-B4,"")) -> 40 | Y4: =IF(U4="Open",Lookups!$B$2-B4,X4) -> 40 | Z4: =IF(AND(U4="Open",Y4>30),"STALE","OK") -> OK | AA4: =TEXT(B4,"yyyy-mm") -> 2026-05 | AB4: =IF(K4="","",TEXT(K4,"yyyy-mm")) -> 2026-07 | AC4: ="Q"&ROUNDUP(MONTH(B4)/3,0)&"-"&YEAR(B4) -> Q2-2026 | AD4: =MIN(100,IF(H4="Enterprise",30,IF(H4="Mid-Market",22,14))+IF(T4="Enterprise",25,IF(T4="Mid-Market",18,10))+IF(Q4="Referral",25,IF(Q4="Organic Search",20,IF(Q4="Email",18,14)))+IF(G4="Technology",10,5)) -> 55 | AE4: =IF(U4<>"Open",U4,IF(N4>=0.8,"Commit",IF(N4>=0.5,"Best Case","Pipeline"))) -> Lost
A5: L00004 | B5: 45697 | C5: Bao Tran | D5: South | E5: SEM - Google | F5: CRM-PRO | G5: Education | H5: SMB | I5: Closed Lost | J5: 45716 | K5: 45716 | L5: 17700 | M5: 0 | N5: 0 | O5: Competitor | P5: 2 | Q5: =IFERROR(VLOOKUP(E5,Lookups!$A$5:$B$24,2,FALSE),"Other") -> Paid Search | R5: =IFERROR(VLOOKUP(F5,Lookups!$D$5:$F$10,2,FALSE),"Unknown Product") -> NexaCRM Pro | S5: =IFERROR(VLOOKUP(F5,Lookups!$D$5:$F$10,3,FALSE),"Unknown") -> CRM | T5: =IF(L5>=50000,"Enterprise",IF(L5>=20000,"Mid-Market","SMB")) -> SMB | U5: =IF(I5="Closed Won","Won",IF(I5="Closed Lost","Lost","Open")) -> Lost | V5: =IF(U5="Won",L5*(1-M5),0) -> 0 | W5: =IF(U5="Open",L5*N5,0) -> 0 | X5: =IF(U5="Open","",IFERROR(K5-B5,"")) -> 19 | Y5: =IF(U5="Open",Lookups!$B$2-B5,X5) -> 19 | Z5: =IF(AND(U5="Open",Y5>30),"STALE","OK") -> OK | AA5: =TEXT(B5,"yyyy-mm") -> 2025-02 | AB5: =IF(K5="","",TEXT(K5,"yyyy-mm")) -> 2025-02 | AC5: ="Q"&ROUNDUP(MONTH(B5)/3,0)&"-"&YEAR(B5) -> Q1-2025 | AD5: =MIN(100,IF(H5="Enterprise",30,IF(H5="Mid-Market",22,14))+IF(T5="Enterprise",25,IF(T5="Mid-Market",18,10))+IF(Q5="Referral",25,IF(Q5="Organic Search",20,IF(Q5="Email",18,14)))+IF(G5="Technology",10,5)) -> 43 | AE5: =IF(U5<>"Open",U5,IF(N5>=0.8,"Commit",IF(N5>=0.5,"Best Case","Pipeline"))) -> Lost
A6: L00005 | B6: 45739 | C6: Chi Le | D6: South | E6: Google Organic | F6: REV-OPS | G6: Education | H6: Mid-Market | I6: Closed Lost | J6: 45786 | K6: 45786 | L6: 40300 | M6: 0 | N6: 0 | O6: Competitor | P6: 4 | Q6: =IFERROR(VLOOKUP(E6,Lookups!$A$5:$B$24,2,FALSE),"Other") -> Organic Search | R6: =IFERROR(VLOOKUP(F6,Lookups!$D$5:$F$10,2,FALSE),"Unknown Product") -> Revenue Operations Suite | S6: =IFERROR(VLOOKUP(F6,Lookups!$D$5:$F$10,3,FALSE),"Unknown") -> Revenue Ops | T6: =IF(L6>=50000,"Enterprise",IF(L6>=20000,"Mid-Market","SMB")) -> Mid-Market | U6: =IF(I6="Closed Won","Won",IF(I6="Closed Lost","Lost","Open")) -> Lost | V6: =IF(U6="Won",L6*(1-M6),0) -> 0 | W6: =IF(U6="Open",L6*N6,0) -> 0 | X6: =IF(U6="Open","",IFERROR(K6-B6,"")) -> 47 | Y6: =IF(U6="Open",Lookups!$B$2-B6,X6) -> 47 | Z6: =IF(AND(U6="Open",Y6>30),"STALE","OK") -> OK | AA6: =TEXT(B6,"yyyy-mm") -> 2025-03 | AB6: =IF(K6="","",TEXT(K6,"yyyy-mm")) -> 2025-05 | AC6: ="Q"&ROUNDUP(MONTH(B6)/3,0)&"-"&YEAR(B6) -> Q1-2025 | AD6: =MIN(100,IF(H6="Enterprise",30,IF(H6="Mid-Market",22,14))+IF(T6="Enterprise",25,IF(T6="Mid-Market",18,10))+IF(Q6="Referral",25,IF(Q6="Organic Search",20,IF(Q6="Email",18,14)))+IF(G6="Technology",10,5)) -> 65 | AE6: =IF(U6<>"Open",U6,IF(N6>=0.8,"Commit",IF(N6>=0.5,"Best Case","Pipeline"))) -> Lost
A7: L00006 | B7: 46224 | C7: An Nguyen | D7: South | E7: linkedin | F7: MKT-AUTO | G7: Healthcare | H7: SMB | I7: Qualified | J7: 46254 | L7: 10400 | M7: 0.05 | N7: 0.2 | P7: 2 | Q7: =IFERROR(VLOOKUP(E7,Lookups!$A$5:$B$24,2,FALSE),"Other") -> LinkedIn | R7: =IFERROR(VLOOKUP(F7,Lookups!$D$5:$F$10,2,FALSE),"Unknown Product") -> Marketing Automation | S7: =IFERROR(VLOOKUP(F7,Lookups!$D$5:$F$10,3,FALSE),"Unknown") -> Marketing | T7: =IF(L7>=50000,"Enterprise",IF(L7>=20000,"Mid-Market","SMB")) -> SMB | U7: =IF(I7="Closed Won","Won",IF(I7="Closed Lost","Lost","Open")) -> Open | V7: =IF(U7="Won",L7*(1-M7),0) -> 0 | W7: =IF(U7="Open",L7*N7,0) -> 2080 | X7: =IF(U7="Open","",IFERROR(K7-B7,"")) | Y7: =IF(U7="Open",Lookups!$B$2-B7,X7) -> 42 | Z7: =IF(AND(U7="Open",Y7>30),"STALE","OK") -> STALE | AA7: =TEXT(B7,"yyyy-mm") -> 2026-07 | AB7: =IF(K7="","",TEXT(K7,"yyyy-mm")) | AC7: ="Q"&ROUNDUP(MONTH(B7)/3,0)&"-"&YEAR(B7) -> Q3-2026 | AD7: =MIN(100,IF(H7="Enterprise",30,IF(H7="Mid-Market",22,14))+IF(T7="Enterprise",25,IF(T7="Mid-Market",18,10))+IF(Q7="Referral",25,IF(Q7="Organic Search",20,IF(Q7="Email",18,14)))+IF(G7="Technology",10,5)) -> 43 | AE7: =IF(U7<>"Open",U7,IF(N7>=0.8,"Commit",IF(N7>=0.5,"Best Case","Pipeline"))) -> Pipeline
A8: L00007 | B8: 45952 | C8: Chi Le | D8: South | E8: Webinar | F8: CRM-CORE | G8: Manufacturing | H8: Mid-Market | I8: Closed Won | J8: 45977 | K8: 45977 | L8: 16700 | M8: 0 | N8: 1 | P8: 6 | Q8: =IFERROR(VLOOKUP(E8,Lookups!$A$5:$B$24,2,FALSE),"Other") -> Webinar | R8: =IFERROR(VLOOKUP(F8,Lookups!$D$5:$F$10,2,FALSE),"Unknown Product") -> NexaCRM Core | S8: =IFERROR(VLOOKUP(F8,Lookups!$D$5:$F$10,3,FALSE),"Unknown") -> CRM | T8: =IF(L8>=50000,"Enterprise",IF(L8>=20000,"Mid-Market","SMB")) -> SMB | U8: =IF(I8="Closed Won","Won",IF(I8="Closed Lost","Lost","Open")) -> Won | V8: =IF(U8="Won",L8*(1-M8),0) -> 16700 | W8: =IF(U8="Open",L8*N8,0) -> 0 | X8: =IF(U8="Open","",IFERROR(K8-B8,"")) -> 25 | Y8: =IF(U8="Open",Lookups!$B$2-B8,X8) -> 25 | Z8: =IF(AND(U8="Open",Y8>30),"STALE","OK") -> OK | AA8: =TEXT(B8,"yyyy-mm") -> 2025-10 | AB8: =IF(K8="","",TEXT(K8,"yyyy-mm")) -> 2025-11 | AC8: ="Q"&ROUNDUP(MONTH(B8)/3,0)&"-"&YEAR(B8) -> Q4-2025 | AD8: =MIN(100,IF(H8="Enterprise",30,IF(H8="Mid-Market",22,14))+IF(T8="Enterprise",25,IF(T8="Mid-Market",18,10))+IF(Q8="Referral",25,IF(Q8="Organic Search",20,IF(Q8="Email",18,14)))+IF(G8="Technology",10,5)) -> 51 | AE8: =IF(U8<>"Open",U8,IF(N8>=0.8,"Commit",IF(N8>=0.5,"Best Case","Pipeline"))) -> Won
A9: L00008 | B9: 45762 | C9: Quynh Vu | D9: North | E9: SEM - Google | F9: MKT-AUTO | G9: Manufacturing | H9: Mid-Market | I9: Closed Lost | J9: 45786 | K9: 45786 | L9: 33600 | M9: 0 | N9: 0 | O9: No Decision | P9: 4 | Q9: =IFERROR(VLOOKUP(E9,Lookups!$A$5:$B$24,2,FALSE),"Other") -> Paid Search | R9: =IFERROR(VLOOKUP(F9,Lookups!$D$5:$F$10,2,FALSE),"Unknown Product") -> Marketing Automation | S9: =IFERROR(VLOOKUP(F9,Lookups!$D$5:$F$10,3,FALSE),"Unknown") -> Marketing | T9: =IF(L9>=50000,"Enterprise",IF(L9>=20000,"Mid-Market","SMB")) -> Mid-Market | U9: =IF(I9="Closed Won","Won",IF(I9="Closed Lost","Lost","Open")) -> Lost | V9: =IF(U9="Won",L9*(1-M9),0) -> 0 | W9: =IF(U9="Open",L9*N9,0) -> 0 | X9: =IF(U9="Open","",IFERROR(K9-B9,"")) -> 24 | Y9: =IF(U9="Open",Lookups!$B$2-B9,X9) -> 24 | Z9: =IF(AND(U9="Open",Y9>30),"STALE","OK") -> OK | AA9: =TEXT(B9,"yyyy-mm") -> 2025-04 | AB9: =IF(K9="","",TEXT(K9,"yyyy-mm")) -> 2025-05 | AC9: ="Q"&ROUNDUP(MONTH(B9)/3,0)&"-"&YEAR(B9) -> Q2-2025 | AD9: =MIN(100,IF(H9="Enterprise",30,IF(H9="Mid-Market",22,14))+IF(T9="Enterprise",25,IF(T9="Mid-Market",18,10))+IF(Q9="Referral",25,IF(Q9="Organic Search",20,IF(Q9="Email",18,14)))+IF(G9="Technology",10,5)) -> 59 | AE9: =IF(U9<>"Open",U9,IF(N9>=0.8,"Commit",IF(N9>=0.5,"Best Case","Pipeline"))) -> Lost
A10: L00009 | B10: 45803 | C10: Quynh Vu | D10: North | E10: Webinar | F10: CS-CLOUD | G10: Education | H10: Mid-Market | I10: Closed Lost | J10: 45843 | K10: 45843 | L10: 23100 | M10: 0 | N10: 0 | O10: Price | P10: 3 | Q10: =IFERROR(VLOOKUP(E10,Lookups!$A$5:$B$24,2,FALSE),"Other") -> Webinar | R10: =IFERROR(VLOOKUP(F10,Lookups!$D$5:$F$10,2,FALSE),"Unknown Product") -> Service Cloud | S10: =IFERROR(VLOOKUP(F10,Lookups!$D$5:$F$10,3,FALSE),"Unknown") -> Customer Service | T10: =IF(L10>=50000,"Enterprise",IF(L10>=20000,"Mid-Market","SMB")) -> Mid-Market | U10: =IF(I10="Closed Won","Won",IF(I10="Closed Lost","Lost","Open")) -> Lost | V10: =IF(U10="Won",L10*(1-M10),0) -> 0 | W10: =IF(U10="Open",L10*N10,0) -> 0 | X10: =IF(U10="Open","",IFERROR(K10-B10,"")) -> 40 | Y10: =IF(U10="Open",Lookups!$B$2-B10,X10) -> 40 | Z10: =IF(AND(U10="Open",Y10>30),"STALE","OK") -> OK | AA10: =TEXT(B10,"yyyy-mm") -> 2025-05 | AB10: =IF(K10="","",TEXT(K10,"yyyy-mm")) -> 2025-07 | AC10: ="Q"&ROUNDUP(MONTH(B10)/3,0)&"-"&YEAR(B10) -> Q2-2025 | AD10: =MIN(100,IF(H10="Enterprise",30,IF(H10="Mid-Market",22,14))+IF(T10="Enterprise",25,IF(T10="Mid-Market",18,10))+IF(Q10="Referral",25,IF(Q10="Organic Search",20,IF(Q10="Email",18,14)))+IF(G10="Technology",10,5)) -> 59 | AE10: =IF(U10<>"Open",U10,IF(N10>=0.8,"Commit",IF(N10>=0.5,"Best Case","Pipeline"))) -> Lost
A11: L00010 | B11: 45950 | C11: Ha Vo | D11: North | E11: organic search | F11: CS-CLOUD | G11: Healthcare | H11: Enterprise | I11: Negotiation | J11: 46070 | L11: 65200 | M11: 0.03 | N11: 0.85 | P11: 5 | Q11: =IFERROR(VLOOKUP(E11,Lookups!$A$5:$B$24,2,FALSE),"Other") -> Organic Search | R11: =IFERROR(VLOOKUP(F11,Lookups!$D$5:$F$10,2,FALSE),"Unknown Product") -> Service Cloud | S11: =IFERROR(VLOOKUP(F11,Lookups!$D$5:$F$10,3,FALSE),"Unknown") -> Customer Service | T11: =IF(L11>=50000,"Enterprise",IF(L11>=20000,"Mid-Market","SMB")) -> Enterprise | U11: =IF(I11="Closed Won","Won",IF(I11="Closed Lost","Lost","Open")) -> Open | V11: =IF(U11="Won",L11*(1-M11),0) -> 0 | W11: =IF(U11="Open",L11*N11,0) -> 55420 | X11: =IF(U11="Open","",IFERROR(K11-B11,"")) | Y11: =IF(U11="Open",Lookups!$B$2-B11,X11) -> 316 | Z11: =IF(AND(U11="Open",Y11>30),"STALE","OK") -> STALE | AA11: =TEXT(B11,"yyyy-mm") -> 2025-10 | AB11: =IF(K11="","",TEXT(K11,"yyyy-mm")) | AC11: ="Q"&ROUNDUP(MONTH(B11)/3,0)&"-"&YEAR(B11) -> Q4-2025 | AD11: =MIN(100,IF(H11="Enterprise",30,IF(H11="Mid-Market",22,14))+IF(T11="Enterprise",25,IF(T11="Mid-Market",18,10))+IF(Q11="Referral",25,IF(Q11="Organic Search",20,IF(Q11="Email",18,14)))+IF(G11="Technology",10,5)) -> 80 | AE11: =IF(U11<>"Open",U11,IF(N11>=0.8,"Commit",IF(N11>=0.5,"Best Case","Pipeline"))) -> Commit
A12: L00011 | B12: 46101 | C12: Tuan Bui | D12: Central | E12: Unknown Event | F12: CS-CLOUD | G12: Education | H12: Mid-Market | I12: Closed Won | J12: 46151 | K12: 46151 | L12: 42000 | M12: 0.12 | N12: 1 | P12: 6 | Q12: =IFERROR(VLOOKUP(E12,Lookups!$A$5:$B$24,2,FALSE),"Other") -> Other | R12: =IFERROR(VLOOKUP(F12,Lookups!$D$5:$F$10,2,FALSE),"Unknown Product") -> Service Cloud | S12: =IFERROR(VLOOKUP(F12,Lookups!$D$5:$F$10,3,FALSE),"Unknown") -> Customer Service | T12: =IF(L12>=50000,"Enterprise",IF(L12>=20000,"Mid-Market","SMB")) -> Mid-Market | U12: =IF(I12="Closed Won","Won",IF(I12="Closed Lost","Lost","Open")) -> Won | V12: =IF(U12="Won",L12*(1-M12),0) -> 36960 | W12: =IF(U12="Open",L12*N12,0) -> 0 | X12: =IF(U12="Open","",IFERROR(K12-B12,"")) -> 50 | Y12: =IF(U12="Open",Lookups!$B$2-B12,X12) -> 50 | Z12: =IF(AND(U12="Open",Y12>30),"STALE","OK") -> OK | AA12: =TEXT(B12,"yyyy-mm") -> 2026-03 | AB12: =IF(K12="","",TEXT(K12,"yyyy-mm")) -> 2026-05 | AC12: ="Q"&ROUNDUP(MONTH(B12)/3,0)&"-"&YEAR(B12) -> Q1-2026 | AD12: =MIN(100,IF(H12="Enterprise",30,IF(H12="Mid-Market",22,14))+IF(T12="Enterprise",25,IF(T12="Mid-Market",18,10))+IF(Q12="Referral",25,IF(Q12="Organic Search",20,IF(Q12="Email",18,14)))+IF(G12="Technology",10,5)) -> 59 | AE12: =IF(U12<>"Open",U12,IF(N12>=0.8,"Commit",IF(N12>=0.5,"Best Case","Pipeline"))) -> Won
A13: L00012 | B13: 45677 | C13: Duy Pham | D13: South | E13: organic search | F13: MKT-AUTO | G13: Education | H13: SMB | I13: Closed Lost | J13: 45716 | K13: 45716 | L13: 15700 | M13: 0 | N13: 0 | O13: Competitor | P13: 5 | Q13: =IFERROR(VLOOKUP(E13,Lookups!$A$5:$B$24,2,FALSE),"Other") -> Organic Search | R13: =IFERROR(VLOOKUP(F13,Lookups!$D$5:$F$10,2,FALSE),"Unknown Product") -> Marketing Automation | S13: =IFERROR(VLOOKUP(F13,Lookups!$D$5:$F$10,3,FALSE),"Unknown") -> Marketing | T13: =IF(L13>=50000,"Enterprise",IF(L13>=20000,"Mid-Market","SMB")) -> SMB | U13: =IF(I13="Closed Won","Won",IF(I13="Closed Lost","Lost","Open")) -> Lost | V13: =IF(U13="Won",L13*(1-M13),0) -> 0 | W13: =IF(U13="Open",L13*N13,0) -> 0 | X13: =IF(U13="Open","",IFERROR(K13-B13,"")) -> 39 | Y13: =IF(U13="Open",Lookups!$B$2-B13,X13) -> 39 | Z13: =IF(AND(U13="Open",Y13>30),"STALE","OK") -> OK | AA13: =TEXT(B13,"yyyy-mm") -> 2025-01 | AB13: =IF(K13="","",TEXT(K13,"yyyy-mm")) -> 2025-02 | AC13: ="Q"&ROUNDUP(MONTH(B13)/3,0)&"-"&YEAR(B13) -> Q1-2025 | AD13: =MIN(100,IF(H13="Enterprise",30,IF(H13="Mid-Market",22,14))+IF(T13="Enterprise",25,IF(T13="Mid-Market",18,10))+IF(Q13="Referral",25,IF(Q13="Organic Search",20,IF(Q13="Email",18,14)))+IF(G13="Technology",10,5)) -> 49 | AE13: =IF(U13<>"Open",U13,IF(N13>=0.8,"Commit",IF(N13>=0.5,"Best Case","Pipeline"))) -> Lost
A14: L00013 | B14: 45715 | C14: An Nguyen | D14: South | E14: virtual event | F14: CS-CLOUD | G14: Education | H14: Mid-Market | I14: Closed Lost | J14: 45758 | K14: 45758 | L14: 34400 | M14: 0 | N14: 0 | O14: Price | P14: 3 | Q14: =IFERROR(VLOOKUP(E14,Lookups!$A$5:$B$24,2,FALSE),"Other") -> Webinar | R14: =IFERROR(VLOOKUP(F14,Lookups!$D$5:$F$10,2,FALSE),"Unknown Product") -> Service Cloud | S14: =IFERROR(VLOOKUP(F14,Lookups!$D$5:$F$10,3,FALSE),"Unknown") -> Customer Service | T14: =IF(L14>=50000,"Enterprise",IF(L14>=20000,"Mid-Market","SMB")) -> Mid-Market | U14: =IF(I14="Closed Won","Won",IF(I14="Closed Lost","Lost","Open")) -> Lost | V14: =IF(U14="Won",L14*(1-M14),0) -> 0 | W14: =IF(U14="Open",L14*N14,0) -> 0 | X14: =IF(U14="Open","",IFERROR(K14-B14,"")) -> 43 | Y14: =IF(U14="Open",Lookups!$B$2-B14,X14) -> 43 | Z14: =IF(AND(U14="Open",Y14>30),"STALE","OK") -> OK | AA14: =TEXT(B14,"yyyy-mm") -> 2025-02 | AB14: =IF(K14="","",TEXT(K14,"yyyy-mm")) -> 2025-04 | AC14: ="Q"&ROUNDUP(MONTH(B14)/3,0)&"-"&YEAR(B14) -> Q1-2025 | AD14: =MIN(100,IF(H14="Enterprise",30,IF(H14="Mid-Market",22,14))+IF(T14="Enterprise",25,IF(T14="Mid-Market",18,10))+IF(Q14="Referral",25,IF(Q14="Organic Search",20,IF(Q14="Email",18,14)))+IF(G14="Technology",10,5)) -> 59 | AE14: =IF(U14<>"Open",U14,IF(N14>=0.8,"Commit",IF(N14>=0.5,"Best Case","Pipeline"))) -> Lost
A15: L00014 | B15: 45696 | C15: Bao Tran | D15: South | E15: Webinar | F15: CRM-CORE | G15: Financial Services | H15: SMB | I15: Negotiation | J15: 46172 | L15: 4800 | M15: 0.05 | N15: 0.85 | P15: 5 | Q15: =IFERROR(VLOOKUP(E15,Lookups!$A$5:$B$24,2,FALSE),"Other") -> Webinar | R15: =IFERROR(VLOOKUP(F15,Lookups!$D$5:$F$10,2,FALSE),"Unknown Product") -> NexaCRM Core | S15: =IFERROR(VLOOKUP(F15,Lookups!$D$5:$F$10,3,FALSE),"Unknown") -> CRM | T15: =IF(L15>=50000,"Enterprise",IF(L15>=20000,"Mid-Market","SMB")) -> SMB | U15: =IF(I15="Closed Won","Won",IF(I15="Closed Lost","Lost","Open")) -> Open | V15: =IF(U15="Won",L15*(1-M15),0) -> 0 | W15: =IF(U15="Open",L15*N15,0) -> 4080 | X15: =IF(U15="Open","",IFERROR(K15-B15,"")) | Y15: =IF(U15="Open",Lookups!$B$2-B15,X15) -> 570 | Z15: =IF(AND(U15="Open",Y15>30),"STALE","OK") -> STALE | AA15: =TEXT(B15,"yyyy-mm") -> 2025-02 | AB15: =IF(K15="","",TEXT(K15,"yyyy-mm")) | AC15: ="Q"&ROUNDUP(MONTH(B15)/3,0)&"-"&YEAR(B15) -> Q1-2025 | AD15: =MIN(100,IF(H15="Enterprise",30,IF(H15="Mid-Market",22,14))+IF(T15="Enterprise",25,IF(T15="Mid-Market",18,10))+IF(Q15="Referral",25,IF(Q15="Organic Search",20,IF(Q15="Email",18,14)))+IF(G15="Technology",10,5)) -> 43 | AE15: =IF(U15<>"Open",U15,IF(N15>=0.8,"Commit",IF(N15>=0.5,"Best Case","Pipeline"))) -> Commit
A16: L00015 | B16: 45955 | C16: Quynh Vu | D16: North | E16: LI Ads | F16: CRM-CORE | G16: Education | H16: Mid-Market | I16: Closed Lost | J16: 45987 | K16: 45987 | L16: 13400 | M16: 0 | N16: 0 | O16: No Decision | P16: 2 | Q16: =IFERROR(VLOOKUP(E16,Lookups!$A$5:$B$24,2,FALSE),"Other") -> LinkedIn | R16: =IFERROR(VLOOKUP(F16,Lookups!$D$5:$F$10,2,FALSE),"Unknown Product") -> NexaCRM Core | S16: =IFERROR(VLOOKUP(F16,Lookups!$D$5:$F$10,3,FALSE),"Unknown") -> CRM | T16: =IF(L16>=50000,"Enterprise",IF(L16>=20000,"Mid-Market","SMB")) -> SMB | U16: =IF(I16="Closed Won","Won",IF(I16="Closed Lost","Lost","Open")) -> Lost | V16: =IF(U16="Won",L16*(1-M16),0) -> 0 | W16: =IF(U16="Open",L16*N16,0) -> 0 | X16: =IF(U16="Open","",IFERROR(K16-B16,"")) -> 32 | Y16: =IF(U16="Open",Lookups!$B$2-B16,X16) -> 32 | Z16: =IF(AND(U16="Open",Y16>30),"STALE","OK") -> OK | AA16: =TEXT(B16,"yyyy-mm") -> 2025-10 | AB16: =IF(K16="","",TEXT(K16,"yyyy-mm")) -> 2025-11 | AC16: ="Q"&ROUNDUP(MONTH(B16)/3,0)&"-"&YEAR(B16) -> Q4-2025 | AD16: =MIN(100,IF(H16="Enterprise",30,IF(H16="Mid-Market",22,14))+IF(T16="Enterprise",25,IF(T16="Mid-Market",18,10))+IF(Q16="Referral",25,IF(Q16="Organic Search",20,IF(Q16="Email",18,14)))+IF(G16="Technology",10,5)) -> 51 | AE16: =IF(U16<>"Open",U16,IF(N16>=0.8,"Commit",IF(N16>=0.5,"Best Case","Pipeline"))) -> Lost
A17: L00016 | B17: 46057 | C17: Tuan Bui | D17: Central | E17: Cold Email | F17: CRM-PRO | G17: Professional Services | H17: SMB | I17: Closed Lost | J17: 46101 | K17: 46101 | L17: 23800 | M17: 0 | N17: 0 | O17: Competitor | P17: 4 | Q17: =IFERROR(VLOOKUP(E17,Lookups!$A$5:$B$24,2,FALSE),"Other") -> Outbound | R17: =IFERROR(VLOOKUP(F17,Lookups!$D$5:$F$10,2,FALSE),"Unknown Product") -> NexaCRM Pro | S17: =IFERROR(VLOOKUP(F17,Lookups!$D$5:$F$10,3,FALSE),"Unknown") -> CRM | T17: =IF(L17>=50000,"Enterprise",IF(L17>=20000,"Mid-Market","SMB")) -> Mid-Market | U17: =IF(I17="Closed Won","Won",IF(I17="Closed Lost","Lost","Open")) -> Lost | V17: =IF(U17="Won",L17*(1-M17),0) -> 0 | W17: =IF(U17="Open",L17*N17,0) -> 0 | X17: =IF(U17="Open","",IFERROR(K17-B17,"")) -> 44 | Y17: =IF(U17="Open",Lookups!$B$2-B17,X17) -> 44 | Z17: =IF(AND(U17="Open",Y17>30),"STALE","OK") -> OK | AA17: =TEXT(B17,"yyyy-mm") -> 2026-02 | AB17: =IF(K17="","",TEXT(K17,"yyyy-mm")) -> 2026-03 | AC17: ="Q"&ROUNDUP(MONTH(B17)/3,0)&"-"&YEAR(B17) -> Q1-2026 | AD17: =MIN(100,IF(H17="Enterprise",30,IF(H17="Mid-Market",22,14))+IF(T17="Enterprise",25,IF(T17="Mid-Market",18,10))+IF(Q17="Referral",25,IF(Q17="Organic Search",20,IF(Q17="Email",18,14)))+IF(G17="Technology",10,5)) -> 51 | AE17: =IF(U17<>"Open",U17,IF(N17>=0.8,"Commit",IF(N17>=0.5,"Best Case","Pipeline"))) -> Lost
A18: L00017 | B18: 45897 | C18: Chi Le | D18: South | E18: Webinar | F18: CRM-CORE | G18: Retail | H18: SMB | I18: Negotiation | J18: 46135 | L18: 7500 | M18: 0 | N18: 0.85 | P18: 5 | Q18: =IFERROR(VLOOKUP(E18,Lookups!$A$5:$B$24,2,FALSE),"Other") -> Webinar | R18: =IFERROR(VLOOKUP(F18,Lookups!$D$5:$F$10,2,FALSE),"Unknown Product") -> NexaCRM Core | S18: =IFERROR(VLOOKUP(F18,Lookups!$D$5:$F$10,3,FALSE),"Unknown") -> CRM | T18: =IF(L18>=50000,"Enterprise",IF(L18>=20000,"Mid-Market","SMB")) -> SMB | U18: =IF(I18="Closed Won","Won",IF(I18="Closed Lost","Lost","Open")) -> Open | V18: =IF(U18="Won",L18*(1-M18),0) -> 0 | W18: =IF(U18="Open",L18*N18,0) -> 6375 | X18: =IF(U18="Open","",IFERROR(K18-B18,"")) | Y18: =IF(U18="Open",Lookups!$B$2-B18,X18) -> 369 | Z18: =IF(AND(U18="Open",Y18>30),"STALE","OK") -> STALE | AA18: =TEXT(B18,"yyyy-mm") -> 2025-08 | AB18: =IF(K18="","",TEXT(K18,"yyyy-mm")) | AC18: ="Q"&ROUNDUP(MONTH(B18)/3,0)&"-"&YEAR(B18) -> Q3-2025 | AD18: =MIN(100,IF(H18="Enterprise",30,IF(H18="Mid-Market",22,14))+IF(T18="Enterprise",25,IF(T18="Mid-Market",18,10))+IF(Q18="Referral",25,IF(Q18="Organic Search",20,IF(Q18="Email",18,14)))+IF(G18="Technology",10,5)) -> 43 | AE18: =IF(U18<>"Open",U18,IF(N18>=0.8,"Commit",IF(N18>=0.5,"Best Case","Pipeline"))) -> Commit
A19: L00018 | B19: 46192 | C19: Quynh Vu | D19: North | E19: Cold Email | F19: REV-OPS | G19: Financial Services | H19: Mid-Market | I19: Closed Lost | J19: 46231 | K19: 46231 | L19: 80200 | M19: 0 | N19: 0 | O19: Timing | P19: 3 | Q19: =IFERROR(VLOOKUP(E19,Lookups!$A$5:$B$24,2,FALSE),"Other") -> Outbound | R19: =IFERROR(VLOOKUP(F19,Lookups!$D$5:$F$10,2,FALSE),"Unknown Product") -> Revenue Operations Suite | S19: =IFERROR(VLOOKUP(F19,Lookups!$D$5:$F$10,3,FALSE),"Unknown") -> Revenue Ops | T19: =IF(L19>=50000,"Enterprise",IF(L19>=20000,"Mid-Market","SMB")) -> Enterprise | U19: =IF(I19="Closed Won","Won",IF(I19="Closed Lost","Lost","Open")) -> Lost | V19: =IF(U19="Won",L19*(1-M19),0) -> 0 | W19: =IF(U19="Open",L19*N19,0) -> 0 | X19: =IF(U19="Open","",IFERROR(K19-B19,"")) -> 39 | Y19: =IF(U19="Open",Lookups!$B$2-B19,X19) -> 39 | Z19: =IF(AND(U19="Open",Y19>30),"STALE","OK") -> OK | AA19: =TEXT(B19,"yyyy-mm") -> 2026-06 | AB19: =IF(K19="","",TEXT(K19,"yyyy-mm")) -> 2026-07 | AC19: ="Q"&ROUNDUP(MONTH(B19)/3,0)&"-"&YEAR(B19) -> Q2-2026 | AD19: =MIN(100,IF(H19="Enterprise",30,IF(H19="Mid-Market",22,14))+IF(T19="Enterprise",25,IF(T19="Mid-Market",18,10))+IF(Q19="Referral",25,IF(Q19="Organic Search",20,IF(Q19="Email",18,14)))+IF(G19="Technology",10,5)) -> 66 | AE19: =IF(U19<>"Open",U19,IF(N19>=0.8,"Commit",IF(N19>=0.5,"Best Case","Pipeline"))) -> Lost
A20: L00019 | B20: 46191 | C20: Tuan Bui | D20: Central | E20: Offline List | F20: MKT-AUTO | G20: Retail | H20: Mid-Market | I20: Demo / Meeting | J20: 46229 | L20: 17200 | M20: 0.05 | N20: 0.4 | P20: 3 | Q20: =IFERROR(VLOOKUP(E20,Lookups!$A$5:$B$24,2,FALSE),"Other") -> Other | R20: =IFERROR(VLOOKUP(F20,Lookups!$D$5:$F$10,2,FALSE),"Unknown Product") -> Marketing Automation | S20: =IFERROR(VLOOKUP(F20,Lookups!$D$5:$F$10,3,FALSE),"Unknown") -> Marketing | T20: =IF(L20>=50000,"Enterprise",IF(L20>=20000,"Mid-Market","SMB")) -> SMB | U20: =IF(I20="Closed Won","Won",IF(I20="Closed Lost","Lost","Open")) -> Open | V20: =IF(U20="Won",L20*(1-M20),0) -> 0 | W20: =IF(U20="Open",L20*N20,0) -> 6880 | X20: =IF(U20="Open","",IFERROR(K20-B20,"")) | Y20: =IF(U20="Open",Lookups!$B$2-B20,X20) -> 75 | Z20: =IF(AND(U20="Open",Y20>30),"STALE","OK") -> STALE | AA20: =TEXT(B20,"yyyy-mm") -> 2026-06 | AB20: =IF(K20="","",TEXT(K20,"yyyy-mm")) | AC20: ="Q"&ROUNDUP(MONTH(B20)/3,0)&"-"&YEAR(B20) -> Q2-2026 | AD20: =MIN(100,IF(H20="Enterprise",30,IF(H20="Mid-Market",22,14))+IF(T20="Enterprise",25,IF(T20="Mid-Market",18,10))+IF(Q20="Referral",25,IF(Q20="Organic Search",20,IF(Q20="Email",18,14)))+IF(G20="Technology",10,5)) -> 51 | AE20: =IF(U20<>"Open",U20,IF(N20>=0.8,"Commit",IF(N20>=0.5,"Best Case","Pipeline"))) -> Pipeline
A21: L00020 | B21: 45689 | C21: Duy Pham | D21: South | E21: Referral | F21: CRM-PRO | G21: Manufacturing | H21: Mid-Market | I21: Closed Won | J21: 45712 | K21: 45712 | L21: 43800 | M21: 0.08 | N21: 1 | P21: 6 | Q21: =IFERROR(VLOOKUP(E21,Lookups!$A$5:$B$24,2,FALSE),"Other") -> Referral | R21: =IFERROR(VLOOKUP(F21,Lookups!$D$5:$F$10,2,FALSE),"Unknown Product") -> NexaCRM Pro | S21: =IFERROR(VLOOKUP(F21,Lookups!$D$5:$F$10,3,FALSE),"Unknown") -> CRM | T21: =IF(L21>=50000,"Enterprise",IF(L21>=20000,"Mid-Market","SMB")) -> Mid-Market | U21: =IF(I21="Closed Won","Won",IF(I21="Closed Lost","Lost","Open")) -> Won | V21: =IF(U21="Won",L21*(1-M21),0) -> 40296 | W21: =IF(U21="Open",L21*N21,0) -> 0 | X21: =IF(U21="Open","",IFERROR(K21-B21,"")) -> 23 | Y21: =IF(U21="Open",Lookups!$B$2-B21,X21) -> 23 | Z21: =IF(AND(U21="Open",Y21>30),"STALE","OK") -> OK | AA21: =TEXT(B21,"yyyy-mm") -> 2025-02 | AB21: =IF(K21="","",TEXT(K21,"yyyy-mm")) -> 2025-02 | AC21: ="Q"&ROUNDUP(MONTH(B21)/3,0)&"-"&YEAR(B21) -> Q1-2025 | AD21: =MIN(100,IF(H21="Enterprise",30,IF(H21="Mid-Market",22,14))+IF(T21="Enterprise",25,IF(T21="Mid-Market",18,10))+IF(Q21="Referral",25,IF(Q21="Organic Search",20,IF(Q21="Email",18,14)))+IF(G21="Technology",10,5)) -> 70 | AE21: =IF(U21<>"Open",U21,IF(N21>=0.8,"Commit",IF(N21>=0.5,"Best Case","Pipeline"))) -> Won
A22: L00021 | B22: 45753 | C22: Duy Pham | D22: South | E22: Outbound | F22: CRM-CORE | G22: Financial Services | H22: SMB | I22: Closed Lost | J22: 45775 | K22: 45775 | L22: 8800 | M22: 0 | N22: 0 | O22: Feature Gap | P22: 4 | Q22: =IFERROR(VLOOKUP(E22,Lookups!$A$5:$B$24,2,FALSE),"Other") -> Outbound | R22: =IFERROR(VLOOKUP(F22,Lookups!$D$5:$F$10,2,FALSE),"Unknown Product") -> NexaCRM Core | S22: =IFERROR(VLOOKUP(F22,Lookups!$D$5:$F$10,3,FALSE),"Unknown") -> CRM | T22: =IF(L22>=50000,"Enterprise",IF(L22>=20000,"Mid-Market","SMB")) -> SMB | U22: =IF(I22="Closed Won","Won",IF(I22="Closed Lost","Lost","Open")) -> Lost | V22: =IF(U22="Won",L22*(1-M22),0) -> 0 | W22: =IF(U22="Open",L22*N22,0) -> 0 | X22: =IF(U22="Open","",IFERROR(K22-B22,"")) -> 22 | Y22: =IF(U22="Open",Lookups!$B$2-B22,X22) -> 22 | Z22: =IF(AND(U22="Open",Y22>30),"STALE","OK") -> OK | AA22: =TEXT(B22,"yyyy-mm") -> 2025-04 | AB22: =IF(K22="","",TEXT(K22,"yyyy-mm")) -> 2025-04 | AC22: ="Q"&ROUNDUP(MONTH(B22)/3,0)&"-"&YEAR(B22) -> Q2-2025 | AD22: =MIN(100,IF(H22="Enterprise",30,IF(H22="Mid-Market",22,14))+IF(T22="Enterprise",25,IF(T22="Mid-Market",18,10))+IF(Q22="Referral",25,IF(Q22="Organic Search",20,IF(Q22="Email",18,14)))+IF(G22="Technology",10,5)) -> 43 | AE22: =IF(U22<>"Open",U22,IF(N22>=0.8,"Commit",IF(N22>=0.5,"Best Case","Pipeline"))) -> Lost
A23: L00022 | B23: 46178 | C23: Bao Tran | D23: South | E23: Google Ads | F23: CRM-CORE | G23: Technology | H23: Mid-Market | I23: Closed Won | J23: 46217 | K23: 46217 | L23: 9100 | M23: 0.05 | N23: 1 | P23: 6 | Q23: =IFERROR(VLOOKUP(E23,Lookups!$A$5:$B$24,2,FALSE),"Other") -> Paid Search | R23: =IFERROR(VLOOKUP(F23,Lookups!$D$5:$F$10,2,FALSE),"Unknown Product") -> NexaCRM Core | S23: =IFERROR(VLOOKUP(F23,Lookups!$D$5:$F$10,3,FALSE),"Unknown") -> CRM | T23: =IF(L23>=50000,"Enterprise",IF(L23>=20000,"Mid-Market","SMB")) -> SMB | U23: =IF(I23="Closed Won","Won",IF(I23="Closed Lost","Lost","Open")) -> Won | V23: =IF(U23="Won",L23*(1-M23),0) -> 8645 | W23: =IF(U23="Open",L23*N23,0) -> 0 | X23: =IF(U23="Open","",IFERROR(K23-B23,"")) -> 39 | Y23: =IF(U23="Open",Lookups!$B$2-B23,X23) -> 39 | Z23: =IF(AND(U23="Open",Y23>30),"STALE","OK") -> OK | AA23: =TEXT(B23,"yyyy-mm") -> 2026-06 | AB23: =IF(K23="","",TEXT(K23,"yyyy-mm")) -> 2026-07 | AC23: ="Q"&ROUNDUP(MONTH(B23)/3,0)&"-"&YEAR(B23) -> Q2-2026 | AD23: =MIN(100,IF(H23="Enterprise",30,IF(H23="Mid-Market",22,14))+IF(T23="Enterprise",25,IF(T23="Mid-Market",18,10))+IF(Q23="Referral",25,IF(Q23="Organic Search",20,IF(Q23="Email",18,14)))+IF(G23="Technology",10,5)) -> 56 | AE23: =IF(U23<>"Open",U23,IF(N23>=0.8,"Commit",IF(N23>=0.5,"Best Case","Pipeline"))) -> Won
A24: L00023 | B24: 45816 | C24: Quynh Vu | D24: North | E24: Referral | F24: CRM-CORE | G24: Education | H24: Enterprise | I24: Closed Lost | J24: 45835 | K24: 45835 | L24: 17400 | M24: 0 | N24: 0 | O24: Competitor | P24: 5 | Q24: =IFERROR(VLOOKUP(E24,Lookups!$A$5:$B$24,2,FALSE),"Other") -> Referral | R24: =IFERROR(VLOOKUP(F24,Lookups!$D$5:$F$10,2,FALSE),"Unknown Product") -> NexaCRM Core | S24: =IFERROR(VLOOKUP(F24,Lookups!$D$5:$F$10,3,FALSE),"Unknown") -> CRM | T24: =IF(L24>=50000,"Enterprise",IF(L24>=20000,"Mid-Market","SMB")) -> SMB | U24: =IF(I24="Closed Won","Won",IF(I24="Closed Lost","Lost","Open")) -> Lost | V24: =IF(U24="Won",L24*(1-M24),0) -> 0 | W24: =IF(U24="Open",L24*N24,0) -> 0 | X24: =IF(U24="Open","",IFERROR(K24-B24,"")) -> 19 | Y24: =IF(U24="Open",Lookups!$B$2-B24,X24) -> 19 | Z24: =IF(AND(U24="Open",Y24>30),"STALE","OK") -> OK | AA24: =TEXT(B24,"yyyy-mm") -> 2025-06 | AB24: =IF(K24="","",TEXT(K24,"yyyy-mm")) -> 2025-06 | AC24: ="Q"&ROUNDUP(MONTH(B24)/3,0)&"-"&YEAR(B24) -> Q2-2025 | AD24: =MIN(100,IF(H24="Enterprise",30,IF(H24="Mid-Market",22,14))+IF(T24="Enterprise",25,IF(T24="Mid-Market",18,10))+IF(Q24="Referral",25,IF(Q24="Organic Search",20,IF(Q24="Email",18,14)))+IF(G24="Technology",10,5)) -> 70 | AE24: =IF(U24<>"Open",U24,IF(N24>=0.8,"Commit",IF(N24>=0.5,"Best Case","Pipeline"))) -> Lost
A25: L00024 | B25: 45856 | C25: Bao Tran | D25: South | E25: SDR Outreach | F25: MKT-AUTO | G25: Manufacturing | H25: Mid-Market | I25: Closed Lost | J25: 45864 | K25: 45864 | L25: 19200 | M25: 0 | N25: 0 | O25: Budget | P25: 4 | Q25: =IFERROR(VLOOKUP(E25,Lookups!$A$5:$B$24,2,FALSE),"Other") -> Outbound | R25: =IFERROR(VLOOKUP(F25,Lookups!$D$5:$F$10,2,FALSE),"Unknown Product") -> Marketing Automation | S25: =IFERROR(VLOOKUP(F25,Lookups!$D$5:$F$10,3,FALSE),"Unknown") -> Marketing | T25: =IF(L25>=50000,"Enterprise",IF(L25>=20000,"Mid-Market","SMB")) -> SMB | U25: =IF(I25="Closed Won","Won",IF(I25="Closed Lost","Lost","Open")) -> Lost | V25: =IF(U25="Won",L25*(1-M25),0) -> 0 | W25: =IF(U25="Open",L25*N25,0) -> 0 | X25: =IF(U25="Open","",IFERROR(K25-B25,"")) -> 8 | Y25: =IF(U25="Open",Lookups!$B$2-B25,X25) -> 8 | Z25: =IF(AND(U25="Open",Y25>30),"STALE","OK") -> OK | AA25: =TEXT(B25,"yyyy-mm") -> 2025-07 | AB25: =IF(K25="","",TEXT(K25,"yyyy-mm")) -> 2025-07 | AC25: ="Q"&ROUNDUP(MONTH(B25)/3,0)&"-"&YEAR(B25) -> Q3-2025 | AD25: =MIN(100,IF(H25="Enterprise",30,IF(H25="Mid-Market",22,14))+IF(T25="Enterprise",25,IF(T25="Mid-Market",18,10))+IF(Q25="Referral",25,IF(Q25="Organic Search",20,IF(Q25="Email",18,14)))+IF(G25="Technology",10,5)) -> 51 | AE25: =IF(U25<>"Open",U25,IF(N25>=0.8,"Commit",IF(N25>=0.5,"Best Case","Pipeline"))) -> Lost
A26: L00025 | B26: 45707 | C26: An Nguyen | D26: South | E26: linkedin | F26: CS-CLOUD | G26: Retail | H26: SMB | I26: Negotiation | J26: 46185 | L26: 22400 | M26: 0 | N26: 0.85 | P26: 5 | Q26: =IFERROR(VLOOKUP(E26,Lookups!$A$5:$B$24,2,FALSE),"Other") -> LinkedIn | R26: =IFERROR(VLOOKUP(F26,Lookups!$D$5:$F$10,2,FALSE),"Unknown Product") -> Service Cloud | S26: =IFERROR(VLOOKUP(F26,Lookups!$D$5:$F$10,3,FALSE),"Unknown") -> Customer Service | T26: =IF(L26>=50000,"Enterprise",IF(L26>=20000,"Mid-Market","SMB")) -> Mid-Market | U26: =IF(I26="Closed Won","Won",IF(I26="Closed Lost","Lost","Open")) -> Open | V26: =IF(U26="Won",L26*(1-M26),0) -> 0 | W26: =IF(U26="Open",L26*N26,0) -> 19040 | X26: =IF(U26="Open","",IFERROR(K26-B26,"")) | Y26: =IF(U26="Open",Lookups!$B$2-B26,X26) -> 559 | Z26: =IF(AND(U26="Open",Y26>30),"STALE","OK") -> STALE | AA26: =TEXT(B26,"yyyy-mm") -> 2025-02 | AB26: =IF(K26="","",TEXT(K26,"yyyy-mm")) | AC26: ="Q"&ROUNDUP(MONTH(B26)/3,0)&"-"&YEAR(B26) -> Q1-2025 | AD26: =MIN(100,IF(H26="Enterprise",30,IF(H26="Mid-Market",22,14))+IF(T26="Enterprise",25,IF(T26="Mid-Market",18,10))+IF(Q26="Referral",25,IF(Q26="Organic Search",20,IF(Q26="Email",18,14)))+IF(G26="Technology",10,5)) -> 51 | AE26: =IF(U26<>"Open",U26,IF(N26>=0.8,"Commit",IF(N26>=0.5,"Best Case","Pipeline"))) -> Commit
A27: L00026 | B27: 46139 | C27: An Nguyen | D27: South | E27: customer referral | F27: CRM-PRO | G27: Professional Services | H27: Enterprise | I27: Negotiation | J27: 46188 | L27: 81700 | M27: 0 | N27: 0.85 | P27: 5 | Q27: =IFERROR(VLOOKUP(E27,Lookups!$A$5:$B$24,2,FALSE),"Other") -> Referral | R27: =IFERROR(VLOOKUP(F27,Lookups!$D$5:$F$10,2,FALSE),"Unknown Product") -> NexaCRM Pro | S27: =IFERROR(VLOOKUP(F27,Lookups!$D$5:$F$10,3,FALSE),"Unknown") -> CRM | T27: =IF(L27>=50000,"Enterprise",IF(L27>=20000,"Mid-Market","SMB")) -> Enterprise | U27: =IF(I27="Closed Won","Won",IF(I27="Closed Lost","Lost","Open")) -> Open | V27: =IF(U27="Won",L27*(1-M27),0) -> 0 | W27: =IF(U27="Open",L27*N27,0) -> 69445 | X27: =IF(U27="Open","",IFERROR(K27-B27,"")) | Y27: =IF(U27="Open",Lookups!$B$2-B27,X27) -> 127 | Z27: =IF(AND(U27="Open",Y27>30),"STALE","OK") -> STALE | AA27: =TEXT(B27,"yyyy-mm") -> 2026-04 | AB27: =IF(K27="","",TEXT(K27,"yyyy-mm")) | AC27: ="Q"&ROUNDUP(MONTH(B27)/3,0)&"-"&YEAR(B27) -> Q2-2026 | AD27: =MIN(100,IF(H27="Enterprise",30,IF(H27="Mid-Market",22,14))+IF(T27="Enterprise",25,IF(T27="Mid-Market",18,10))+IF(Q27="Referral",25,IF(Q27="Organic Search",20,IF(Q27="Email",18,14)))+IF(G27="Technology",10,5)) -> 85 | AE27: =IF(U27<>"Open",U27,IF(N27>=0.8,"Commit",IF(N27>=0.5,"Best Case","Pipeline"))) -> Commit
A28: L00027 | B28: 46110 | C28: Tuan Bui | D28: Central | E28: virtual event | F28: CS-CLOUD | G28: Manufacturing | H28: Mid-Market | I28: Closed Lost | J28: 46118 | K28: 46118 | L28: 49100 | M28: 0 | N28: 0 | O28: Price | P28: 2 | Q28: =IFERROR(VLOOKUP(E28,Lookups!$A$5:$B$24,2,FALSE),"Other") -> Webinar | R28: =IFERROR(VLOOKUP(F28,Lookups!$D$5:$F$10,2,FALSE),"Unknown Product") -> Service Cloud | S28: =IFERROR(VLOOKUP(F28,Lookups!$D$5:$F$10,3,FALSE),"Unknown") -> Customer Service | T28: =IF(L28>=50000,"Enterprise",IF(L28>=20000,"Mid-Market","SMB")) -> Mid-Market | U28: =IF(I28="Closed Won","Won",IF(I28="Closed Lost","Lost","Open")) -> Lost | V28: =IF(U28="Won",L28*(1-M28),0) -> 0 | W28: =IF(U28="Open",L28*N28,0) -> 0 | X28: =IF(U28="Open","",IFERROR(K28-B28,"")) -> 8 | Y28: =IF(U28="Open",Lookups!$B$2-B28,X28) -> 8 | Z28: =IF(AND(U28="Open",Y28>30),"STALE","OK") -> OK | AA28: =TEXT(B28,"yyyy-mm") -> 2026-03 | AB28: =IF(K28="","",TEXT(K28,"yyyy-mm")) -> 2026-04 | AC28: ="Q"&ROUNDUP(MONTH(B28)/3,0)&"-"&YEAR(B28) -> Q1-2026 | AD28: =MIN(100,IF(H28="Enterprise",30,IF(H28="Mid-Market",22,14))+IF(T28="Enterprise",25,IF(T28="Mid-Market",18,10))+IF(Q28="Referral",25,IF(Q28="Organic Search",20,IF(Q28="Email",18,14)))+IF(G28="Technology",10,5)) -> 59 | AE28: =IF(U28<>"Open",U28,IF(N28>=0.8,"Commit",IF(N28>=0.5,"Best Case","Pipeline"))) -> Lost
A29: L00028 | B29: 45911 | C29: Ha Vo | D29: North | E29: LI Ads | F29: MKT-AUTO | G29: Retail | H29: Mid-Market | I29: Closed Lost | J29: 45961 | K29: 45961 | L29: 22500 | M29: 0 | N29: 0 | O29: Competitor | P29: 5 | Q29: =IFERROR(VLOOKUP(E29,Lookups!$A$5:$B$24,2,FALSE),"Other") -> LinkedIn | R29: =IFERROR(VLOOKUP(F29,Lookups!$D$5:$F$10,2,FALSE),"Unknown Product") -> Marketing Automation | S29: =IFERROR(VLOOKUP(F29,Lookups!$D$5:$F$10,3,FALSE),"Unknown") -> Marketing | T29: =IF(L29>=50000,"Enterprise",IF(L29>=20000,"Mid-Market","SMB")) -> Mid-Market | U29: =IF(I29="Closed Won","Won",IF(I29="Closed Lost","Lost","Open")) -> Lost | V29: =IF(U29="Won",L29*(1-M29),0) -> 0 | W29: =IF(U29="Open",L29*N29,0) -> 0 | X29: =IF(U29="Open","",IFERROR(K29-B29,"")) -> 50 | Y29: =IF(U29="Open",Lookups!$B$2-B29,X29) -> 50 | Z29: =IF(AND(U29="Open",Y29>30),"STALE","OK") -> OK | AA29: =TEXT(B29,"yyyy-mm") -> 2025-09 | AB29: =IF(K29="","",TEXT(K29,"yyyy-mm")) -> 2025-10 | AC29: ="Q"&ROUNDUP(MONTH(B29)/3,0)&"-"&YEAR(B29) -> Q3-2025 | AD29: =MIN(100,IF(H29="Enterprise",30,IF(H29="Mid-Market",22,14))+IF(T29="Enterprise",25,IF(T29="Mid-Market",18,10))+IF(Q29="Referral",25,IF(Q29="Organic Search",20,IF(Q29="Email",18,14)))+IF(G29="Technology",10,5)) -> 59 | AE29: =IF(U29<>"Open",U29,IF(N29>=0.8,"Commit",IF(N29>=0.5,"Best Case","Pipeline"))) -> Lost
A30: L00029 | B30: 45963 | C30: An Nguyen | D30: South | E30: email nurture | F30: CRM-CORE | G30: Professional Services | H30: Mid-Market | I30: Closed Lost | J30: 46011 | K30: 46011 | L30: 8400 | M30: 0 | N30: 0 | O30: Price | P30: 3 | Q30: =IFERROR(VLOOKUP(E30,Lookups!$A$5:$B$24,2,FALSE),"Other") -> Email | R30: =IFERROR(VLOOKUP(F30,Lookups!$D$5:$F$10,2,FALSE),"Unknown Product") -> NexaCRM Core | S30: =IFERROR(VLOOKUP(F30,Lookups!$D$5:$F$10,3,FALSE),"Unknown") -> CRM | T30: =IF(L30>=50000,"Enterprise",IF(L30>=20000,"Mid-Market","SMB")) -> SMB | U30: =IF(I30="Closed Won","Won",IF(I30="Closed Lost","Lost","Open")) -> Lost | V30: =IF(U30="Won",L30*(1-M30),0) -> 0 | W30: =IF(U30="Open",L30*N30,0) -> 0 | X30: =IF(U30="Open","",IFERROR(K30-B30,"")) -> 48 | Y30: =IF(U30="Open",Lookups!$B$2-B30,X30) -> 48 | Z30: =IF(AND(U30="Open",Y30>30),"STALE","OK") -> OK | AA30: =TEXT(B30,"yyyy-mm") -> 2025-11 | AB30: =IF(K30="","",TEXT(K30,"yyyy-mm")) -> 2025-12 | AC30: ="Q"&ROUNDUP(MONTH(B30)/3,0)&"-"&YEAR(B30) -> Q4-2025 | AD30: =MIN(100,IF(H30="Enterprise",30,IF(H30="Mid-Market",22,14))+IF(T30="Enterprise",25,IF(T30="Mid-Market",18,10))+IF(Q30="Referral",25,IF(Q30="Organic Search",20,IF(Q30="Email",18,14)))+IF(G30="Technology",10,5)) -> 55 | AE30: =IF(U30<>"Open",U30,IF(N30>=0.8,"Commit",IF(N30>=0.5,"Best Case","Pipeline"))) -> Lost
A31: L00030 | B31: 46247 | C31: Quynh Vu | D31: North | E31: linkedin | F31: CRM-PRO | G31: Manufacturing | H31: Enterprise | I31: Qualified | J31: 46258 | L31: 80900 | M31: 0 | N31: 0.2 | P31: 2 | Q31: =IFERROR(VLOOKUP(E31,Lookups!$A$5:$B$24,2,FALSE),"Other") -> LinkedIn | R31: =IFERROR(VLOOKUP(F31,Lookups!$D$5:$F$10,2,FALSE),"Unknown Product") -> NexaCRM Pro | S31: =IFERROR(VLOOKUP(F31,Lookups!$D$5:$F$10,3,FALSE),"Unknown") -> CRM | T31: =IF(L31>=50000,"Enterprise",IF(L31>=20000,"Mid-Market","SMB")) -> Enterprise | U31: =IF(I31="Closed Won","Won",IF(I31="Closed Lost","Lost","Open")) -> Open | V31: =IF(U31="Won",L31*(1-M31),0) -> 0 | W31: =IF(U31="Open",L31*N31,0) -> 16180 | X31: =IF(U31="Open","",IFERROR(K31-B31,"")) | Y31: =IF(U31="Open",Lookups!$B$2-B31,X31) -> 19 | Z31: =IF(AND(U31="Open",Y31>30),"STALE","OK") -> OK | AA31: =TEXT(B31,"yyyy-mm") -> 2026-08 | AB31: =IF(K31="","",TEXT(K31,"yyyy-mm")) | AC31: ="Q"&ROUNDUP(MONTH(B31)/3,0)&"-"&YEAR(B31) -> Q3-2026 | AD31: =MIN(100,IF(H31="Enterprise",30,IF(H31="Mid-Market",22,14))+IF(T31="Enterprise",25,IF(T31="Mid-Market",18,10))+IF(Q31="Referral",25,IF(Q31="Organic Search",20,IF(Q31="Email",18,14)))+IF(G31="Technology",10,5)) -> 74 | AE31: =IF(U31<>"Open",U31,IF(N31>=0.8,"Commit",IF(N31>=0.5,"Best Case","Pipeline"))) -> Pipeline
A32: L00031 | B32: 45988 | C32: Duy Pham | D32: South | E32: email nurture | F32: MKT-AUTO | G32: Professional Services | H32: Mid-Market | I32: Closed Lost | J32: 46029 | K32: 46029 | L32: 21200 | M32: 0 | N32: 0 | O32: Timing | P32: 2 | Q32: =IFERROR(VLOOKUP(E32,Lookups!$A$5:$B$24,2,FALSE),"Other") -> Email | R32: =IFERROR(VLOOKUP(F32,Lookups!$D$5:$F$10,2,FALSE),"Unknown Product") -> Marketing Automation | S32: =IFERROR(VLOOKUP(F32,Lookups!$D$5:$F$10,3,FALSE),"Unknown") -> Marketing | T32: =IF(L32>=50000,"Enterprise",IF(L32>=20000,"Mid-Market","SMB")) -> Mid-Market | U32: =IF(I32="Closed Won","Won",IF(I32="Closed Lost","Lost","Open")) -> Lost | V32: =IF(U32="Won",L32*(1-M32),0) -> 0 | W32: =IF(U32="Open",L32*N32,0) -> 0 | X32: =IF(U32="Open","",IFERROR(K32-B32,"")) -> 41 | Y32: =IF(U32="Open",Lookups!$B$2-B32,X32) -> 41 | Z32: =IF(AND(U32="Open",Y32>30),"STALE","OK") -> OK | AA32: =TEXT(B32,"yyyy-mm") -> 2025-11 | AB32: =IF(K32="","",TEXT(K32,"yyyy-mm")) -> 2026-01 | AC32: ="Q"&ROUNDUP(MONTH(B32)/3,0)&"-"&YEAR(B32) -> Q4-2025 | AD32: =MIN(100,IF(H32="Enterprise",30,IF(H32="Mid-Market",22,14))+IF(T32="Enterprise",25,IF(T32="Mid-Market",18,10))+IF(Q32="Referral",25,IF(Q32="Organic Search",20,IF(Q32="Email",18,14)))+IF(G32="Technology",10,5)) -> 63 | AE32: =IF(U32<>"Open",U32,IF(N32>=0.8,"Commit",IF(N32>=0.5,"Best Case","Pipeline"))) -> Lost
A33: L00032 | B33: 46006 | C33: Ha Vo | D33: North | E33: google cpc | F33: CRM-CORE | G33: Professional Services | H33: Enterprise | I33: Negotiation | J33: 46185 | L33: 26900 | M33: 0.03 | N33: 0.85 | P33: 5 | Q33: =IFERROR(VLOOKUP(E33,Lookups!$A$5:$B$24,2,FALSE),"Other") -> Paid Search | R33: =IFERROR(VLOOKUP(F33,Lookups!$D$5:$F$10,2,FALSE),"Unknown Product") -> NexaCRM Core | S33: =IFERROR(VLOOKUP(F33,Lookups!$D$5:$F$10,3,FALSE),"Unknown") -> CRM | T33: =IF(L33>=50000,"Enterprise",IF(L33>=20000,"Mid-Market","SMB")) -> Mid-Market | U33: =IF(I33="Closed Won","Won",IF(I33="Closed Lost","Lost","Open")) -> Open | V33: =IF(U33="Won",L33*(1-M33),0) -> 0 | W33: =IF(U33="Open",L33*N33,0) -> 22865 | X33: =IF(U33="Open","",IFERROR(K33-B33,"")) | Y33: =IF(U33="Open",Lookups!$B$2-B33,X33) -> 260 | Z33: =IF(AND(U33="Open",Y33>30),"STALE","OK") -> STALE | AA33: =TEXT(B33,"yyyy-mm") -> 2025-12 | AB33: =IF(K33="","",TEXT(K33,"yyyy-mm")) | AC33: ="Q"&ROUNDUP(MONTH(B33)/3,0)&"-"&YEAR(B33) -> Q4-2025 | AD33: =MIN(100,IF(H33="Enterprise",30,IF(H33="Mid-Market",22,14))+IF(T33="Enterprise",25,IF(T33="Mid-Market",18,10))+IF(Q33="Referral",25,IF(Q33="Organic Search",20,IF(Q33="Email",18,14)))+IF(G33="Technology",10,5)) -> 67 | AE33: =IF(U33<>"Open",U33,IF(N33>=0.8,"Commit",IF(N33>=0.5,"Best Case","Pipeline"))) -> Commit
A34: L00033 | B34: 45810 | C34: Duy Pham | D34: South | E34: SEM - Google | F34: CRM-PRO | G34: Manufacturing | H34: SMB | I34: Closed Lost | J34: 45864 | K34: 45864 | L34: 12600 | M34: 0 | N34: 0 | O34: Timing | P34: 3 | Q34: =IFERROR(VLOOKUP(E34,Lookups!$A$5:$B$24,2,FALSE),"Other") -> Paid Search | R34: =IFERROR(VLOOKUP(F34,Lookups!$D$5:$F$10,2,FALSE),"Unknown Product") -> NexaCRM Pro | S34: =IFERROR(VLOOKUP(F34,Lookups!$D$5:$F$10,3,FALSE),"Unknown") -> CRM | T34: =IF(L34>=50000,"Enterprise",IF(L34>=20000,"Mid-Market","SMB")) -> SMB | U34: =IF(I34="Closed Won","Won",IF(I34="Closed Lost","Lost","Open")) -> Lost | V34: =IF(U34="Won",L34*(1-M34),0) -> 0 | W34: =IF(U34="Open",L34*N34,0) -> 0 | X34: =IF(U34="Open","",IFERROR(K34-B34,"")) -> 54 | Y34: =IF(U34="Open",Lookups!$B$2-B34,X34) -> 54 | Z34: =IF(AND(U34="Open",Y34>30),"STALE","OK") -> OK | AA34: =TEXT(B34,"yyyy-mm") -> 2025-06 | AB34: =IF(K34="","",TEXT(K34,"yyyy-mm")) -> 2025-07 | AC34: ="Q"&ROUNDUP(MONTH(B34)/3,0)&"-"&YEAR(B34) -> Q2-2025 | AD34: =MIN(100,IF(H34="Enterprise",30,IF(H34="Mid-Market",22,14))+IF(T34="Enterprise",25,IF(T34="Mid-Market",18,10))+IF(Q34="Referral",25,IF(Q34="Organic Search",20,IF(Q34="Email",18,14)))+IF(G34="Technology",10,5)) -> 43 | AE34: =IF(U34<>"Open",U34,IF(N34>=0.8,"Commit",IF(N34>=0.5,"Best Case","Pipeline"))) -> Lost
A35: L00034 | B35: 45773 | C35: An Nguyen | D35: South | E35: Referral | F35: REV-OPS | G35: Professional Services | H35: Mid-Market | I35: Closed Lost | J35: 45801 | K35: 45801 | L35: 48900 | M35: 0 | N35: 0 | O35: No Decision | P35: 4 | Q35: =IFERROR(VLOOKUP(E35,Lookups!$A$5:$B$24,2,FALSE),"Other") -> Referral | R35: =IFERROR(VLOOKUP(F35,Lookups!$D$5:$F$10,2,FALSE),"Unknown Product") -> Revenue Operations Suite | S35: =IFERROR(VLOOKUP(F35,Lookups!$D$5:$F$10,3,FALSE),"Unknown") -> Revenue Ops | T35: =IF(L35>=50000,"Enterprise",IF(L35>=20000,"Mid-Market","SMB")) -> Mid-Market | U35: =IF(I35="Closed Won","Won",IF(I35="Closed Lost","Lost","Open")) -> Lost | V35: =IF(U35="Won",L35*(1-M35),0) -> 0 | W35: =IF(U35="Open",L35*N35,0) -> 0 | X35: =IF(U35="Open","",IFERROR(K35-B35,"")) -> 28 | Y35: =IF(U35="Open",Lookups!$B$2-B35,X35) -> 28 | Z35: =IF(AND(U35="Open",Y35>30),"STALE","OK") -> OK | AA35: =TEXT(B35,"yyyy-mm") -> 2025-04 | AB35: =IF(K35="","",TEXT(K35,"yyyy-mm")) -> 2025-05 | AC35: ="Q"&ROUNDUP(MONTH(B35)/3,0)&"-"&YEAR(B35) -> Q2-2025 | AD35: =MIN(100,IF(H35="Enterprise",30,IF(H35="Mid-Market",22,14))+IF(T35="Enterprise",25,IF(T35="Mid-Market",18,10))+IF(Q35="Referral",25,IF(Q35="Organic Search",20,IF(Q35="Email",18,14)))+IF(G35="Technology",10,5)) -> 70 | AE35: =IF(U35<>"Open",U35,IF(N35>=0.8,"Commit",IF(N35>=0.5,"Best Case","Pipeline"))) -> Lost
A36: L00035 | B36: 45912 | C36: Duy Pham | D36: South | E36: customer referral | F36: MKT-AUTO | G36: Retail | H36: SMB | I36: Closed Won | J36: 45956 | K36: 45956 | L36: 12800 | M36: 0.08 | N36: 1 | P36: 6 | Q36: =IFERROR(VLOOKUP(E36,Lookups!$A$5:$B$24,2,FALSE),"Other") -> Referral | R36: =IFERROR(VLOOKUP(F36,Lookups!$D$5:$F$10,2,FALSE),"Unknown Product") -> Marketing Automation | S36: =IFERROR(VLOOKUP(F36,Lookups!$D$5:$F$10,3,FALSE),"Unknown") -> Marketing | T36: =IF(L36>=50000,"Enterprise",IF(L36>=20000,"Mid-Market","SMB")) -> SMB | U36: =IF(I36="Closed Won","Won",IF(I36="Closed Lost","Lost","Open")) -> Won | V36: =IF(U36="Won",L36*(1-M36),0) -> 11776 | W36: =IF(U36="Open",L36*N36,0) -> 0 | X36: =IF(U36="Open","",IFERROR(K36-B36,"")) -> 44 | Y36: =IF(U36="Open",Lookups!$B$2-B36,X36) -> 44 | Z36: =IF(AND(U36="Open",Y36>30),"STALE","OK") -> OK | AA36: =TEXT(B36,"yyyy-mm") -> 2025-09 | AB36: =IF(K36="","",TEXT(K36,"yyyy-mm")) -> 2025-10 | AC36: ="Q"&ROUNDUP(MONTH(B36)/3,0)&"-"&YEAR(B36) -> Q3-2025 | AD36: =MIN(100,IF(H36="Enterprise",30,IF(H36="Mid-Market",22,14))+IF(T36="Enterprise",25,IF(T36="Mid-Market",18,10))+IF(Q36="Referral",25,IF(Q36="Organic Search",20,IF(Q36="Email",18,14)))+IF(G36="Technology",10,5)) -> 54 | AE36: =IF(U36<>"Open",U36,IF(N36>=0.8,"Commit",IF(N36>=0.5,"Best Case","Pipeline"))) -> Won
A37: L00036 | B37: 45932 | C37: An Nguyen | D37: South | E37: Conference Scan | F37: BI-PLUS | G37: Retail | H37: Mid-Market | I37: Closed Won | J37: 45944 | K37: 45944 | L37: 43600 | M37: 0.03 | N37: 1 | P37: 6 | Q37: =IFERROR(VLOOKUP(E37,Lookups!$A$5:$B$24,2,FALSE),"Other") -> Other | R37: =IFERROR(VLOOKUP(F37,Lookups!$D$5:$F$10,2,FALSE),"Unknown Product") -> Analytics Plus | S37: =IFERROR(VLOOKUP(F37,Lookups!$D$5:$F$10,3,FALSE),"Unknown") -> Analytics | T37: =IF(L37>=50000,"Enterprise",IF(L37>=20000,"Mid-Market","SMB")) -> Mid-Market | U37: =IF(I37="Closed Won","Won",IF(I37="Closed Lost","Lost","Open")) -> Won | V37: =IF(U37="Won",L37*(1-M37),0) -> 42292 | W37: =IF(U37="Open",L37*N37,0) -> 0 | X37: =IF(U37="Open","",IFERROR(K37-B37,"")) -> 12 | Y37: =IF(U37="Open",Lookups!$B$2-B37,X37) -> 12 | Z37: =IF(AND(U37="Open",Y37>30),"STALE","OK") -> OK | AA37: =TEXT(B37,"yyyy-mm") -> 2025-10 | AB37: =IF(K37="","",TEXT(K37,"yyyy-mm")) -> 2025-10 | AC37: ="Q"&ROUNDUP(MONTH(B37)/3,0)&"-"&YEAR(B37) -> Q4-2025 | AD37: =MIN(100,IF(H37="Enterprise",30,IF(H37="Mid-Market",22,14))+IF(T37="Enterprise",25,IF(T37="Mid-Market",18,10))+IF(Q37="Referral",25,IF(Q37="Organic Search",20,IF(Q37="Email",18,14)))+IF(G37="Technology",10,5)) -> 59 | AE37: =IF(U37<>"Open",U37,IF(N37>=0.8,"Commit",IF(N37>=0.5,"Best Case","Pipeline"))) -> Won
A38: L00037 | B38: 46070 | C38: Quynh Vu | D38: North | E38: Google Ads | F38: MKT-AUTO | G38: Manufacturing | H38: Mid-Market | I38: Negotiation | J38: 46201 | L38: 36600 | M38: 0.05 | N38: 0.85 | P38: 5 | Q38: =IFERROR(VLOOKUP(E38,Lookups!$A$5:$B$24,2,FALSE),"Other") -> Paid Search | R38: =IFERROR(VLOOKUP(F38,Lookups!$D$5:$F$10,2,FALSE),"Unknown Product") -> Marketing Automation | S38: =IFERROR(VLOOKUP(F38,Lookups!$D$5:$F$10,3,FALSE),"Unknown") -> Marketing | T38: =IF(L38>=50000,"Enterprise",IF(L38>=20000,"Mid-Market","SMB")) -> Mid-Market | U38: =IF(I38="Closed Won","Won",IF(I38="Closed Lost","Lost","Open")) -> Open | V38: =IF(U38="Won",L38*(1-M38),0) -> 0 | W38: =IF(U38="Open",L38*N38,0) -> 31110 | X38: =IF(U38="Open","",IFERROR(K38-B38,"")) | Y38: =IF(U38="Open",Lookups!$B$2-B38,X38) -> 196 | Z38: =IF(AND(U38="Open",Y38>30),"STALE","OK") -> STALE | AA38: =TEXT(B38,"yyyy-mm") -> 2026-02 | AB38: =IF(K38="","",TEXT(K38,"yyyy-mm")) | AC38: ="Q"&ROUNDUP(MONTH(B38)/3,0)&"-"&YEAR(B38) -> Q1-2026 | AD38: =MIN(100,IF(H38="Enterprise",30,IF(H38="Mid-Market",22,14))+IF(T38="Enterprise",25,IF(T38="Mid-Market",18,10))+IF(Q38="Referral",25,IF(Q38="Organic Search",20,IF(Q38="Email",18,14)))+IF(G38="Technology",10,5)) -> 59 | AE38: =IF(U38<>"Open",U38,IF(N38>=0.8,"Commit",IF(N38>=0.5,"Best Case","Pipeline"))) -> Commit
A39: L00038 | B39: 46149 | C39: Tuan Bui | D39: Central | E39: customer referral | F39: CRM-CORE | G39: Healthcare | H39: Mid-Market | I39: Closed Lost | J39: 46210 | K39: 46210 | L39: 10800 | M39: 0 | N39: 0 | O39: No Decision | P39: 5 | Q39: =IFERROR(VLOOKUP(E39,Lookups!$A$5:$B$24,2,FALSE),"Other") -> Referral | R39: =IFERROR(VLOOKUP(F39,Lookups!$D$5:$F$10,2,FALSE),"Unknown Product") -> NexaCRM Core | S39: =IFERROR(VLOOKUP(F39,Lookups!$D$5:$F$10,3,FALSE),"Unknown") -> CRM | T39: =IF(L39>=50000,"Enterprise",IF(L39>=20000,"Mid-Market","SMB")) -> SMB | U39: =IF(I39="Closed Won","Won",IF(I39="Closed Lost","Lost","Open")) -> Lost | V39: =IF(U39="Won",L39*(1-M39),0) -> 0 | W39: =IF(U39="Open",L39*N39,0) -> 0 | X39: =IF(U39="Open","",IFERROR(K39-B39,"")) -> 61 | Y39: =IF(U39="Open",Lookups!$B$2-B39,X39) -> 61 | Z39: =IF(AND(U39="Open",Y39>30),"STALE","OK") -> OK | AA39: =TEXT(B39,"yyyy-mm") -> 2026-05 | AB39: =IF(K39="","",TEXT(K39,"yyyy-mm")) -> 2026-07 | AC39: ="Q"&ROUNDUP(MONTH(B39)/3,0)&"-"&YEAR(B39) -> Q2-2026 | AD39: =MIN(100,IF(H39="Enterprise",30,IF(H39="Mid-Market",22,14))+IF(T39="Enterprise",25,IF(T39="Mid-Market",18,10))+IF(Q39="Referral",25,IF(Q39="Organic Search",20,IF(Q39="Email",18,14)))+IF(G39="Technology",10,5)) -> 62 | AE39: =IF(U39<>"Open",U39,IF(N39>=0.8,"Commit",IF(N39>=0.5,"Best Case","Pipeline"))) -> Lost
A40: L00039 | B40: 45962 | C40: An Nguyen | D40: South | E40: LI Ads | F40: CRM-CORE | G40: Manufacturing | H40: SMB | I40: Closed Lost | J40: 45996 | K40: 45996 | L40: 4700 | M40: 0 | N40: 0 | O40: No Decision | P40: 4 | Q40: =IFERROR(VLOOKUP(E40,Lookups!$A$5:$B$24,2,FALSE),"Other") -> LinkedIn | R40: =IFERROR(VLOOKUP(F40,Lookups!$D$5:$F$10,2,FALSE),"Unknown Product") -> NexaCRM Core | S40: =IFERROR(VLOOKUP(F40,Lookups!$D$5:$F$10,3,FALSE),"Unknown") -> CRM | T40: =IF(L40>=50000,"Enterprise",IF(L40>=20000,"Mid-Market","SMB")) -> SMB | U40: =IF(I40="Closed Won","Won",IF(I40="Closed Lost","Lost","Open")) -> Lost | V40: =IF(U40="Won",L40*(1-M40),0) -> 0 | W40: =IF(U40="Open",L40*N40,0) -> 0 | X40: =IF(U40="Open","",IFERROR(K40-B40,"")) -> 34 | Y40: =IF(U40="Open",Lookups!$B$2-B40,X40) -> 34 | Z40: =IF(AND(U40="Open",Y40>30),"STALE","OK") -> OK | AA40: =TEXT(B40,"yyyy-mm") -> 2025-11 | AB40: =IF(K40="","",TEXT(K40,"yyyy-mm")) -> 2025-12 | AC40: ="Q"&ROUNDUP(MONTH(B40)/3,0)&"-"&YEAR(B40) -> Q4-2025 | AD40: =MIN(100,IF(H40="Enterprise",30,IF(H40="Mid-Market",22,14))+IF(T40="Enterprise",25,IF(T40="Mid-Market",18,10))+IF(Q40="Referral",25,IF(Q40="Organic Search",20,IF(Q40="Email",18,14)))+IF(G40="Technology",10,5)) -> 43 | AE40: =IF(U40<>"Open",U40,IF(N40>=0.8,"Commit",IF(N40>=0.5,"Best Case","Pipeline"))) -> Lost
A41: L00040 | B41: 46152 | C41: Bao Tran | D41: South | E41: SEO | F41: CRM-CORE | G41: Education | H41: SMB | I41: Closed Lost | J41: 46219 | K41: 46219 | L41: 4600 | M41: 0 | N41: 0 | O41: Price | P41: 3 | Q41: =IFERROR(VLOOKUP(E41,Lookups!$A$5:$B$24,2,FALSE),"Other") -> Organic Search | R41: =IFERROR(VLOOKUP(F41,Lookups!$D$5:$F$10,2,FALSE),"Unknown Product") -> NexaCRM Core | S41: =IFERROR(VLOOKUP(F41,Lookups!$D$5:$F$10,3,FALSE),"Unknown") -> CRM | T41: =IF(L41>=50000,"Enterprise",IF(L41>=20000,"Mid-Market","SMB")) -> SMB | U41: =IF(I41="Closed Won","Won",IF(I41="Closed Lost","Lost","Open")) -> Lost | V41: =IF(U41="Won",L41*(1-M41),0) -> 0 | W41: =IF(U41="Open",L41*N41,0) -> 0 | X41: =IF(U41="Open","",IFERROR(K41-B41,"")) -> 67 | Y41: =IF(U41="Open",Lookups!$B$2-B41,X41) -> 67 | Z41: =IF(AND(U41="Open",Y41>30),"STALE","OK") -> OK | AA41: =TEXT(B41,"yyyy-mm") -> 2026-05 | AB41: =IF(K41="","",TEXT(K41,"yyyy-mm")) -> 2026-07 | AC41: ="Q"&ROUNDUP(MONTH(B41)/3,0)&"-"&YEAR(B41) -> Q2-2026 | AD41: =MIN(100,IF(H41="Enterprise",30,IF(H41="Mid-Market",22,14))+IF(T41="Enterprise",25,IF(T41="Mid-Market",18,10))+IF(Q41="Referral",25,IF(Q41="Organic Search",20,IF(Q41="Email",18,14)))+IF(G41="Technology",10,5)) -> 49 | AE41: =IF(U41<>"Open",U41,IF(N41>=0.8,"Commit",IF(N41>=0.5,"Best Case","Pipeline"))) -> Lost
A42: L00041 | B42: 45954 | C42: Duy Pham | D42: South | E42: Cold Email | F42: CRM-CORE | G42: Retail | H42: Mid-Market | I42: Closed Won | J42: 46016 | K42: 46016 | L42: 13200 | M42: 0.08 | N42: 1 | P42: 6 | Q42: =IFERROR(VLOOKUP(E42,Lookups!$A$5:$B$24,2,FALSE),"Other") -> Outbound | R42: =IFERROR(VLOOKUP(F42,Lookups!$D$5:$F$10,2,FALSE),"Unknown Product") -> NexaCRM Core | S42: =IFERROR(VLOOKUP(F42,Lookups!$D$5:$F$10,3,FALSE),"Unknown") -> CRM | T42: =IF(L42>=50000,"Enterprise",IF(L42>=20000,"Mid-Market","SMB")) -> SMB | U42: =IF(I42="Closed Won","Won",IF(I42="Closed Lost","Lost","Open")) -> Won | V42: =IF(U42="Won",L42*(1-M42),0) -> 12144 | W42: =IF(U42="Open",L42*N42,0) -> 0 | X42: =IF(U42="Open","",IFERROR(K42-B42,"")) -> 62 | Y42: =IF(U42="Open",Lookups!$B$2-B42,X42) -> 62 | Z42: =IF(AND(U42="Open",Y42>30),"STALE","OK") -> OK | AA42: =TEXT(B42,"yyyy-mm") -> 2025-10 | AB42: =IF(K42="","",TEXT(K42,"yyyy-mm")) -> 2025-12 | AC42: ="Q"&ROUNDUP(MONTH(B42)/3,0)&"-"&YEAR(B42) -> Q4-2025 | AD42: =MIN(100,IF(H42="Enterprise",30,IF(H42="Mid-Market",22,14))+IF(T42="Enterprise",25,IF(T42="Mid-Market",18,10))+IF(Q42="Referral",25,IF(Q42="Organic Search",20,IF(Q42="Email",18,14)))+IF(G42="Technology",10,5)) -> 51 | AE42: =IF(U42<>"Open",U42,IF(N42>=0.8,"Commit",IF(N42>=0.5,"Best Case","Pipeline"))) -> Won
A43: L00042 | B43: 46221 | C43: Ha Vo | D43: North | E43: organic search | F43: CRM-PRO | G43: Retail | H43: Mid-Market | I43: Demo / Meeting | J43: 46252 | L43: 38800 | M43: 0 | N43: 0.4 | P43: 3 | Q43: =IFERROR(VLOOKUP(E43,Lookups!$A$5:$B$24,2,FALSE),"Other") -> Organic Search | R43: =IFERROR(VLOOKUP(F43,Lookups!$D$5:$F$10,2,FALSE),"Unknown Product") -> NexaCRM Pro | S43: =IFERROR(VLOOKUP(F43,Lookups!$D$5:$F$10,3,FALSE),"Unknown") -> CRM | T43: =IF(L43>=50000,"Enterprise",IF(L43>=20000,"Mid-Market","SMB")) -> Mid-Market | U43: =IF(I43="Closed Won","Won",IF(I43="Closed Lost","Lost","Open")) -> Open | V43: =IF(U43="Won",L43*(1-M43),0) -> 0 | W43: =IF(U43="Open",L43*N43,0) -> 15520 | X43: =IF(U43="Open","",IFERROR(K43-B43,"")) | Y43: =IF(U43="Open",Lookups!$B$2-B43,X43) -> 45 | Z43: =IF(AND(U43="Open",Y43>30),"STALE","OK") -> STALE | AA43: =TEXT(B43,"yyyy-mm") -> 2026-07 | AB43: =IF(K43="","",TEXT(K43,"yyyy-mm")) | AC43: ="Q"&ROUNDUP(MONTH(B43)/3,0)&"-"&YEAR(B43) -> Q3-2026 | AD43: =MIN(100,IF(H43="Enterprise",30,IF(H43="Mid-Market",22,14))+IF(T43="Enterprise",25,IF(T43="Mid-Market",18,10))+IF(Q43="Referral",25,IF(Q43="Organic Search",20,IF(Q43="Email",18,14)))+IF(G43="Technology",10,5)) -> 65 | AE43: =IF(U43<>"Open",U43,IF(N43>=0.8,"Commit",IF(N43>=0.5,"Best Case","Pipeline"))) -> Pipeline
A44: L00043 | B44: 46129 | C44: Tuan Bui | D44: Central | E44: SEM - Google | F44: CRM-PRO | G44: Professional Services | H44: SMB | I44: Closed Lost | J44: 46179 | K44: 46179 | L44: 24800 | M44: 0 | N44: 0 | O44: Budget | P44: 2 | Q44: =IFERROR(VLOOKUP(E44,Lookups!$A$5:$B$24,2,FALSE),"Other") -> Paid Search | R44: =IFERROR(VLOOKUP(F44,Lookups!$D$5:$F$10,2,FALSE),"Unknown Product") -> NexaCRM Pro | S44: =IFERROR(VLOOKUP(F44,Lookups!$D$5:$F$10,3,FALSE),"Unknown") -> CRM | T44: =IF(L44>=50000,"Enterprise",IF(L44>=20000,"Mid-Market","SMB")) -> Mid-Market | U44: =IF(I44="Closed Won","Won",IF(I44="Closed Lost","Lost","Open")) -> Lost | V44: =IF(U44="Won",L44*(1-M44),0) -> 0 | W44: =IF(U44="Open",L44*N44,0) -> 0 | X44: =IF(U44="Open","",IFERROR(K44-B44,"")) -> 50 | Y44: =IF(U44="Open",Lookups!$B$2-B44,X44) -> 50 | Z44: =IF(AND(U44="Open",Y44>30),"STALE","OK") -> OK | AA44: =TEXT(B44,"yyyy-mm") -> 2026-04 | AB44: =IF(K44="","",TEXT(K44,"yyyy-mm")) -> 2026-06 | AC44: ="Q"&ROUNDUP(MONTH(B44)/3,0)&"-"&YEAR(B44) -> Q2-2026 | AD44: =MIN(100,IF(H44="Enterprise",30,IF(H44="Mid-Market",22,14))+IF(T44="Enterprise",25,IF(T44="Mid-Market",18,10))+IF(Q44="Referral",25,IF(Q44="Organic Search",20,IF(Q44="Email",18,14)))+IF(G44="Technology",10,5)) -> 51 | AE44: =IF(U44<>"Open",U44,IF(N44>=0.8,"Commit",IF(N44>=0.5,"Best Case","Pipeline"))) -> Lost
A45: L00044 | B45: 46024 | C45: Bao Tran | D45: South | E45: Google Ads | F45: CS-CLOUD | G45: Manufacturing | H45: SMB | I45: Closed Lost | J45: 46080 | K45: 46080 | L45: 14900 | M45: 0 | N45: 0 | O45: Budget | P45: 5 | Q45: =IFERROR(VLOOKUP(E45,Lookups!$A$5:$B$24,2,FALSE),"Other") -> Paid Search | R45: =IFERROR(VLOOKUP(F45,Lookups!$D$5:$F$10,2,FALSE),"Unknown Product") -> Service Cloud | S45: =IFERROR(VLOOKUP(F45,Lookups!$D$5:$F$10,3,FALSE),"Unknown") -> Customer Service | T45: =IF(L45>=50000,"Enterprise",IF(L45>=20000,"Mid-Market","SMB")) -> SMB | U45: =IF(I45="Closed Won","Won",IF(I45="Closed Lost","Lost","Open")) -> Lost | V45: =IF(U45="Won",L45*(1-M45),0) -> 0 | W45: =IF(U45="Open",L45*N45,0) -> 0 | X45: =IF(U45="Open","",IFERROR(K45-B45,"")) -> 56 | Y45: =IF(U45="Open",Lookups!$B$2-B45,X45) -> 56 | Z45: =IF(AND(U45="Open",Y45>30),"STALE","OK") -> OK | AA45: =TEXT(B45,"yyyy-mm") -> 2026-01 | AB45: =IF(K45="","",TEXT(K45,"yyyy-mm")) -> 2026-02 | AC45: ="Q"&ROUNDUP(MONTH(B45)/3,0)&"-"&YEAR(B45) -> Q1-2026 | AD45: =MIN(100,IF(H45="Enterprise",30,IF(H45="Mid-Market",22,14))+IF(T45="Enterprise",25,IF(T45="Mid-Market",18,10))+IF(Q45="Referral",25,IF(Q45="Organic Search",20,IF(Q45="Email",18,14)))+IF(G45="Technology",10,5)) -> 43 | AE45: =IF(U45<>"Open",U45,IF(N45>=0.8,"Commit",IF(N45>=0.5,"Best Case","Pipeline"))) -> Lost
A46: L00045 | B46: 45957 | C46: Quynh Vu | D46: North | E46: LI Ads | F46: CRM-CORE | G46: Professional Services | H46: SMB | I46: Closed Won | J46: 45987 | K46: 45987 | L46: 8000 | M46: 0.08 | N46: 1 | P46: 6 | Q46: =IFERROR(VLOOKUP(E46,Lookups!$A$5:$B$24,2,FALSE),"Other") -> LinkedIn | R46: =IFERROR(VLOOKUP(F46,Lookups!$D$5:$F$10,2,FALSE),"Unknown Product") -> NexaCRM Core | S46: =IFERROR(VLOOKUP(F46,Lookups!$D$5:$F$10,3,FALSE),"Unknown") -> CRM | T46: =IF(L46>=50000,"Enterprise",IF(L46>=20000,"Mid-Market","SMB")) -> SMB | U46: =IF(I46="Closed Won","Won",IF(I46="Closed Lost","Lost","Open")) -> Won | V46: =IF(U46="Won",L46*(1-M46),0) -> 7360 | W46: =IF(U46="Open",L46*N46,0) -> 0 | X46: =IF(U46="Open","",IFERROR(K46-B46,"")) -> 30 | Y46: =IF(U46="Open",Lookups!$B$2-B46,X46) -> 30 | Z46: =IF(AND(U46="Open",Y46>30),"STALE","OK") -> OK | AA46: =TEXT(B46,"yyyy-mm") -> 2025-10 | AB46: =IF(K46="","",TEXT(K46,"yyyy-mm")) -> 2025-11 | AC46: ="Q"&ROUNDUP(MONTH(B46)/3,0)&"-"&YEAR(B46) -> Q4-2025 | AD46: =MIN(100,IF(H46="Enterprise",30,IF(H46="Mid-Market",22,14))+IF(T46="Enterprise",25,IF(T46="Mid-Market",18,10))+IF(Q46="Referral",25,IF(Q46="Organic Search",20,IF(Q46="Email",18,14)))+IF(G46="Technology",10,5)) -> 43 | AE46: =IF(U46<>"Open",U46,IF(N46>=0.8,"Commit",IF(N46>=0.5,"Best Case","Pipeline"))) -> Won
A47: L00046 | B47: 45698 | C47: Quynh Vu | D47: North | E47: organic search | F47: REV-OPS | G47: Technology | H47: SMB | I47: Closed Lost | J47: 45719 | K47: 45719 | L47: 39100 | M47: 0 | N47: 0 | O47: No Decision | P47: 3 | Q47: =IFERROR(VLOOKUP(E47,Lookups!$A$5:$B$24,2,FALSE),"Other") -> Organic Search | R47: =IFERROR(VLOOKUP(F47,Lookups!$D$5:$F$10,2,FALSE),"Unknown Product") -> Revenue Operations Suite | S47: =IFERROR(VLOOKUP(F47,Lookups!$D$5:$F$10,3,FALSE),"Unknown") -> Revenue Ops | T47: =IF(L47>=50000,"Enterprise",IF(L47>=20000,"Mid-Market","SMB")) -> Mid-Market | U47: =IF(I47="Closed Won","Won",IF(I47="Closed Lost","Lost","Open")) -> Lost | V47: =IF(U47="Won",L47*(1-M47),0) -> 0 | W47: =IF(U47="Open",L47*N47,0) -> 0 | X47: =IF(U47="Open","",IFERROR(K47-B47,"")) -> 21 | Y47: =IF(U47="Open",Lookups!$B$2-B47,X47) -> 21 | Z47: =IF(AND(U47="Open",Y47>30),"STALE","OK") -> OK | AA47: =TEXT(B47,"yyyy-mm") -> 2025-02 | AB47: =IF(K47="","",TEXT(K47,"yyyy-mm")) -> 2025-03 | AC47: ="Q"&ROUNDUP(MONTH(B47)/3,0)&"-"&YEAR(B47) -> Q1-2025 | AD47: =MIN(100,IF(H47="Enterprise",30,IF(H47="Mid-Market",22,14))+IF(T47="Enterprise",25,IF(T47="Mid-Market",18,10))+IF(Q47="Referral",25,IF(Q47="Organic Search",20,IF(Q47="Email",18,14)))+IF(G47="Technology",10,5)) -> 62 | AE47: =IF(U47<>"Open",U47,IF(N47>=0.8,"Commit",IF(N47>=0.5,"Best Case","Pipeline"))) -> Lost
A48: L00047 | B48: 46036 | C48: An Nguyen | D48: South | E48: LinkedIn Ads | F48: CRM-CORE | G48: Healthcare | H48: Mid-Market | I48: Closed Won | J48: 46081 | K48: 46081 | L48: 18000 | M48: 0.12 | N48: 1 | P48: 6 | Q48: =IFERROR(VLOOKUP(E48,Lookups!$A$5:$B$24,2,FALSE),"Other") -> LinkedIn | R48: =IFERROR(VLOOKUP(F48,Lookups!$D$5:$F$10,2,FALSE),"Unknown Product") -> NexaCRM Core | S48: =IFERROR(VLOOKUP(F48,Lookups!$D$5:$F$10,3,FALSE),"Unknown") -> CRM | T48: =IF(L48>=50000,"Enterprise",IF(L48>=20000,"Mid-Market","SMB")) -> SMB | U48: =IF(I48="Closed Won","Won",IF(I48="Closed Lost","Lost","Open")) -> Won | V48: =IF(U48="Won",L48*(1-M48),0) -> 15840 | W48: =IF(U48="Open",L48*N48,0) -> 0 | X48: =IF(U48="Open","",IFERROR(K48-B48,"")) -> 45 | Y48: =IF(U48="Open",Lookups!$B$2-B48,X48) -> 45 | Z48: =IF(AND(U48="Open",Y48>30),"STALE","OK") -> OK | AA48: =TEXT(B48,"yyyy-mm") -> 2026-01 | AB48: =IF(K48="","",TEXT(K48,"yyyy-mm")) -> 2026-02 | AC48: ="Q"&ROUNDUP(MONTH(B48)/3,0)&"-"&YEAR(B48) -> Q1-2026 | AD48: =MIN(100,IF(H48="Enterprise",30,IF(H48="Mid-Market",22,14))+IF(T48="Enterprise",25,IF(T48="Mid-Market",18,10))+IF(Q48="Referral",25,IF(Q48="Organic Search",20,IF(Q48="Email",18,14)))+IF(G48="Technology",10,5)) -> 51 | AE48: =IF(U48<>"Open",U48,IF(N48>=0.8,"Commit",IF(N48>=0.5,"Best Case","Pipeline"))) -> Won
A49: L00048 | B49: 45857 | C49: Minh Do | D49: North | E49: LinkedIn Ads | F49: CRM-CORE | G49: Financial Services | H49: SMB | I49: Closed Lost | J49: 45915 | K49: 45915 | L49: 8200 | M49: 0 | N49: 0 | O49: Price | P49: 2 | Q49: =IFERROR(VLOOKUP(E49,Lookups!$A$5:$B$24,2,FALSE),"Other") -> LinkedIn | R49: =IFERROR(VLOOKUP(F49,Lookups!$D$5:$F$10,2,FALSE),"Unknown Product") -> NexaCRM Core | S49: =IFERROR(VLOOKUP(F49,Lookups!$D$5:$F$10,3,FALSE),"Unknown") -> CRM | T49: =IF(L49>=50000,"Enterprise",IF(L49>=20000,"Mid-Market","SMB")) -> SMB | U49: =IF(I49="Closed Won","Won",IF(I49="Closed Lost","Lost","Open")) -> Lost | V49: =IF(U49="Won",L49*(1-M49),0) -> 0 | W49: =IF(U49="Open",L49*N49,0) -> 0 | X49: =IF(U49="Open","",IFERROR(K49-B49,"")) -> 58 | Y49: =IF(U49="Open",Lookups!$B$2-B49,X49) -> 58 | Z49: =IF(AND(U49="Open",Y49>30),"STALE","OK") -> OK | AA49: =TEXT(B49,"yyyy-mm") -> 2025-07 | AB49: =IF(K49="","",TEXT(K49,"yyyy-mm")) -> 2025-09 | AC49: ="Q"&ROUNDUP(MONTH(B49)/3,0)&"-"&YEAR(B49) -> Q3-2025 | AD49: =MIN(100,IF(H49="Enterprise",30,IF(H49="Mid-Market",22,14))+IF(T49="Enterprise",25,IF(T49="Mid-Market",18,10))+IF(Q49="Referral",25,IF(Q49="Organic Search",20,IF(Q49="Email",18,14)))+IF(G49="Technology",10,5)) -> 43 | AE49: =IF(U49<>"Open",U49,IF(N49>=0.8,"Commit",IF(N49>=0.5,"Best Case","Pipeline"))) -> Lost
A50: L00049 | B50: 45681 | C50: Bao Tran | D50: South | E50: newsletter | F50: MKT-AUTO | G50: Manufacturing | H50: SMB | I50: Closed Lost | J50: 45743 | K50: 45743 | L50: 11000 | M50: 0 | N50: 0 | O50: Budget | P50: 3 | Q50: =IFERROR(VLOOKUP(E50,Lookups!$A$5:$B$24,2,FALSE),"Other") -> Email | R50: =IFERROR(VLOOKUP(F50,Lookups!$D$5:$F$10,2,FALSE),"Unknown Product") -> Marketing Automation | S50: =IFERROR(VLOOKUP(F50,Lookups!$D$5:$F$10,3,FALSE),"Unknown") -> Marketing | T50: =IF(L50>=50000,"Enterprise",IF(L50>=20000,"Mid-Market","SMB")) -> SMB | U50: =IF(I50="Closed Won","Won",IF(I50="Closed Lost","Lost","Open")) -> Lost | V50: =IF(U50="Won",L50*(1-M50),0) -> 0 | W50: =IF(U50="Open",L50*N50,0) -> 0 | X50: =IF(U50="Open","",IFERROR(K50-B50,"")) -> 62 | Y50: =IF(U50="Open",Lookups!$B$2-B50,X50) -> 62 | Z50: =IF(AND(U50="Open",Y50>30),"STALE","OK") -> OK | AA50: =TEXT(B50,"yyyy-mm") -> 2025-01 | AB50: =IF(K50="","",TEXT(K50,"yyyy-mm")) -> 2025-03 | AC50: ="Q"&ROUNDUP(MONTH(B50)/3,0)&"-"&YEAR(B50) -> Q1-2025 | AD50: =MIN(100,IF(H50="Enterprise",30,IF(H50="Mid-Market",22,14))+IF(T50="Enterprise",25,IF(T50="Mid-Market",18,10))+IF(Q50="Referral",25,IF(Q50="Organic Search",20,IF(Q50="Email",18,14)))+IF(G50="Technology",10,5)) -> 47 | AE50: =IF(U50<>"Open",U50,IF(N50>=0.8,"Commit",IF(N50>=0.5,"Best Case","Pipeline"))) -> Lost
A51: L00050 | B51: 46160 | C51: Ha Vo | D51: North | E51: LI Ads | F51: BI-PLUS | G51: Retail | H51: Mid-Market | I51: Demo / Meeting | J51: 46206 | L51: 48300 | M51: 0 | N51: 0.4 | P51: 3 | Q51: =IFERROR(VLOOKUP(E51,Lookups!$A$5:$B$24,2,FALSE),"Other") -> LinkedIn | R51: =IFERROR(VLOOKUP(F51,Lookups!$D$5:$F$10,2,FALSE),"Unknown Product") -> Analytics Plus | S51: =IFERROR(VLOOKUP(F51,Lookups!$D$5:$F$10,3,FALSE),"Unknown") -> Analytics | T51: =IF(L51>=50000,"Enterprise",IF(L51>=20000,"Mid-Market","SMB")) -> Mid-Market | U51: =IF(I51="Closed Won","Won",IF(I51="Closed Lost","Lost","Open")) -> Open | V51: =IF(U51="Won",L51*(1-M51),0) -> 0 | W51: =IF(U51="Open",L51*N51,0) -> 19320 | X51: =IF(U51="Open","",IFERROR(K51-B51,"")) | Y51: =IF(U51="Open",Lookups!$B$2-B51,X51) -> 106 | Z51: =IF(AND(U51="Open",Y51>30),"STALE","OK") -> STALE | AA51: =TEXT(B51,"yyyy-mm") -> 2026-05 | AB51: =IF(K51="","",TEXT(K51,"yyyy-mm")) | AC51: ="Q"&ROUNDUP(MONTH(B51)/3,0)&"-"&YEAR(B51) -> Q2-2026 | AD51: =MIN(100,IF(H51="Enterprise",30,IF(H51="Mid-Market",22,14))+IF(T51="Enterprise",25,IF(T51="Mid-Market",18,10))+IF(Q51="Referral",25,IF(Q51="Organic Search",20,IF(Q51="Email",18,14)))+IF(G51="Technology",10,5)) -> 59 | AE51: =IF(U51<>"Open",U51,IF(N51>=0.8,"Commit",IF(N51>=0.5,"Best Case","Pipeline"))) -> Pipeline
A52: L00051 | B52: 45706 | C52: Chi Le | D52: South | E52: Google Ads | F52: MKT-AUTO | G52: Technology | H52: SMB | I52: Closed Won | J52: 45761 | K52: 45761 | L52: 13900 | M52: 0.1 | N52: 1 | P52: 6 | Q52: =IFERROR(VLOOKUP(E52,Lookups!$A$5:$B$24,2,FALSE),"Other") -> Paid Search | R52: =IFERROR(VLOOKUP(F52,Lookups!$D$5:$F$10,2,FALSE),"Unknown Product") -> Marketing Automation | S52: =IFERROR(VLOOKUP(F52,Lookups!$D$5:$F$10,3,FALSE),"Unknown") -> Marketing | T52: =IF(L52>=50000,"Enterprise",IF(L52>=20000,"Mid-Market","SMB")) -> SMB | U52: =IF(I52="Closed Won","Won",IF(I52="Closed Lost","Lost","Open")) -> Won | V52: =IF(U52="Won",L52*(1-M52),0) -> 12510 | W52: =IF(U52="Open",L52*N52,0) -> 0 | X52: =IF(U52="Open","",IFERROR(K52-B52,"")) -> 55 | Y52: =IF(U52="Open",Lookups!$B$2-B52,X52) -> 55 | Z52: =IF(AND(U52="Open",Y52>30),"STALE","OK") -> OK | AA52: =TEXT(B52,"yyyy-mm") -> 2025-02 | AB52: =IF(K52="","",TEXT(K52,"yyyy-mm")) -> 2025-04 | AC52: ="Q"&ROUNDUP(MONTH(B52)/3,0)&"-"&YEAR(B52) -> Q1-2025 | AD52: =MIN(100,IF(H52="Enterprise",30,IF(H52="Mid-Market",22,14))+IF(T52="Enterprise",25,IF(T52="Mid-Market",18,10))+IF(Q52="Referral",25,IF(Q52="Organic Search",20,IF(Q52="Email",18,14)))+IF(G52="Technology",10,5)) -> 48 | AE52: =IF(U52<>"Open",U52,IF(N52>=0.8,"Commit",IF(N52>=0.5,"Best Case","Pipeline"))) -> Won
A53: L00052 | B53: 45701 | C53: An Nguyen | D53: South | E53: SDR Outreach | F53: MKT-AUTO | G53: Professional Services | H53: SMB | I53: Closed Lost | J53: 45756 | K53: 45756 | L53: 12400 | M53: 0 | N53: 0 | O53: Competitor | P53: 3 | Q53: =IFERROR(VLOOKUP(E53,Lookups!$A$5:$B$24,2,FALSE),"Other") -> Outbound | R53: =IFERROR(VLOOKUP(F53,Lookups!$D$5:$F$10,2,FALSE),"Unknown Product") -> Marketing Automation | S53: =IFERROR(VLOOKUP(F53,Lookups!$D$5:$F$10,3,FALSE),"Unknown") -> Marketing | T53: =IF(L53>=50000,"Enterprise",IF(L53>=20000,"Mid-Market","SMB")) -> SMB | U53: =IF(I53="Closed Won","Won",IF(I53="Closed Lost","Lost","Open")) -> Lost | V53: =IF(U53="Won",L53*(1-M53),0) -> 0 | W53: =IF(U53="Open",L53*N53,0) -> 0 | X53: =IF(U53="Open","",IFERROR(K53-B53,"")) -> 55 | Y53: =IF(U53="Open",Lookups!$B$2-B53,X53) -> 55 | Z53: =IF(AND(U53="Open",Y53>30),"STALE","OK") -> OK | AA53: =TEXT(B53,"yyyy-mm") -> 2025-02 | AB53: =IF(K53="","",TEXT(K53,"yyyy-mm")) -> 2025-04 | AC53: ="Q"&ROUNDUP(MONTH(B53)/3,0)&"-"&YEAR(B53) -> Q1-2025 | AD53: =MIN(100,IF(H53="Enterprise",30,IF(H53="Mid-Market",22,14))+IF(T53="Enterprise",25,IF(T53="Mid-Market",18,10))+IF(Q53="Referral",25,IF(Q53="Organic Search",20,IF(Q53="Email",18,14)))+IF(G53="Technology",10,5)) -> 43 | AE53: =IF(U53<>"Open",U53,IF(N53>=0.8,"Commit",IF(N53>=0.5,"Best Case","Pipeline"))) -> Lost
A54: L00053 | B54: 46055 | C54: An Nguyen | D54: South | E54: SEO | F54: CRM-PRO | G54: Technology | H54: SMB | I54: Closed Won | J54: 46173 | K54: 46173 | L54: 15500 | M54: 0.1 | N54: 1 | P54: 6 | Q54: =IFERROR(VLOOKUP(E54,Lookups!$A$5:$B$24,2,FALSE),"Other") -> Organic Search | R54: =IFERROR(VLOOKUP(F54,Lookups!$D$5:$F$10,2,FALSE),"Unknown Product") -> NexaCRM Pro | S54: =IFERROR(VLOOKUP(F54,Lookups!$D$5:$F$10,3,FALSE),"Unknown") -> CRM | T54: =IF(L54>=50000,"Enterprise",IF(L54>=20000,"Mid-Market","SMB")) -> SMB | U54: =IF(I54="Closed Won","Won",IF(I54="Closed Lost","Lost","Open")) -> Won | V54: =IF(U54="Won",L54*(1-M54),0) -> 13950 | W54: =IF(U54="Open",L54*N54,0) -> 0 | X54: =IF(U54="Open","",IFERROR(K54-B54,"")) -> 118 | Y54: =IF(U54="Open",Lookups!$B$2-B54,X54) -> 118 | Z54: =IF(AND(U54="Open",Y54>30),"STALE","OK") -> OK | AA54: =TEXT(B54,"yyyy-mm") -> 2026-02 | AB54: =IF(K54="","",TEXT(K54,"yyyy-mm")) -> 2026-05 | AC54: ="Q"&ROUNDUP(MONTH(B54)/3,0)&"-"&YEAR(B54) -> Q1-2026 | AD54: =MIN(100,IF(H54="Enterprise",30,IF(H54="Mid-Market",22,14))+IF(T54="Enterprise",25,IF(T54="Mid-Market",18,10))+IF(Q54="Referral",25,IF(Q54="Organic Search",20,IF(Q54="Email",18,14)))+IF(G54="Technology",10,5)) -> 54 | AE54: =IF(U54<>"Open",U54,IF(N54>=0.8,"Commit",IF(N54>=0.5,"Best Case","Pipeline"))) -> Won
A55: L00054 | B55: 46149 | C55: Bao Tran | D55: South | E55: linkedin | F55: CRM-PRO | G55: Retail | H55: SMB | I55: Demo / Meeting | J55: 46235 | L55: 20200 | M55: 0 | N55: 0.4 | P55: 3 | Q55: =IFERROR(VLOOKUP(E55,Lookups!$A$5:$B$24,2,FALSE),"Other") -> LinkedIn | R55: =IFERROR(VLOOKUP(F55,Lookups!$D$5:$F$10,2,FALSE),"Unknown Product") -> NexaCRM Pro | S55: =IFERROR(VLOOKUP(F55,Lookups!$D$5:$F$10,3,FALSE),"Unknown") -> CRM | T55: =IF(L55>=50000,"Enterprise",IF(L55>=20000,"Mid-Market","SMB")) -> Mid-Market | U55: =IF(I55="Closed Won","Won",IF(I55="Closed Lost","Lost","Open")) -> Open | V55: =IF(U55="Won",L55*(1-M55),0) -> 0 | W55: =IF(U55="Open",L55*N55,0) -> 8080 | X55: =IF(U55="Open","",IFERROR(K55-B55,"")) | Y55: =IF(U55="Open",Lookups!$B$2-B55,X55) -> 117 | Z55: =IF(AND(U55="Open",Y55>30),"STALE","OK") -> STALE | AA55: =TEXT(B55,"yyyy-mm") -> 2026-05 | AB55: =IF(K55="","",TEXT(K55,"yyyy-mm")) | AC55: ="Q"&ROUNDUP(MONTH(B55)/3,0)&"-"&YEAR(B55) -> Q2-2026 | AD55: =MIN(100,IF(H55="Enterprise",30,IF(H55="Mid-Market",22,14))+IF(T55="Enterprise",25,IF(T55="Mid-Market",18,10))+IF(Q55="Referral",25,IF(Q55="Organic Search",20,IF(Q55="Email",18,14)))+IF(G55="Technology",10,5)) -> 51 | AE55: =IF(U55<>"Open",U55,IF(N55>=0.8,"Commit",IF(N55>=0.5,"Best Case","Pipeline"))) -> Pipeline
A56: L00055 | B56: 45899 | C56: Duy Pham | D56: South | E56: SEO | F56: CS-CLOUD | G56: Technology | H56: Enterprise | I56: Negotiation | J56: 46162 | L56: 65000 | M56: 0 | N56: 0.85 | P56: 5 | Q56: =IFERROR(VLOOKUP(E56,Lookups!$A$5:$B$24,2,FALSE),"Other") -> Organic Search | R56: =IFERROR(VLOOKUP(F56,Lookups!$D$5:$F$10,2,FALSE),"Unknown Product") -> Service Cloud | S56: =IFERROR(VLOOKUP(F56,Lookups!$D$5:$F$10,3,FALSE),"Unknown") -> Customer Service | T56: =IF(L56>=50000,"Enterprise",IF(L56>=20000,"Mid-Market","SMB")) -> Enterprise | U56: =IF(I56="Closed Won","Won",IF(I56="Closed Lost","Lost","Open")) -> Open | V56: =IF(U56="Won",L56*(1-M56),0) -> 0 | W56: =IF(U56="Open",L56*N56,0) -> 55250 | X56: =IF(U56="Open","",IFERROR(K56-B56,"")) | Y56: =IF(U56="Open",Lookups!$B$2-B56,X56) -> 367 | Z56: =IF(AND(U56="Open",Y56>30),"STALE","OK") -> STALE | AA56: =TEXT(B56,"yyyy-mm") -> 2025-08 | AB56: =IF(K56="","",TEXT(K56,"yyyy-mm")) | AC56: ="Q"&ROUNDUP(MONTH(B56)/3,0)&"-"&YEAR(B56) -> Q3-2025 | AD56: =MIN(100,IF(H56="Enterprise",30,IF(H56="Mid-Market",22,14))+IF(T56="Enterprise",25,IF(T56="Mid-Market",18,10))+IF(Q56="Referral",25,IF(Q56="Organic Search",20,IF(Q56="Email",18,14)))+IF(G56="Technology",10,5)) -> 85 | AE56: =IF(U56<>"Open",U56,IF(N56>=0.8,"Commit",IF(N56>=0.5,"Best Case","Pipeline"))) -> Commit
A57: L00056 | B57: 46077 | C57: Ha Vo | D57: North | E57: linkedin | F57: REV-OPS | G57: Manufacturing | H57: Enterprise | I57: Closed Lost | J57: 46138 | K57: 46138 | L57: 119000 | M57: 0 | N57: 0 | O57: Feature Gap | P57: 4 | Q57: =IFERROR(VLOOKUP(E57,Lookups!$A$5:$B$24,2,FALSE),"Other") -> LinkedIn | R57: =IFERROR(VLOOKUP(F57,Lookups!$D$5:$F$10,2,FALSE),"Unknown Product") -> Revenue Operations Suite | S57: =IFERROR(VLOOKUP(F57,Lookups!$D$5:$F$10,3,FALSE),"Unknown") -> Revenue Ops | T57: =IF(L57>=50000,"Enterprise",IF(L57>=20000,"Mid-Market","SMB")) -> Enterprise | U57: =IF(I57="Closed Won","Won",IF(I57="Closed Lost","Lost","Open")) -> Lost | V57: =IF(U57="Won",L57*(1-M57),0) -> 0 | W57: =IF(U57="Open",L57*N57,0) -> 0 | X57: =IF(U57="Open","",IFERROR(K57-B57,"")) -> 61 | Y57: =IF(U57="Open",Lookups!$B$2-B57,X57) -> 61 | Z57: =IF(AND(U57="Open",Y57>30),"STALE","OK") -> OK | AA57: =TEXT(B57,"yyyy-mm") -> 2026-02 | AB57: =IF(K57="","",TEXT(K57,"yyyy-mm")) -> 2026-04 | AC57: ="Q"&ROUNDUP(MONTH(B57)/3,0)&"-"&YEAR(B57) -> Q1-2026 | AD57: =MIN(100,IF(H57="Enterprise",30,IF(H57="Mid-Market",22,14))+IF(T57="Enterprise",25,IF(T57="Mid-Market",18,10))+IF(Q57="Referral",25,IF(Q57="Organic Search",20,IF(Q57="Email",18,14)))+IF(G57="Technology",10,5)) -> 74 | AE57: =IF(U57<>"Open",U57,IF(N57>=0.8,"Commit",IF(N57>=0.5,"Best Case","Pipeline"))) -> Lost
A58: L00057 | B58: 45711 | C58: Bao Tran | D58: South | E58: SEO | F58: CRM-CORE | G58: Retail | H58: Mid-Market | I58: Closed Lost | J58: 45743 | K58: 45743 | L58: 14300 | M58: 0 | N58: 0 | O58: Timing | P58: 3 | Q58: =IFERROR(VLOOKUP(E58,Lookups!$A$5:$B$24,2,FALSE),"Other") -> Organic Search | R58: =IFERROR(VLOOKUP(F58,Lookups!$D$5:$F$10,2,FALSE),"Unknown Product") -> NexaCRM Core | S58: =IFERROR(VLOOKUP(F58,Lookups!$D$5:$F$10,3,FALSE),"Unknown") -> CRM | T58: =IF(L58>=50000,"Enterprise",IF(L58>=20000,"Mid-Market","SMB")) -> SMB | U58: =IF(I58="Closed Won","Won",IF(I58="Closed Lost","Lost","Open")) -> Lost | V58: =IF(U58="Won",L58*(1-M58),0) -> 0 | W58: =IF(U58="Open",L58*N58,0) -> 0 | X58: =IF(U58="Open","",IFERROR(K58-B58,"")) -> 32 | Y58: =IF(U58="Open",Lookups!$B$2-B58,X58) -> 32 | Z58: =IF(AND(U58="Open",Y58>30),"STALE","OK") -> OK | AA58: =TEXT(B58,"yyyy-mm") -> 2025-02 | AB58: =IF(K58="","",TEXT(K58,"yyyy-mm")) -> 2025-03 | AC58: ="Q"&ROUNDUP(MONTH(B58)/3,0)&"-"&YEAR(B58) -> Q1-2025 | AD58: =MIN(100,IF(H58="Enterprise",30,IF(H58="Mid-Market",22,14))+IF(T58="Enterprise",25,IF(T58="Mid-Market",18,10))+IF(Q58="Referral",25,IF(Q58="Organic Search",20,IF(Q58="Email",18,14)))+IF(G58="Technology",10,5)) -> 57 | AE58: =IF(U58<>"Open",U58,IF(N58>=0.8,"Commit",IF(N58>=0.5,"Best Case","Pipeline"))) -> Lost
A59: L00058 | B59: 46226 | C59: Tuan Bui | D59: Central | E59: linkedin | F59: MKT-AUTO | G59: Healthcare | H59: SMB | I59: Qualified | J59: 46251 | L59: 13800 | M59: 0.03 | N59: 0.2 | P59: 2 | Q59: =IFERROR(VLOOKUP(E59,Lookups!$A$5:$B$24,2,FALSE),"Other") -> LinkedIn | R59: =IFERROR(VLOOKUP(F59,Lookups!$D$5:$F$10,2,FALSE),"Unknown Product") -> Marketing Automation | S59: =IFERROR(VLOOKUP(F59,Lookups!$D$5:$F$10,3,FALSE),"Unknown") -> Marketing | T59: =IF(L59>=50000,"Enterprise",IF(L59>=20000,"Mid-Market","SMB")) -> SMB | U59: =IF(I59="Closed Won","Won",IF(I59="Closed Lost","Lost","Open")) -> Open | V59: =IF(U59="Won",L59*(1-M59),0) -> 0 | W59: =IF(U59="Open",L59*N59,0) -> 2760 | X59: =IF(U59="Open","",IFERROR(K59-B59,"")) | Y59: =IF(U59="Open",Lookups!$B$2-B59,X59) -> 40 | Z59: =IF(AND(U59="Open",Y59>30),"STALE","OK") -> STALE | AA59: =TEXT(B59,"yyyy-mm") -> 2026-07 | AB59: =IF(K59="","",TEXT(K59,"yyyy-mm")) | AC59: ="Q"&ROUNDUP(MONTH(B59)/3,0)&"-"&YEAR(B59) -> Q3-2026 | AD59: =MIN(100,IF(H59="Enterprise",30,IF(H59="Mid-Market",22,14))+IF(T59="Enterprise",25,IF(T59="Mid-Market",18,10))+IF(Q59="Referral",25,IF(Q59="Organic Search",20,IF(Q59="Email",18,14)))+IF(G59="Technology",10,5)) -> 43 | AE59: =IF(U59<>"Open",U59,IF(N59>=0.8,"Commit",IF(N59>=0.5,"Best Case","Pipeline"))) -> Pipeline
A60: L00059 | B60: 45721 | C60: Tuan Bui | D60: Central | E60: Email Campaign | F60: BI-PLUS | G60: Technology | H60: Mid-Market | I60: Closed Won | J60: 45756 | K60: 45756 | L60: 44300 | M60: 0.12 | N60: 1 | P60: 6 | Q60: =IFERROR(VLOOKUP(E60,Lookups!$A$5:$B$24,2,FALSE),"Other") -> Email | R60: =IFERROR(VLOOKUP(F60,Lookups!$D$5:$F$10,2,FALSE),"Unknown Product") -> Analytics Plus | S60: =IFERROR(VLOOKUP(F60,Lookups!$D$5:$F$10,3,FALSE),"Unknown") -> Analytics | T60: =IF(L60>=50000,"Enterprise",IF(L60>=20000,"Mid-Market","SMB")) -> Mid-Market | U60: =IF(I60="Closed Won","Won",IF(I60="Closed Lost","Lost","Open")) -> Won | V60: =IF(U60="Won",L60*(1-M60),0) -> 38984 | W60: =IF(U60="Open",L60*N60,0) -> 0 | X60: =IF(U60="Open","",IFERROR(K60-B60,"")) -> 35 | Y60: =IF(U60="Open",Lookups!$B$2-B60,X60) -> 35 | Z60: =IF(AND(U60="Open",Y60>30),"STALE","OK") -> OK | AA60: =TEXT(B60,"yyyy-mm") -> 2025-03 | AB60: =IF(K60="","",TEXT(K60,"yyyy-mm")) -> 2025-04 | AC60: ="Q"&ROUNDUP(MONTH(B60)/3,0)&"-"&YEAR(B60) -> Q1-2025 | AD60: =MIN(100,IF(H60="Enterprise",30,IF(H60="Mid-Market",22,14))+IF(T60="Enterprise",25,IF(T60="Mid-Market",18,10))+IF(Q60="Referral",25,IF(Q60="Organic Search",20,IF(Q60="Email",18,14)))+IF(G60="Technology",10,5)) -> 68 | AE60: =IF(U60<>"Open",U60,IF(N60>=0.8,"Commit",IF(N60>=0.5,"Best Case","Pipeline"))) -> Won
A61: L00060 | B61: 46130 | C61: Duy Pham | D61: South | E61: virtual event | F61: CRM-PRO | G61: Education | H61: SMB | I61: Closed Lost | J61: 46182 | K61: 46182 | L61: 14100 | M61: 0 | N61: 0 | O61: No Decision | P61: 5 | Q61: =IFERROR(VLOOKUP(E61,Lookups!$A$5:$B$24,2,FALSE),"Other") -> Webinar | R61: =IFERROR(VLOOKUP(F61,Lookups!$D$5:$F$10,2,FALSE),"Unknown Product") -> NexaCRM Pro | S61: =IFERROR(VLOOKUP(F61,Lookups!$D$5:$F$10,3,FALSE),"Unknown") -> CRM | T61: =IF(L61>=50000,"Enterprise",IF(L61>=20000,"Mid-Market","SMB")) -> SMB | U61: =IF(I61="Closed Won","Won",IF(I61="Closed Lost","Lost","Open")) -> Lost | V61: =IF(U61="Won",L61*(1-M61),0) -> 0 | W61: =IF(U61="Open",L61*N61,0) -> 0 | X61: =IF(U61="Open","",IFERROR(K61-B61,"")) -> 52 | Y61: =IF(U61="Open",Lookups!$B$2-B61,X61) -> 52 | Z61: =IF(AND(U61="Open",Y61>30),"STALE","OK") -> OK | AA61: =TEXT(B61,"yyyy-mm") -> 2026-04 | AB61: =IF(K61="","",TEXT(K61,"yyyy-mm")) -> 2026-06 | AC61: ="Q"&ROUNDUP(MONTH(B61)/3,0)&"-"&YEAR(B61) -> Q2-2026 | AD61: =MIN(100,IF(H61="Enterprise",30,IF(H61="Mid-Market",22,14))+IF(T61="Enterprise",25,IF(T61="Mid-Market",18,10))+IF(Q61="Referral",25,IF(Q61="Organic Search",20,IF(Q61="Email",18,14)))+IF(G61="Technology",10,5)) -> 43 | AE61: =IF(U61<>"Open",U61,IF(N61>=0.8,"Commit",IF(N61>=0.5,"Best Case","Pipeline"))) -> Lost
A62: L00061 | B62: 45919 | C62: Bao Tran | D62: South | E62: Referral | F62: CRM-CORE | G62: Financial Services | H62: SMB | I62: Closed Lost | J62: 45978 | K62: 45978 | L62: 9300 | M62: 0 | N62: 0 | O62: Timing | P62: 4 | Q62: =IFERROR(VLOOKUP(E62,Lookups!$A$5:$B$24,2,FALSE),"Other") -> Referral | R62: =IFERROR(VLOOKUP(F62,Lookups!$D$5:$F$10,2,FALSE),"Unknown Product") -> NexaCRM Core | S62: =IFERROR(VLOOKUP(F62,Lookups!$D$5:$F$10,3,FALSE),"Unknown") -> CRM | T62: =IF(L62>=50000,"Enterprise",IF(L62>=20000,"Mid-Market","SMB")) -> SMB | U62: =IF(I62="Closed Won","Won",IF(I62="Closed Lost","Lost","Open")) -> Lost | V62: =IF(U62="Won",L62*(1-M62),0) -> 0 | W62: =IF(U62="Open",L62*N62,0) -> 0 | X62: =IF(U62="Open","",IFERROR(K62-B62,"")) -> 59 | Y62: =IF(U62="Open",Lookups!$B$2-B62,X62) -> 59 | Z62: =IF(AND(U62="Open",Y62>30),"STALE","OK") -> OK | AA62: =TEXT(B62,"yyyy-mm") -> 2025-09 | AB62: =IF(K62="","",TEXT(K62,"yyyy-mm")) -> 2025-11 | AC62: ="Q"&ROUNDUP(MONTH(B62)/3,0)&"-"&YEAR(B62) -> Q3-2025 | AD62: =MIN(100,IF(H62="Enterprise",30,IF(H62="Mid-Market",22,14))+IF(T62="Enterprise",25,IF(T62="Mid-Market",18,10))+IF(Q62="Referral",25,IF(Q62="Organic Search",20,IF(Q62="Email",18,14)))+IF(G62="Technology",10,5)) -> 54 | AE62: =IF(U62<>"Open",U62,IF(N62>=0.8,"Commit",IF(N62>=0.5,"Best Case","Pipeline"))) -> Lost
A63: L00062 | B63: 45912 | C63: Ha Vo | D63: North | E63: Google Ads | F63: REV-OPS | G63: Professional Services | H63: SMB | I63: Closed Lost | J63: 45933 | K63: 45933 | L63: 41400 | M63: 0 | N63: 0 | O63: Price | P63: 5 | Q63: =IFERROR(VLOOKUP(E63,Lookups!$A$5:$B$24,2,FALSE),"Other") -> Paid Search | R63: =IFERROR(VLOOKUP(F63,Lookups!$D$5:$F$10,2,FALSE),"Unknown Product") -> Revenue Operations Suite | S63: =IFERROR(VLOOKUP(F63,Lookups!$D$5:$F$10,3,FALSE),"Unknown") -> Revenue Ops | T63: =IF(L63>=50000,"Enterprise",IF(L63>=20000,"Mid-Market","SMB")) -> Mid-Market | U63: =IF(I63="Closed Won","Won",IF(I63="Closed Lost","Lost","Open")) -> Lost | V63: =IF(U63="Won",L63*(1-M63),0) -> 0 | W63: =IF(U63="Open",L63*N63,0) -> 0 | X63: =IF(U63="Open","",IFERROR(K63-B63,"")) -> 21 | Y63: =IF(U63="Open",Lookups!$B$2-B63,X63) -> 21 | Z63: =IF(AND(U63="Open",Y63>30),"STALE","OK") -> OK | AA63: =TEXT(B63,"yyyy-mm") -> 2025-09 | AB63: =IF(K63="","",TEXT(K63,"yyyy-mm")) -> 2025-10 | AC63: ="Q"&ROUNDUP(MONTH(B63)/3,0)&"-"&YEAR(B63) -> Q3-2025 | AD63: =MIN(100,IF(H63="Enterprise",30,IF(H63="Mid-Market",22,14))+IF(T63="Enterprise",25,IF(T63="Mid-Market",18,10))+IF(Q63="Referral",25,IF(Q63="Organic Search",20,IF(Q63="Email",18,14)))+IF(G63="Technology",10,5)) -> 51 | AE63: =IF(U63<>"Open",U63,IF(N63>=0.8,"Commit",IF(N63>=0.5,"Best Case","Pipeline"))) -> Lost
A64: L00063 | B64: 46055 | C64: Quynh Vu | D64: North | E64: organic search | F64: CRM-CORE | G64: Retail | H64: SMB | I64: Closed Lost | J64: 46101 | K64: 46101 | L64: 5700 | M64: 0 | N64: 0 | O64: No Decision | P64: 4 | Q64: =IFERROR(VLOOKUP(E64,Lookups!$A$5:$B$24,2,FALSE),"Other") -> Organic Search | R64: =IFERROR(VLOOKUP(F64,Lookups!$D$5:$F$10,2,FALSE),"Unknown Product") -> NexaCRM Core | S64: =IFERROR(VLOOKUP(F64,Lookups!$D$5:$F$10,3,FALSE),"Unknown") -> CRM | T64: =IF(L64>=50000,"Enterprise",IF(L64>=20000,"Mid-Market","SMB")) -> SMB | U64: =IF(I64="Closed Won","Won",IF(I64="Closed Lost","Lost","Open")) -> Lost | V64: =IF(U64="Won",L64*(1-M64),0) -> 0 | W64: =IF(U64="Open",L64*N64,0) -> 0 | X64: =IF(U64="Open","",IFERROR(K64-B64,"")) -> 46 | Y64: =IF(U64="Open",Lookups!$B$2-B64,X64) -> 46 | Z64: =IF(AND(U64="Open",Y64>30),"STALE","OK") -> OK | AA64: =TEXT(B64,"yyyy-mm") -> 2026-02 | AB64: =IF(K64="","",TEXT(K64,"yyyy-mm")) -> 2026-03 | AC64: ="Q"&ROUNDUP(MONTH(B64)/3,0)&"-"&YEAR(B64) -> Q1-2026 | AD64: =MIN(100,IF(H64="Enterprise",30,IF(H64="Mid-Market",22,14))+IF(T64="Enterprise",25,IF(T64="Mid-Market",18,10))+IF(Q64="Referral",25,IF(Q64="Organic Search",20,IF(Q64="Email",18,14)))+IF(G64="Technology",10,5)) -> 49 | AE64: =IF(U64<>"Open",U64,IF(N64>=0.8,"Commit",IF(N64>=0.5,"Best Case","Pipeline"))) -> Lost
A65: L00064 | B65: 46095 | C65: Duy Pham | D65: South | E65: Partner Referral | F65: CS-CLOUD | G65: Professional Services | H65: SMB | I65: Closed Won | J65: 46151 | K65: 46151 | L65: 27700 | M65: 0.12 | N65: 1 | P65: 6 | Q65: =IFERROR(VLOOKUP(E65,Lookups!$A$5:$B$24,2,FALSE),"Other") -> Referral | R65: =IFERROR(VLOOKUP(F65,Lookups!$D$5:$F$10,2,FALSE),"Unknown Product") -> Service Cloud | S65: =IFERROR(VLOOKUP(F65,Lookups!$D$5:$F$10,3,FALSE),"Unknown") -> Customer Service | T65: =IF(L65>=50000,"Enterprise",IF(L65>=20000,"Mid-Market","SMB")) -> Mid-Market | U65: =IF(I65="Closed Won","Won",IF(I65="Closed Lost","Lost","Open")) -> Won | V65: =IF(U65="Won",L65*(1-M65),0) -> 24376 | W65: =IF(U65="Open",L65*N65,0) -> 0 | X65: =IF(U65="Open","",IFERROR(K65-B65,"")) -> 56 | Y65: =IF(U65="Open",Lookups!$B$2-B65,X65) -> 56 | Z65: =IF(AND(U65="Open",Y65>30),"STALE","OK") -> OK | AA65: =TEXT(B65,"yyyy-mm") -> 2026-03 | AB65: =IF(K65="","",TEXT(K65,"yyyy-mm")) -> 2026-05 | AC65: ="Q"&ROUNDUP(MONTH(B65)/3,0)&"-"&YEAR(B65) -> Q1-2026 | AD65: =MIN(100,IF(H65="Enterprise",30,IF(H65="Mid-Market",22,14))+IF(T65="Enterprise",25,IF(T65="Mid-Market",18,10))+IF(Q65="Referral",25,IF(Q65="Organic Search",20,IF(Q65="Email",18,14)))+IF(G65="Technology",10,5)) -> 62 | AE65: =IF(U65<>"Open",U65,IF(N65>=0.8,"Commit",IF(N65>=0.5,"Best Case","Pipeline"))) -> Won
A66: L00065 | B66: 46227 | C66: Minh Do | D66: North | E66: organic search | F66: MKT-AUTO | G66: Education | H66: Enterprise | I66: Demo / Meeting | J66: 46251 | L66: 35700 | M66: 0 | N66: 0.4 | P66: 3 | Q66: =IFERROR(VLOOKUP(E66,Lookups!$A$5:$B$24,2,FALSE),"Other") -> Organic Search | R66: =IFERROR(VLOOKUP(F66,Lookups!$D$5:$F$10,2,FALSE),"Unknown Product") -> Marketing Automation | S66: =IFERROR(VLOOKUP(F66,Lookups!$D$5:$F$10,3,FALSE),"Unknown") -> Marketing | T66: =IF(L66>=50000,"Enterprise",IF(L66>=20000,"Mid-Market","SMB")) -> Mid-Market | U66: =IF(I66="Closed Won","Won",IF(I66="Closed Lost","Lost","Open")) -> Open | V66: =IF(U66="Won",L66*(1-M66),0) -> 0 | W66: =IF(U66="Open",L66*N66,0) -> 14280 | X66: =IF(U66="Open","",IFERROR(K66-B66,"")) | Y66: =IF(U66="Open",Lookups!$B$2-B66,X66) -> 39 | Z66: =IF(AND(U66="Open",Y66>30),"STALE","OK") -> STALE | AA66: =TEXT(B66,"yyyy-mm") -> 2026-07 | AB66: =IF(K66="","",TEXT(K66,"yyyy-mm")) | AC66: ="Q"&ROUNDUP(MONTH(B66)/3,0)&"-"&YEAR(B66) -> Q3-2026 | AD66: =MIN(100,IF(H66="Enterprise",30,IF(H66="Mid-Market",22,14))+IF(T66="Enterprise",25,IF(T66="Mid-Market",18,10))+IF(Q66="Referral",25,IF(Q66="Organic Search",20,IF(Q66="Email",18,14)))+IF(G66="Technology",10,5)) -> 73 | AE66: =IF(U66<>"Open",U66,IF(N66>=0.8,"Commit",IF(N66>=0.5,"Best Case","Pipeline"))) -> Pipeline
A67: L00066 | B67: 45987 | C67: Quynh Vu | D67: North | E67: google cpc | F67: BI-PLUS | G67: Manufacturing | H67: SMB | I67: Closed Lost | J67: 46027 | K67: 46027 | L67: 13900 | M67: 0 | N67: 0 | O67: Timing | P67: 3 | Q67: =IFERROR(VLOOKUP(E67,Lookups!$A$5:$B$24,2,FALSE),"Other") -> Paid Search | R67: =IFERROR(VLOOKUP(F67,Lookups!$D$5:$F$10,2,FALSE),"Unknown Product") -> Analytics Plus | S67: =IFERROR(VLOOKUP(F67,Lookups!$D$5:$F$10,3,FALSE),"Unknown") -> Analytics | T67: =IF(L67>=50000,"Enterprise",IF(L67>=20000,"Mid-Market","SMB")) -> SMB | U67: =IF(I67="Closed Won","Won",IF(I67="Closed Lost","Lost","Open")) -> Lost | V67: =IF(U67="Won",L67*(1-M67),0) -> 0 | W67: =IF(U67="Open",L67*N67,0) -> 0 | X67: =IF(U67="Open","",IFERROR(K67-B67,"")) -> 40 | Y67: =IF(U67="Open",Lookups!$B$2-B67,X67) -> 40 | Z67: =IF(AND(U67="Open",Y67>30),"STALE","OK") -> OK | AA67: =TEXT(B67,"yyyy-mm") -> 2025-11 | AB67: =IF(K67="","",TEXT(K67,"yyyy-mm")) -> 2026-01 | AC67: ="Q"&ROUNDUP(MONTH(B67)/3,0)&"-"&YEAR(B67) -> Q4-2025 | AD67: =MIN(100,IF(H67="Enterprise",30,IF(H67="Mid-Market",22,14))+IF(T67="Enterprise",25,IF(T67="Mid-Market",18,10))+IF(Q67="Referral",25,IF(Q67="Organic Search",20,IF(Q67="Email",18,14)))+IF(G67="Technology",10,5)) -> 43 | AE67: =IF(U67<>"Open",U67,IF(N67>=0.8,"Commit",IF(N67>=0.5,"Best Case","Pipeline"))) -> Lost
A68: L00067 | B68: 45784 | C68: An Nguyen | D68: South | E68: customer referral | F68: CRM-PRO | G68: Financial Services | H68: Mid-Market | I68: Closed Won | J68: 45832 | K68: 45832 | L68: 21400 | M68: 0.08 | N68: 1 | P68: 6 | Q68: =IFERROR(VLOOKUP(E68,Lookups!$A$5:$B$24,2,FALSE),"Other") -> Referral | R68: =IFERROR(VLOOKUP(F68,Lookups!$D$5:$F$10,2,FALSE),"Unknown Product") -> NexaCRM Pro | S68: =IFERROR(VLOOKUP(F68,Lookups!$D$5:$F$10,3,FALSE),"Unknown") -> CRM | T68: =IF(L68>=50000,"Enterprise",IF(L68>=20000,"Mid-Market","SMB")) -> Mid-Market | U68: =IF(I68="Closed Won","Won",IF(I68="Closed Lost","Lost","Open")) -> Won | V68: =IF(U68="Won",L68*(1-M68),0) -> 19688 | W68: =IF(U68="Open",L68*N68,0) -> 0 | X68: =IF(U68="Open","",IFERROR(K68-B68,"")) -> 48 | Y68: =IF(U68="Open",Lookups!$B$2-B68,X68) -> 48 | Z68: =IF(AND(U68="Open",Y68>30),"STALE","OK") -> OK | AA68: =TEXT(B68,"yyyy-mm") -> 2025-05 | AB68: =IF(K68="","",TEXT(K68,"yyyy-mm")) -> 2025-06 | AC68: ="Q"&ROUNDUP(MONTH(B68)/3,0)&"-"&YEAR(B68) -> Q2-2025 | AD68: =MIN(100,IF(H68="Enterprise",30,IF(H68="Mid-Market",22,14))+IF(T68="Enterprise",25,IF(T68="Mid-Market",18,10))+IF(Q68="Referral",25,IF(Q68="Organic Search",20,IF(Q68="Email",18,14)))+IF(G68="Technology",10,5)) -> 70 | AE68: =IF(U68<>"Open",U68,IF(N68>=0.8,"Commit",IF(N68>=0.5,"Best Case","Pipeline"))) -> Won
A69: L00068 | B69: 45935 | C69: Minh Do | D69: North | E69: SDR Outreach | F69: BI-PLUS | G69: Healthcare | H69: Mid-Market | I69: Closed Lost | J69: 45961 | K69: 45961 | L69: 29300 | M69: 0 | N69: 0 | O69: No Decision | P69: 2 | Q69: =IFERROR(VLOOKUP(E69,Lookups!$A$5:$B$24,2,FALSE),"Other") -> Outbound | R69: =IFERROR(VLOOKUP(F69,Lookups!$D$5:$F$10,2,FALSE),"Unknown Product") -> Analytics Plus | S69: =IFERROR(VLOOKUP(F69,Lookups!$D$5:$F$10,3,FALSE),"Unknown") -> Analytics | T69: =IF(L69>=50000,"Enterprise",IF(L69>=20000,"Mid-Market","SMB")) -> Mid-Market | U69: =IF(I69="Closed Won","Won",IF(I69="Closed Lost","Lost","Open")) -> Lost | V69: =IF(U69="Won",L69*(1-M69),0) -> 0 | W69: =IF(U69="Open",L69*N69,0) -> 0 | X69: =IF(U69="Open","",IFERROR(K69-B69,"")) -> 26 | Y69: =IF(U69="Open",Lookups!$B$2-B69,X69) -> 26 | Z69: =IF(AND(U69="Open",Y69>30),"STALE","OK") -> OK | AA69: =TEXT(B69,"yyyy-mm") -> 2025-10 | AB69: =IF(K69="","",TEXT(K69,"yyyy-mm")) -> 2025-10 | AC69: ="Q"&ROUNDUP(MONTH(B69)/3,0)&"-"&YEAR(B69) -> Q4-2025 | AD69: =MIN(100,IF(H69="Enterprise",30,IF(H69="Mid-Market",22,14))+IF(T69="Enterprise",25,IF(T69="Mid-Market",18,10))+IF(Q69="Referral",25,IF(Q69="Organic Search",20,IF(Q69="Email",18,14)))+IF(G69="Technology",10,5)) -> 59 | AE69: =IF(U69<>"Open",U69,IF(N69>=0.8,"Commit",IF(N69>=0.5,"Best Case","Pipeline"))) -> Lost
A70: L00069 | B70: 46134 | C70: Ha Vo | D70: North | E70: Outbound | F70: CRM-CORE | G70: Technology | H70: SMB | I70: Closed Lost | J70: 46206 | K70: 46206 | L70: 9100 | M70: 0 | N70: 0 | O70: Budget | P70: 5 | Q70: =IFERROR(VLOOKUP(E70,Lookups!$A$5:$B$24,2,FALSE),"Other") -> Outbound | R70: =IFERROR(VLOOKUP(F70,Lookups!$D$5:$F$10,2,FALSE),"Unknown Product") -> NexaCRM Core | S70: =IFERROR(VLOOKUP(F70,Lookups!$D$5:$F$10,3,FALSE),"Unknown") -> CRM | T70: =IF(L70>=50000,"Enterprise",IF(L70>=20000,"Mid-Market","SMB")) -> SMB | U70: =IF(I70="Closed Won","Won",IF(I70="Closed Lost","Lost","Open")) -> Lost | V70: =IF(U70="Won",L70*(1-M70),0) -> 0 | W70: =IF(U70="Open",L70*N70,0) -> 0 | X70: =IF(U70="Open","",IFERROR(K70-B70,"")) -> 72 | Y70: =IF(U70="Open",Lookups!$B$2-B70,X70) -> 72 | Z70: =IF(AND(U70="Open",Y70>30),"STALE","OK") -> OK | AA70: =TEXT(B70,"yyyy-mm") -> 2026-04 | AB70: =IF(K70="","",TEXT(K70,"yyyy-mm")) -> 2026-07 | AC70: ="Q"&ROUNDUP(MONTH(B70)/3,0)&"-"&YEAR(B70) -> Q2-2026 | AD70: =MIN(100,IF(H70="Enterprise",30,IF(H70="Mid-Market",22,14))+IF(T70="Enterprise",25,IF(T70="Mid-Market",18,10))+IF(Q70="Referral",25,IF(Q70="Organic Search",20,IF(Q70="Email",18,14)))+IF(G70="Technology",10,5)) -> 48 | AE70: =IF(U70<>"Open",U70,IF(N70>=0.8,"Commit",IF(N70>=0.5,"Best Case","Pipeline"))) -> Lost
A71: L00070 | B71: 46070 | C71: Minh Do | D71: North | E71: organic search | F71: CS-CLOUD | G71: Professional Services | H71: SMB | I71: Closed Lost | J71: 46138 | K71: 46138 | L71: 26300 | M71: 0 | N71: 0 | O71: Price | P71: 4 | Q71: =IFERROR(VLOOKUP(E71,Lookups!$A$5:$B$24,2,FALSE),"Other") -> Organic Search | R71: =IFERROR(VLOOKUP(F71,Lookups!$D$5:$F$10,2,FALSE),"Unknown Product") -> Service Cloud | S71: =IFERROR(VLOOKUP(F71,Lookups!$D$5:$F$10,3,FALSE),"Unknown") -> Customer Service | T71: =IF(L71>=50000,"Enterprise",IF(L71>=20000,"Mid-Market","SMB")) -> Mid-Market | U71: =IF(I71="Closed Won","Won",IF(I71="Closed Lost","Lost","Open")) -> Lost | V71: =IF(U71="Won",L71*(1-M71),0) -> 0 | W71: =IF(U71="Open",L71*N71,0) -> 0 | X71: =IF(U71="Open","",IFERROR(K71-B71,"")) -> 68 | Y71: =IF(U71="Open",Lookups!$B$2-B71,X71) -> 68 | Z71: =IF(AND(U71="Open",Y71>30),"STALE","OK") -> OK | AA71: =TEXT(B71,"yyyy-mm") -> 2026-02 | AB71: =IF(K71="","",TEXT(K71,"yyyy-mm")) -> 2026-04 | AC71: ="Q"&ROUNDUP(MONTH(B71)/3,0)&"-"&YEAR(B71) -> Q1-2026 | AD71: =MIN(100,IF(H71="Enterprise",30,IF(H71="Mid-Market",22,14))+IF(T71="Enterprise",25,IF(T71="Mid-Market",18,10))+IF(Q71="Referral",25,IF(Q71="Organic Search",20,IF(Q71="Email",18,14)))+IF(G71="Technology",10,5)) -> 57 | AE71: =IF(U71<>"Open",U71,IF(N71>=0.8,"Commit",IF(N71>=0.5,"Best Case","Pipeline"))) -> Lost
A72: L00071 | B72: 45723 | C72: An Nguyen | D72: South | E72: SEO | F72: CRM-CORE | G72: Manufacturing | H72: SMB | I72: Closed Won | J72: 45798 | K72: 45798 | L72: 6500 | M72: 0 | N72: 1 | P72: 6 | Q72: =IFERROR(VLOOKUP(E72,Lookups!$A$5:$B$24,2,FALSE),"Other") -> Organic Search | R72: =IFERROR(VLOOKUP(F72,Lookups!$D$5:$F$10,2,FALSE),"Unknown Product") -> NexaCRM Core | S72: =IFERROR(VLOOKUP(F72,Lookups!$D$5:$F$10,3,FALSE),"Unknown") -> CRM | T72: =IF(L72>=50000,"Enterprise",IF(L72>=20000,"Mid-Market","SMB")) -> SMB | U72: =IF(I72="Closed Won","Won",IF(I72="Closed Lost","Lost","Open")) -> Won | V72: =IF(U72="Won",L72*(1-M72),0) -> 6500 | W72: =IF(U72="Open",L72*N72,0) -> 0 | X72: =IF(U72="Open","",IFERROR(K72-B72,"")) -> 75 | Y72: =IF(U72="Open",Lookups!$B$2-B72,X72) -> 75 | Z72: =IF(AND(U72="Open",Y72>30),"STALE","OK") -> OK | AA72: =TEXT(B72,"yyyy-mm") -> 2025-03 | AB72: =IF(K72="","",TEXT(K72,"yyyy-mm")) -> 2025-05 | AC72: ="Q"&ROUNDUP(MONTH(B72)/3,0)&"-"&YEAR(B72) -> Q1-2025 | AD72: =MIN(100,IF(H72="Enterprise",30,IF(H72="Mid-Market",22,14))+IF(T72="Enterprise",25,IF(T72="Mid-Market",18,10))+IF(Q72="Referral",25,IF(Q72="Organic Search",20,IF(Q72="Email",18,14)))+IF(G72="Technology",10,5)) -> 49 | AE72: =IF(U72<>"Open",U72,IF(N72>=0.8,"Commit",IF(N72>=0.5,"Best Case","Pipeline"))) -> Won
A73: L00072 | B73: 46184 | C73: Chi Le | D73: South | E73: SEM - Google | F73: CS-CLOUD | G73: Retail | H73: SMB | I73: Demo / Meeting | J73: 46218 | L73: 22300 | M73: 0 | N73: 0.4 | P73: 3 | Q73: =IFERROR(VLOOKUP(E73,Lookups!$A$5:$B$24,2,FALSE),"Other") -> Paid Search | R73: =IFERROR(VLOOKUP(F73,Lookups!$D$5:$F$10,2,FALSE),"Unknown Product") -> Service Cloud | S73: =IFERROR(VLOOKUP(F73,Lookups!$D$5:$F$10,3,FALSE),"Unknown") -> Customer Service | T73: =IF(L73>=50000,"Enterprise",IF(L73>=20000,"Mid-Market","SMB")) -> Mid-Market | U73: =IF(I73="Closed Won","Won",IF(I73="Closed Lost","Lost","Open")) -> Open | V73: =IF(U73="Won",L73*(1-M73),0) -> 0 | W73: =IF(U73="Open",L73*N73,0) -> 8920 | X73: =IF(U73="Open","",IFERROR(K73-B73,"")) | Y73: =IF(U73="Open",Lookups!$B$2-B73,X73) -> 82 | Z73: =IF(AND(U73="Open",Y73>30),"STALE","OK") -> STALE | AA73: =TEXT(B73,"yyyy-mm") -> 2026-06 | AB73: =IF(K73="","",TEXT(K73,"yyyy-mm")) | AC73: ="Q"&ROUNDUP(MONTH(B73)/3,0)&"-"&YEAR(B73) -> Q2-2026 | AD73: =MIN(100,IF(H73="Enterprise",30,IF(H73="Mid-Market",22,14))+IF(T73="Enterprise",25,IF(T73="Mid-Market",18,10))+IF(Q73="Referral",25,IF(Q73="Organic Search",20,IF(Q73="Email",18,14)))+IF(G73="Technology",10,5)) -> 51 | AE73: =IF(U73<>"Open",U73,IF(N73>=0.8,"Commit",IF(N73>=0.5,"Best Case","Pipeline"))) -> Pipeline
A74: L00073 | B74: 45744 | C74: Chi Le | D74: South | E74: google cpc | F74: MKT-AUTO | G74: Professional Services | H74: SMB | I74: Closed Lost | J74: 45795 | K74: 45795 | L74: 18000 | M74: 0 | N74: 0 | O74: Price | P74: 5 | Q74: =IFERROR(VLOOKUP(E74,Lookups!$A$5:$B$24,2,FALSE),"Other") -> Paid Search | R74: =IFERROR(VLOOKUP(F74,Lookups!$D$5:$F$10,2,FALSE),"Unknown Product") -> Marketing Automation | S74: =IFERROR(VLOOKUP(F74,Lookups!$D$5:$F$10,3,FALSE),"Unknown") -> Marketing | T74: =IF(L74>=50000,"Enterprise",IF(L74>=20000,"Mid-Market","SMB")) -> SMB | U74: =IF(I74="Closed Won","Won",IF(I74="Closed Lost","Lost","Open")) -> Lost | V74: =IF(U74="Won",L74*(1-M74),0) -> 0 | W74: =IF(U74="Open",L74*N74,0) -> 0 | X74: =IF(U74="Open","",IFERROR(K74-B74,"")) -> 51 | Y74: =IF(U74="Open",Lookups!$B$2-B74,X74) -> 51 | Z74: =IF(AND(U74="Open",Y74>30),"STALE","OK") -> OK | AA74: =TEXT(B74,"yyyy-mm") -> 2025-03 | AB74: =IF(K74="","",TEXT(K74,"yyyy-mm")) -> 2025-05 | AC74: ="Q"&ROUNDUP(MONTH(B74)/3,0)&"-"&YEAR(B74) -> Q1-2025 | AD74: =MIN(100,IF(H74="Enterprise",30,IF(H74="Mid-Market",22,14))+IF(T74="Enterprise",25,IF(T74="Mid-Market",18,10))+IF(Q74="Referral",25,IF(Q74="Organic Search",20,IF(Q74="Email",18,14)))+IF(G74="Technology",10,5)) -> 43 | AE74: =IF(U74<>"Open",U74,IF(N74>=0.8,"Commit",IF(N74>=0.5,"Best Case","Pipeline"))) -> Lost
A75: L00074 | B75: 45695 | C75: Ha Vo | D75: North | E75: SDR Outreach | F75: CRM-PRO | G75: Professional Services | H75: SMB | I75: Negotiation | J75: 45926 | L75: 14700 | M75: 0.03 | N75: 0.85 | P75: 5 | Q75: =IFERROR(VLOOKUP(E75,Lookups!$A$5:$B$24,2,FALSE),"Other") -> Outbound | R75: =IFERROR(VLOOKUP(F75,Lookups!$D$5:$F$10,2,FALSE),"Unknown Product") -> NexaCRM Pro | S75: =IFERROR(VLOOKUP(F75,Lookups!$D$5:$F$10,3,FALSE),"Unknown") -> CRM | T75: =IF(L75>=50000,"Enterprise",IF(L75>=20000,"Mid-Market","SMB")) -> SMB | U75: =IF(I75="Closed Won","Won",IF(I75="Closed Lost","Lost","Open")) -> Open | V75: =IF(U75="Won",L75*(1-M75),0) -> 0 | W75: =IF(U75="Open",L75*N75,0) -> 12495 | X75: =IF(U75="Open","",IFERROR(K75-B75,"")) | Y75: =IF(U75="Open",Lookups!$B$2-B75,X75) -> 571 | Z75: =IF(AND(U75="Open",Y75>30),"STALE","OK") -> STALE | AA75: =TEXT(B75,"yyyy-mm") -> 2025-02 | AB75: =IF(K75="","",TEXT(K75,"yyyy-mm")) | AC75: ="Q"&ROUNDUP(MONTH(B75)/3,0)&"-"&YEAR(B75) -> Q1-2025 | AD75: =MIN(100,IF(H75="Enterprise",30,IF(H75="Mid-Market",22,14))+IF(T75="Enterprise",25,IF(T75="Mid-Market",18,10))+IF(Q75="Referral",25,IF(Q75="Organic Search",20,IF(Q75="Email",18,14)))+IF(G75="Technology",10,5)) -> 43 | AE75: =IF(U75<>"Open",U75,IF(N75>=0.8,"Commit",IF(N75>=0.5,"Best Case","Pipeline"))) -> Commit
A76: L00075 | B76: 46221 | C76: Minh Do | D76: North | E76: LI Ads | F76: BI-PLUS | G76: Retail | H76: SMB | I76: Closed Lost | J76: 46256 | K76: 46256 | L76: 17600 | M76: 0 | N76: 0 | O76: Price | P76: 4 | Q76: =IFERROR(VLOOKUP(E76,Lookups!$A$5:$B$24,2,FALSE),"Other") -> LinkedIn | R76: =IFERROR(VLOOKUP(F76,Lookups!$D$5:$F$10,2,FALSE),"Unknown Product") -> Analytics Plus | S76: =IFERROR(VLOOKUP(F76,Lookups!$D$5:$F$10,3,FALSE),"Unknown") -> Analytics | T76: =IF(L76>=50000,"Enterprise",IF(L76>=20000,"Mid-Market","SMB")) -> SMB | U76: =IF(I76="Closed Won","Won",IF(I76="Closed Lost","Lost","Open")) -> Lost | V76: =IF(U76="Won",L76*(1-M76),0) -> 0 | W76: =IF(U76="Open",L76*N76,0) -> 0 | X76: =IF(U76="Open","",IFERROR(K76-B76,"")) -> 35 | Y76: =IF(U76="Open",Lookups!$B$2-B76,X76) -> 35 | Z76: =IF(AND(U76="Open",Y76>30),"STALE","OK") -> OK | AA76: =TEXT(B76,"yyyy-mm") -> 2026-07 | AB76: =IF(K76="","",TEXT(K76,"yyyy-mm")) -> 2026-08 | AC76: ="Q"&ROUNDUP(MONTH(B76)/3,0)&"-"&YEAR(B76) -> Q3-2026 | AD76: =MIN(100,IF(H76="Enterprise",30,IF(H76="Mid-Market",22,14))+IF(T76="Enterprise",25,IF(T76="Mid-Market",18,10))+IF(Q76="Referral",25,IF(Q76="Organic Search",20,IF(Q76="Email",18,14)))+IF(G76="Technology",10,5)) -> 43 | AE76: =IF(U76<>"Open",U76,IF(N76>=0.8,"Commit",IF(N76>=0.5,"Best Case","Pipeline"))) -> Lost
A77: L00076 | B77: 46218 | C77: Duy Pham | D77: South | E77: Google Ads | F77: CRM-CORE | G77: Financial Services | H77: Enterprise | I77: Closed Won | J77: 46266 | K77: 46266 | L77: 20000 | M77: 0 | N77: 1 | P77: 6 | Q77: =IFERROR(VLOOKUP(E77,Lookups!$A$5:$B$24,2,FALSE),"Other") -> Paid Search | R77: =IFERROR(VLOOKUP(F77,Lookups!$D$5:$F$10,2,FALSE),"Unknown Product") -> NexaCRM Core | S77: =IFERROR(VLOOKUP(F77,Lookups!$D$5:$F$10,3,FALSE),"Unknown") -> CRM | T77: =IF(L77>=50000,"Enterprise",IF(L77>=20000,"Mid-Market","SMB")) -> Mid-Market | U77: =IF(I77="Closed Won","Won",IF(I77="Closed Lost","Lost","Open")) -> Won | V77: =IF(U77="Won",L77*(1-M77),0) -> 20000 | W77: =IF(U77="Open",L77*N77,0) -> 0 | X77: =IF(U77="Open","",IFERROR(K77-B77,"")) -> 48 | Y77: =IF(U77="Open",Lookups!$B$2-B77,X77) -> 48 | Z77: =IF(AND(U77="Open",Y77>30),"STALE","OK") -> OK | AA77: =TEXT(B77,"yyyy-mm") -> 2026-07 | AB77: =IF(K77="","",TEXT(K77,"yyyy-mm")) -> 2026-09 | AC77: ="Q"&ROUNDUP(MONTH(B77)/3,0)&"-"&YEAR(B77) -> Q3-2026 | AD77: =MIN(100,IF(H77="Enterprise",30,IF(H77="Mid-Market",22,14))+IF(T77="Enterprise",25,IF(T77="Mid-Market",18,10))+IF(Q77="Referral",25,IF(Q77="Organic Search",20,IF(Q77="Email",18,14)))+IF(G77="Technology",10,5)) -> 67 | AE77: =IF(U77<>"Open",U77,IF(N77>=0.8,"Commit",IF(N77>=0.5,"Best Case","Pipeline"))) -> Won
A78: L00077 | B78: 46007 | C78: Minh Do | D78: North | E78: SEO | F78: MKT-AUTO | G78: Technology | H78: Mid-Market | I78: Negotiation | J78: 46168 | L78: 29300 | M78: 0.05 | N78: 0.85 | P78: 5 | Q78: =IFERROR(VLOOKUP(E78,Lookups!$A$5:$B$24,2,FALSE),"Other") -> Organic Search | R78: =IFERROR(VLOOKUP(F78,Lookups!$D$5:$F$10,2,FALSE),"Unknown Product") -> Marketing Automation | S78: =IFERROR(VLOOKUP(F78,Lookups!$D$5:$F$10,3,FALSE),"Unknown") -> Marketing | T78: =IF(L78>=50000,"Enterprise",IF(L78>=20000,"Mid-Market","SMB")) -> Mid-Market | U78: =IF(I78="Closed Won","Won",IF(I78="Closed Lost","Lost","Open")) -> Open | V78: =IF(U78="Won",L78*(1-M78),0) -> 0 | W78: =IF(U78="Open",L78*N78,0) -> 24905 | X78: =IF(U78="Open","",IFERROR(K78-B78,"")) | Y78: =IF(U78="Open",Lookups!$B$2-B78,X78) -> 259 | Z78: =IF(AND(U78="Open",Y78>30),"STALE","OK") -> STALE | AA78: =TEXT(B78,"yyyy-mm") -> 2025-12 | AB78: =IF(K78="","",TEXT(K78,"yyyy-mm")) | AC78: ="Q"&ROUNDUP(MONTH(B78)/3,0)&"-"&YEAR(B78) -> Q4-2025 | AD78: =MIN(100,IF(H78="Enterprise",30,IF(H78="Mid-Market",22,14))+IF(T78="Enterprise",25,IF(T78="Mid-Market",18,10))+IF(Q78="Referral",25,IF(Q78="Organic Search",20,IF(Q78="Email",18,14)))+IF(G78="Technology",10,5)) -> 70 | AE78: =IF(U78<>"Open",U78,IF(N78>=0.8,"Commit",IF(N78>=0.5,"Best Case","Pipeline"))) -> Commit
A79: L00078 | B79: 46187 | C79: Tuan Bui | D79: Central | E79: linkedin | F79: CS-CLOUD | G79: Healthcare | H79: SMB | I79: Closed Lost | J79: 46237 | K79: 46237 | L79: 22700 | M79: 0 | N79: 0 | O79: No Decision | P79: 5 | Q79: =IFERROR(VLOOKUP(E79,Lookups!$A$5:$B$24,2,FALSE),"Other") -> LinkedIn | R79: =IFERROR(VLOOKUP(F79,Lookups!$D$5:$F$10,2,FALSE),"Unknown Product") -> Service Cloud | S79: =IFERROR(VLOOKUP(F79,Lookups!$D$5:$F$10,3,FALSE),"Unknown") -> Customer Service | T79: =IF(L79>=50000,"Enterprise",IF(L79>=20000,"Mid-Market","SMB")) -> Mid-Market | U79: =IF(I79="Closed Won","Won",IF(I79="Closed Lost","Lost","Open")) -> Lost | V79: =IF(U79="Won",L79*(1-M79),0) -> 0 | W79: =IF(U79="Open",L79*N79,0) -> 0 | X79: =IF(U79="Open","",IFERROR(K79-B79,"")) -> 50 | Y79: =IF(U79="Open",Lookups!$B$2-B79,X79) -> 50 | Z79: =IF(AND(U79="Open",Y79>30),"STALE","OK") -> OK | AA79: =TEXT(B79,"yyyy-mm") -> 2026-06 | AB79: =IF(K79="","",TEXT(K79,"yyyy-mm")) -> 2026-08 | AC79: ="Q"&ROUNDUP(MONTH(B79)/3,0)&"-"&YEAR(B79) -> Q2-2026 | AD79: =MIN(100,IF(H79="Enterprise",30,IF(H79="Mid-Market",22,14))+IF(T79="Enterprise",25,IF(T79="Mid-Market",18,10))+IF(Q79="Referral",25,IF(Q79="Organic Search",20,IF(Q79="Email",18,14)))+IF(G79="Technology",10,5)) -> 51 | AE79: =IF(U79<>"Open",U79,IF(N79>=0.8,"Commit",IF(N79>=0.5,"Best Case","Pipeline"))) -> Lost
A80: L00079 | B80: 45909 | C80: Tuan Bui | D80: Central | E80: SEO | F80: BI-PLUS | G80: Professional Services | H80: SMB | I80: Closed Won | J80: 45969 | K80: 45969 | L80: 14700 | M80: 0 | N80: 1 | P80: 6 | Q80: =IFERROR(VLOOKUP(E80,Lookups!$A$5:$B$24,2,FALSE),"Other") -> Organic Search | R80: =IFERROR(VLOOKUP(F80,Lookups!$D$5:$F$10,2,FALSE),"Unknown Product") -> Analytics Plus | S80: =IFERROR(VLOOKUP(F80,Lookups!$D$5:$F$10,3,FALSE),"Unknown") -> Analytics | T80: =IF(L80>=50000,"Enterprise",IF(L80>=20000,"Mid-Market","SMB")) -> SMB | U80: =IF(I80="Closed Won","Won",IF(I80="Closed Lost","Lost","Open")) -> Won | V80: =IF(U80="Won",L80*(1-M80),0) -> 14700 | W80: =IF(U80="Open",L80*N80,0) -> 0 | X80: =IF(U80="Open","",IFERROR(K80-B80,"")) -> 60 | Y80: =IF(U80="Open",Lookups!$B$2-B80,X80) -> 60 | Z80: =IF(AND(U80="Open",Y80>30),"STALE","OK") -> OK | AA80: =TEXT(B80,"yyyy-mm") -> 2025-09 | AB80: =IF(K80="","",TEXT(K80,"yyyy-mm")) -> 2025-11 | AC80: ="Q"&ROUNDUP(MONTH(B80)/3,0)&"-"&YEAR(B80) -> Q3-2025 | AD80: =MIN(100,IF(H80="Enterprise",30,IF(H80="Mid-Market",22,14))+IF(T80="Enterprise",25,IF(T80="Mid-Market",18,10))+IF(Q80="Referral",25,IF(Q80="Organic Search",20,IF(Q80="Email",18,14)))+IF(G80="Technology",10,5)) -> 49 | AE80: =IF(U80<>"Open",U80,IF(N80>=0.8,"Commit",IF(N80>=0.5,"Best Case","Pipeline"))) -> Won
A81: L00080 | B81: 46192 | C81: Quynh Vu | D81: North | E81: Offline List | F81: CRM-CORE | G81: Healthcare | H81: Mid-Market | I81: Closed Lost | J81: 46250 | K81: 46250 | L81: 18000 | M81: 0 | N81: 0 | O81: Competitor | P81: 5 | Q81: =IFERROR(VLOOKUP(E81,Lookups!$A$5:$B$24,2,FALSE),"Other") -> Other | R81: =IFERROR(VLOOKUP(F81,Lookups!$D$5:$F$10,2,FALSE),"Unknown Product") -> NexaCRM Core | S81: =IFERROR(VLOOKUP(F81,Lookups!$D$5:$F$10,3,FALSE),"Unknown") -> CRM | T81: =IF(L81>=50000,"Enterprise",IF(L81>=20000,"Mid-Market","SMB")) -> SMB | U81: =IF(I81="Closed Won","Won",IF(I81="Closed Lost","Lost","Open")) -> Lost | V81: =IF(U81="Won",L81*(1-M81),0) -> 0 | W81: =IF(U81="Open",L81*N81,0) -> 0 | X81: =IF(U81="Open","",IFERROR(K81-B81,"")) -> 58 | Y81: =IF(U81="Open",Lookups!$B$2-B81,X81) -> 58 | Z81: =IF(AND(U81="Open",Y81>30),"STALE","OK") -> OK | AA81: =TEXT(B81,"yyyy-mm") -> 2026-06 | AB81: =IF(K81="","",TEXT(K81,"yyyy-mm")) -> 2026-08 | AC81: ="Q"&ROUNDUP(MONTH(B81)/3,0)&"-"&YEAR(B81) -> Q2-2026 | AD81: =MIN(100,IF(H81="Enterprise",30,IF(H81="Mid-Market",22,14))+IF(T81="Enterprise",25,IF(T81="Mid-Market",18,10))+IF(Q81="Referral",25,IF(Q81="Organic Search",20,IF(Q81="Email",18,14)))+IF(G81="Technology",10,5)) -> 51 | AE81: =IF(U81<>"Open",U81,IF(N81>=0.8,"Commit",IF(N81>=0.5,"Best Case","Pipeline"))) -> Lost
A82: L00081 | B82: 46197 | C82: Quynh Vu | D82: North | E82: LinkedIn Ads | F82: MKT-AUTO | G82: Professional Services | H82: Mid-Market | I82: Demo / Meeting | J82: 46246 | L82: 20100 | M82: 0.05 | N82: 0.4 | P82: 3 | Q82: =IFERROR(VLOOKUP(E82,Lookups!$A$5:$B$24,2,FALSE),"Other") -> LinkedIn | R82: =IFERROR(VLOOKUP(F82,Lookups!$D$5:$F$10,2,FALSE),"Unknown Product") -> Marketing Automation | S82: =IFERROR(VLOOKUP(F82,Lookups!$D$5:$F$10,3,FALSE),"Unknown") -> Marketing | T82: =IF(L82>=50000,"Enterprise",IF(L82>=20000,"Mid-Market","SMB")) -> Mid-Market | U82: =IF(I82="Closed Won","Won",IF(I82="Closed Lost","Lost","Open")) -> Open | V82: =IF(U82="Won",L82*(1-M82),0) -> 0 | W82: =IF(U82="Open",L82*N82,0) -> 8040 | X82: =IF(U82="Open","",IFERROR(K82-B82,"")) | Y82: =IF(U82="Open",Lookups!$B$2-B82,X82) -> 69 | Z82: =IF(AND(U82="Open",Y82>30),"STALE","OK") -> STALE | AA82: =TEXT(B82,"yyyy-mm") -> 2026-06 | AB82: =IF(K82="","",TEXT(K82,"yyyy-mm")) | AC82: ="Q"&ROUNDUP(MONTH(B82)/3,0)&"-"&YEAR(B82) -> Q2-2026 | AD82: =MIN(100,IF(H82="Enterprise",30,IF(H82="Mid-Market",22,14))+IF(T82="Enterprise",25,IF(T82="Mid-Market",18,10))+IF(Q82="Referral",25,IF(Q82="Organic Search",20,IF(Q82="Email",18,14)))+IF(G82="Technology",10,5)) -> 59 | AE82: =IF(U82<>"Open",U82,IF(N82>=0.8,"Commit",IF(N82>=0.5,"Best Case","Pipeline"))) -> Pipeline
A83: L00082 | B83: 46133 | C83: Duy Pham | D83: South | E83: Google Ads | F83: CRM-PRO | G83: Education | H83: SMB | I83: Closed Won | J83: 46201 | K83: 46201 | L83: 18000 | M83: 0.1 | N83: 1 | P83: 6 | Q83: =IFERROR(VLOOKUP(E83,Lookups!$A$5:$B$24,2,FALSE),"Other") -> Paid Search | R83: =IFERROR(VLOOKUP(F83,Lookups!$D$5:$F$10,2,FALSE),"Unknown Product") -> NexaCRM Pro | S83: =IFERROR(VLOOKUP(F83,Lookups!$D$5:$F$10,3,FALSE),"Unknown") -> CRM | T83: =IF(L83>=50000,"Enterprise",IF(L83>=20000,"Mid-Market","SMB")) -> SMB | U83: =IF(I83="Closed Won","Won",IF(I83="Closed Lost","Lost","Open")) -> Won | V83: =IF(U83="Won",L83*(1-M83),0) -> 16200 | W83: =IF(U83="Open",L83*N83,0) -> 0 | X83: =IF(U83="Open","",IFERROR(K83-B83,"")) -> 68 | Y83: =IF(U83="Open",Lookups!$B$2-B83,X83) -> 68 | Z83: =IF(AND(U83="Open",Y83>30),"STALE","OK") -> OK | AA83: =TEXT(B83,"yyyy-mm") -> 2026-04 | AB83: =IF(K83="","",TEXT(K83,"yyyy-mm")) -> 2026-06 | AC83: ="Q"&ROUNDUP(MONTH(B83)/3,0)&"-"&YEAR(B83) -> Q2-2026 | AD83: =MIN(100,IF(H83="Enterprise",30,IF(H83="Mid-Market",22,14))+IF(T83="Enterprise",25,IF(T83="Mid-Market",18,10))+IF(Q83="Referral",25,IF(Q83="Organic Search",20,IF(Q83="Email",18,14)))+IF(G83="Technology",10,5)) -> 43 | AE83: =IF(U83<>"Open",U83,IF(N83>=0.8,"Commit",IF(N83>=0.5,"Best Case","Pipeline"))) -> Won
A84: L00083 | B84: 45701 | C84: Quynh Vu | D84: North | E84: Partner Referral | F84: CS-CLOUD | G84: Financial Services | H84: Mid-Market | I84: Negotiation | J84: 45913 | L84: 36100 | M84: 0.05 | N84: 0.85 | P84: 5 | Q84: =IFERROR(VLOOKUP(E84,Lookups!$A$5:$B$24,2,FALSE),"Other") -> Referral | R84: =IFERROR(VLOOKUP(F84,Lookups!$D$5:$F$10,2,FALSE),"Unknown Product") -> Service Cloud | S84: =IFERROR(VLOOKUP(F84,Lookups!$D$5:$F$10,3,FALSE),"Unknown") -> Customer Service | T84: =IF(L84>=50000,"Enterprise",IF(L84>=20000,"Mid-Market","SMB")) -> Mid-Market | U84: =IF(I84="Closed Won","Won",IF(I84="Closed Lost","Lost","Open")) -> Open | V84: =IF(U84="Won",L84*(1-M84),0) -> 0 | W84: =IF(U84="Open",L84*N84,0) -> 30685 | X84: =IF(U84="Open","",IFERROR(K84-B84,"")) | Y84: =IF(U84="Open",Lookups!$B$2-B84,X84) -> 565 | Z84: =IF(AND(U84="Open",Y84>30),"STALE","OK") -> STALE | AA84: =TEXT(B84,"yyyy-mm") -> 2025-02 | AB84: =IF(K84="","",TEXT(K84,"yyyy-mm")) | AC84: ="Q"&ROUNDUP(MONTH(B84)/3,0)&"-"&YEAR(B84) -> Q1-2025 | AD84: =MIN(100,IF(H84="Enterprise",30,IF(H84="Mid-Market",22,14))+IF(T84="Enterprise",25,IF(T84="Mid-Market",18,10))+IF(Q84="Referral",25,IF(Q84="Organic Search",20,IF(Q84="Email",18,14)))+IF(G84="Technology",10,5)) -> 70 | AE84: =IF(U84<>"Open",U84,IF(N84>=0.8,"Commit",IF(N84>=0.5,"Best Case","Pipeline"))) -> Commit
A85: L00084 | B85: 46265 | C85: Chi Le | D85: South | E85: google cpc | F85: CRM-CORE | G85: Technology | H85: SMB | I85: New | J85: 46266 | L85: 4500 | M85: 0.05 | N85: 0.05 | P85: 1 | Q85: =IFERROR(VLOOKUP(E85,Lookups!$A$5:$B$24,2,FALSE),"Other") -> Paid Search | R85: =IFERROR(VLOOKUP(F85,Lookups!$D$5:$F$10,2,FALSE),"Unknown Product") -> NexaCRM Core | S85: =IFERROR(VLOOKUP(F85,Lookups!$D$5:$F$10,3,FALSE),"Unknown") -> CRM | T85: =IF(L85>=50000,"Enterprise",IF(L85>=20000,"Mid-Market","SMB")) -> SMB | U85: =IF(I85="Closed Won","Won",IF(I85="Closed Lost","Lost","Open")) -> Open | V85: =IF(U85="Won",L85*(1-M85),0) -> 0 | W85: =IF(U85="Open",L85*N85,0) -> 225 | X85: =IF(U85="Open","",IFERROR(K85-B85,"")) | Y85: =IF(U85="Open",Lookups!$B$2-B85,X85) -> 1 | Z85: =IF(AND(U85="Open",Y85>30),"STALE","OK") -> OK | AA85: =TEXT(B85,"yyyy-mm") -> 2026-08 | AB85: =IF(K85="","",TEXT(K85,"yyyy-mm")) | AC85: ="Q"&ROUNDUP(MONTH(B85)/3,0)&"-"&YEAR(B85) -> Q3-2026 | AD85: =MIN(100,IF(H85="Enterprise",30,IF(H85="Mid-Market",22,14))+IF(T85="Enterprise",25,IF(T85="Mid-Market",18,10))+IF(Q85="Referral",25,IF(Q85="Organic Search",20,IF(Q85="Email",18,14)))+IF(G85="Technology",10,5)) -> 48 | AE85: =IF(U85<>"Open",U85,IF(N85>=0.8,"Commit",IF(N85>=0.5,"Best Case","Pipeline"))) -> Pipeline
A86: L00085 | B86: 46135 | C86: Duy Pham | D86: South | E86: Cold Email | F86: MKT-AUTO | G86: Technology | H86: SMB | I86: Closed Lost | J86: 46179 | K86: 46179 | L86: 13400 | M86: 0 | N86: 0 | O86: Competitor | P86: 4 | Q86: =IFERROR(VLOOKUP(E86,Lookups!$A$5:$B$24,2,FALSE),"Other") -> Outbound | R86: =IFERROR(VLOOKUP(F86,Lookups!$D$5:$F$10,2,FALSE),"Unknown Product") -> Marketing Automation | S86: =IFERROR(VLOOKUP(F86,Lookups!$D$5:$F$10,3,FALSE),"Unknown") -> Marketing | T86: =IF(L86>=50000,"Enterprise",IF(L86>=20000,"Mid-Market","SMB")) -> SMB | U86: =IF(I86="Closed Won","Won",IF(I86="Closed Lost","Lost","Open")) -> Lost | V86: =IF(U86="Won",L86*(1-M86),0) -> 0 | W86: =IF(U86="Open",L86*N86,0) -> 0 | X86: =IF(U86="Open","",IFERROR(K86-B86,"")) -> 44 | Y86: =IF(U86="Open",Lookups!$B$2-B86,X86) -> 44 | Z86: =IF(AND(U86="Open",Y86>30),"STALE","OK") -> OK | AA86: =TEXT(B86,"yyyy-mm") -> 2026-04 | AB86: =IF(K86="","",TEXT(K86,"yyyy-mm")) -> 2026-06 | AC86: ="Q"&ROUNDUP(MONTH(B86)/3,0)&"-"&YEAR(B86) -> Q2-2026 | AD86: =MIN(100,IF(H86="Enterprise",30,IF(H86="Mid-Market",22,14))+IF(T86="Enterprise",25,IF(T86="Mid-Market",18,10))+IF(Q86="Referral",25,IF(Q86="Organic Search",20,IF(Q86="Email",18,14)))+IF(G86="Technology",10,5)) -> 48 | AE86: =IF(U86<>"Open",U86,IF(N86>=0.8,"Commit",IF(N86>=0.5,"Best Case","Pipeline"))) -> Lost
A87: L00086 | B87: 45782 | C87: Ha Vo | D87: North | E87: customer referral | F87: MKT-AUTO | G87: Healthcare | H87: SMB | I87: Closed Lost | J87: 45828 | K87: 45828 | L87: 15600 | M87: 0 | N87: 0 | O87: Competitor | P87: 5 | Q87: =IFERROR(VLOOKUP(E87,Lookups!$A$5:$B$24,2,FALSE),"Other") -> Referral | R87: =IFERROR(VLOOKUP(F87,Lookups!$D$5:$F$10,2,FALSE),"Unknown Product") -> Marketing Automation | S87: =IFERROR(VLOOKUP(F87,Lookups!$D$5:$F$10,3,FALSE),"Unknown") -> Marketing | T87: =IF(L87>=50000,"Enterprise",IF(L87>=20000,"Mid-Market","SMB")) -> SMB | U87: =IF(I87="Closed Won","Won",IF(I87="Closed Lost","Lost","Open")) -> Lost | V87: =IF(U87="Won",L87*(1-M87),0) -> 0 | W87: =IF(U87="Open",L87*N87,0) -> 0 | X87: =IF(U87="Open","",IFERROR(K87-B87,"")) -> 46 | Y87: =IF(U87="Open",Lookups!$B$2-B87,X87) -> 46 | Z87: =IF(AND(U87="Open",Y87>30),"STALE","OK") -> OK | AA87: =TEXT(B87,"yyyy-mm") -> 2025-05 | AB87: =IF(K87="","",TEXT(K87,"yyyy-mm")) -> 2025-06 | AC87: ="Q"&ROUNDUP(MONTH(B87)/3,0)&"-"&YEAR(B87) -> Q2-2025 | AD87: =MIN(100,IF(H87="Enterprise",30,IF(H87="Mid-Market",22,14))+IF(T87="Enterprise",25,IF(T87="Mid-Market",18,10))+IF(Q87="Referral",25,IF(Q87="Organic Search",20,IF(Q87="Email",18,14)))+IF(G87="Technology",10,5)) -> 54 | AE87: =IF(U87<>"Open",U87,IF(N87>=0.8,"Commit",IF(N87>=0.5,"Best Case","Pipeline"))) -> Lost
A88: L00087 | B88: 46042 | C88: Chi Le | D88: South | E88: SDR Outreach | F88: CRM-CORE | G88: Financial Services | H88: SMB | I88: Closed Lost | J88: 46105 | K88: 46105 | L88: 7600 | M88: 0 | N88: 0 | O88: No Decision | P88: 3 | Q88: =IFERROR(VLOOKUP(E88,Lookups!$A$5:$B$24,2,FALSE),"Other") -> Outbound | R88: =IFERROR(VLOOKUP(F88,Lookups!$D$5:$F$10,2,FALSE),"Unknown Product") -> NexaCRM Core | S88: =IFERROR(VLOOKUP(F88,Lookups!$D$5:$F$10,3,FALSE),"Unknown") -> CRM | T88: =IF(L88>=50000,"Enterprise",IF(L88>=20000,"Mid-Market","SMB")) -> SMB | U88: =IF(I88="Closed Won","Won",IF(I88="Closed Lost","Lost","Open")) -> Lost | V88: =IF(U88="Won",L88*(1-M88),0) -> 0 | W88: =IF(U88="Open",L88*N88,0) -> 0 | X88: =IF(U88="Open","",IFERROR(K88-B88,"")) -> 63 | Y88: =IF(U88="Open",Lookups!$B$2-B88,X88) -> 63 | Z88: =IF(AND(U88="Open",Y88>30),"STALE","OK") -> OK | AA88: =TEXT(B88,"yyyy-mm") -> 2026-01 | AB88: =IF(K88="","",TEXT(K88,"yyyy-mm")) -> 2026-03 | AC88: ="Q"&ROUNDUP(MONTH(B88)/3,0)&"-"&YEAR(B88) -> Q1-2026 | AD88: =MIN(100,IF(H88="Enterprise",30,IF(H88="Mid-Market",22,14))+IF(T88="Enterprise",25,IF(T88="Mid-Market",18,10))+IF(Q88="Referral",25,IF(Q88="Organic Search",20,IF(Q88="Email",18,14)))+IF(G88="Technology",10,5)) -> 43 | AE88: =IF(U88<>"Open",U88,IF(N88>=0.8,"Commit",IF(N88>=0.5,"Best Case","Pipeline"))) -> Lost
A89: L00088 | B89: 45694 | C89: Ha Vo | D89: North | E89: SEM - Google | F89: MKT-AUTO | G89: Healthcare | H89: SMB | I89: Closed Won | J89: 45729 | K89: 45729 | L89: 17500 | M89: 0.03 | N89: 1 | P89: 6 | Q89: =IFERROR(VLOOKUP(E89,Lookups!$A$5:$B$24,2,FALSE),"Other") -> Paid Search | R89: =IFERROR(VLOOKUP(F89,Lookups!$D$5:$F$10,2,FALSE),"Unknown Product") -> Marketing Automation | S89: =IFERROR(VLOOKUP(F89,Lookups!$D$5:$F$10,3,FALSE),"Unknown") -> Marketing | T89: =IF(L89>=50000,"Enterprise",IF(L89>=20000,"Mid-Market","SMB")) -> SMB | U89: =IF(I89="Closed Won","Won",IF(I89="Closed Lost","Lost","Open")) -> Won | V89: =IF(U89="Won",L89*(1-M89),0) -> 16975 | W89: =IF(U89="Open",L89*N89,0) -> 0 | X89: =IF(U89="Open","",IFERROR(K89-B89,"")) -> 35 | Y89: =IF(U89="Open",Lookups!$B$2-B89,X89) -> 35 | Z89: =IF(AND(U89="Open",Y89>30),"STALE","OK") -> OK | AA89: =TEXT(B89,"yyyy-mm") -> 2025-02 | AB89: =IF(K89="","",TEXT(K89,"yyyy-mm")) -> 2025-03 | AC89: ="Q"&ROUNDUP(MONTH(B89)/3,0)&"-"&YEAR(B89) -> Q1-2025 | AD89: =MIN(100,IF(H89="Enterprise",30,IF(H89="Mid-Market",22,14))+IF(T89="Enterprise",25,IF(T89="Mid-Market",18,10))+IF(Q89="Referral",25,IF(Q89="Organic Search",20,IF(Q89="Email",18,14)))+IF(G89="Technology",10,5)) -> 43 | AE89: =IF(U89<>"Open",U89,IF(N89>=0.8,"Commit",IF(N89>=0.5,"Best Case","Pipeline"))) -> Won
A90: L00089 | B90: 46024 | C90: Quynh Vu | D90: North | E90: Email Campaign | F90: CRM-CORE | G90: Retail | H90: Mid-Market | I90: Closed Lost | J90: 46036 | K90: 46036 | L90: 16200 | M90: 0 | N90: 0 | O90: No Decision | P90: 3 | Q90: =IFERROR(VLOOKUP(E90,Lookups!$A$5:$B$24,2,FALSE),"Other") -> Email | R90: =IFERROR(VLOOKUP(F90,Lookups!$D$5:$F$10,2,FALSE),"Unknown Product") -> NexaCRM Core | S90: =IFERROR(VLOOKUP(F90,Lookups!$D$5:$F$10,3,FALSE),"Unknown") -> CRM | T90: =IF(L90>=50000,"Enterprise",IF(L90>=20000,"Mid-Market","SMB")) -> SMB | U90: =IF(I90="Closed Won","Won",IF(I90="Closed Lost","Lost","Open")) -> Lost | V90: =IF(U90="Won",L90*(1-M90),0) -> 0 | W90: =IF(U90="Open",L90*N90,0) -> 0 | X90: =IF(U90="Open","",IFERROR(K90-B90,"")) -> 12 | Y90: =IF(U90="Open",Lookups!$B$2-B90,X90) -> 12 | Z90: =IF(AND(U90="Open",Y90>30),"STALE","OK") -> OK | AA90: =TEXT(B90,"yyyy-mm") -> 2026-01 | AB90: =IF(K90="","",TEXT(K90,"yyyy-mm")) -> 2026-01 | AC90: ="Q"&ROUNDUP(MONTH(B90)/3,0)&"-"&YEAR(B90) -> Q1-2026 | AD90: =MIN(100,IF(H90="Enterprise",30,IF(H90="Mid-Market",22,14))+IF(T90="Enterprise",25,IF(T90="Mid-Market",18,10))+IF(Q90="Referral",25,IF(Q90="Organic Search",20,IF(Q90="Email",18,14)))+IF(G90="Technology",10,5)) -> 55 | AE90: =IF(U90<>"Open",U90,IF(N90>=0.8,"Commit",IF(N90>=0.5,"Best Case","Pipeline"))) -> Lost
A91: L00090 | B91: 46007 | C91: Chi Le | D91: South | E91: SEO | F91: REV-OPS | G91: Retail | H91: Enterprise | I91: Closed Won | J91: 46072 | K91: 46072 | L91: 74500 | M91: 0.12 | N91: 1 | P91: 6 | Q91: =IFERROR(VLOOKUP(E91,Lookups!$A$5:$B$24,2,FALSE),"Other") -> Organic Search | R91: =IFERROR(VLOOKUP(F91,Lookups!$D$5:$F$10,2,FALSE),"Unknown Product") -> Revenue Operations Suite | S91: =IFERROR(VLOOKUP(F91,Lookups!$D$5:$F$10,3,FALSE),"Unknown") -> Revenue Ops | T91: =IF(L91>=50000,"Enterprise",IF(L91>=20000,"Mid-Market","SMB")) -> Enterprise | U91: =IF(I91="Closed Won","Won",IF(I91="Closed Lost","Lost","Open")) -> Won | V91: =IF(U91="Won",L91*(1-M91),0) -> 65560 | W91: =IF(U91="Open",L91*N91,0) -> 0 | X91: =IF(U91="Open","",IFERROR(K91-B91,"")) -> 65 | Y91: =IF(U91="Open",Lookups!$B$2-B91,X91) -> 65 | Z91: =IF(AND(U91="Open",Y91>30),"STALE","OK") -> OK | AA91: =TEXT(B91,"yyyy-mm") -> 2025-12 | AB91: =IF(K91="","",TEXT(K91,"yyyy-mm")) -> 2026-02 | AC91: ="Q"&ROUNDUP(MONTH(B91)/3,0)&"-"&YEAR(B91) -> Q4-2025 | AD91: =MIN(100,IF(H91="Enterprise",30,IF(H91="Mid-Market",22,14))+IF(T91="Enterprise",25,IF(T91="Mid-Market",18,10))+IF(Q91="Referral",25,IF(Q91="Organic Search",20,IF(Q91="Email",18,14)))+IF(G91="Technology",10,5)) -> 80 | AE91: =IF(U91<>"Open",U91,IF(N91>=0.8,"Commit",IF(N91>=0.5,"Best Case","Pipeline"))) -> Won
A92: L00091 | B92: 45873 | C92: Minh Do | D92: North | E92: SEO | F92: CRM-CORE | G92: Retail | H92: SMB | I92: Negotiation | J92: 46097 | L92: 6700 | M92: 0 | N92: 0.85 | P92: 5 | Q92: =IFERROR(VLOOKUP(E92,Lookups!$A$5:$B$24,2,FALSE),"Other") -> Organic Search | R92: =IFERROR(VLOOKUP(F92,Lookups!$D$5:$F$10,2,FALSE),"Unknown Product") -> NexaCRM Core | S92: =IFERROR(VLOOKUP(F92,Lookups!$D$5:$F$10,3,FALSE),"Unknown") -> CRM | T92: =IF(L92>=50000,"Enterprise",IF(L92>=20000,"Mid-Market","SMB")) -> SMB | U92: =IF(I92="Closed Won","Won",IF(I92="Closed Lost","Lost","Open")) -> Open | V92: =IF(U92="Won",L92*(1-M92),0) -> 0 | W92: =IF(U92="Open",L92*N92,0) -> 5695 | X92: =IF(U92="Open","",IFERROR(K92-B92,"")) | Y92: =IF(U92="Open",Lookups!$B$2-B92,X92) -> 393 | Z92: =IF(AND(U92="Open",Y92>30),"STALE","OK") -> STALE | AA92: =TEXT(B92,"yyyy-mm") -> 2025-08 | AB92: =IF(K92="","",TEXT(K92,"yyyy-mm")) | AC92: ="Q"&ROUNDUP(MONTH(B92)/3,0)&"-"&YEAR(B92) -> Q3-2025 | AD92: =MIN(100,IF(H92="Enterprise",30,IF(H92="Mid-Market",22,14))+IF(T92="Enterprise",25,IF(T92="Mid-Market",18,10))+IF(Q92="Referral",25,IF(Q92="Organic Search",20,IF(Q92="Email",18,14)))+IF(G92="Technology",10,5)) -> 49 | AE92: =IF(U92<>"Open",U92,IF(N92>=0.8,"Commit",IF(N92>=0.5,"Best Case","Pipeline"))) -> Commit
A93: L00092 | B93: 45822 | C93: Tuan Bui | D93: Central | E93: Google Ads | F93: CS-CLOUD | G93: Education | H93: SMB | I93: Closed Lost | J93: 45840 | K93: 45840 | L93: 27100 | M93: 0 | N93: 0 | O93: Price | P93: 2 | Q93: =IFERROR(VLOOKUP(E93,Lookups!$A$5:$B$24,2,FALSE),"Other") -> Paid Search | R93: =IFERROR(VLOOKUP(F93,Lookups!$D$5:$F$10,2,FALSE),"Unknown Product") -> Service Cloud | S93: =IFERROR(VLOOKUP(F93,Lookups!$D$5:$F$10,3,FALSE),"Unknown") -> Customer Service | T93: =IF(L93>=50000,"Enterprise",IF(L93>=20000,"Mid-Market","SMB")) -> Mid-Market | U93: =IF(I93="Closed Won","Won",IF(I93="Closed Lost","Lost","Open")) -> Lost | V93: =IF(U93="Won",L93*(1-M93),0) -> 0 | W93: =IF(U93="Open",L93*N93,0) -> 0 | X93: =IF(U93="Open","",IFERROR(K93-B93,"")) -> 18 | Y93: =IF(U93="Open",Lookups!$B$2-B93,X93) -> 18 | Z93: =IF(AND(U93="Open",Y93>30),"STALE","OK") -> OK | AA93: =TEXT(B93,"yyyy-mm") -> 2025-06 | AB93: =IF(K93="","",TEXT(K93,"yyyy-mm")) -> 2025-07 | AC93: ="Q"&ROUNDUP(MONTH(B93)/3,0)&"-"&YEAR(B93) -> Q2-2025 | AD93: =MIN(100,IF(H93="Enterprise",30,IF(H93="Mid-Market",22,14))+IF(T93="Enterprise",25,IF(T93="Mid-Market",18,10))+IF(Q93="Referral",25,IF(Q93="Organic Search",20,IF(Q93="Email",18,14)))+IF(G93="Technology",10,5)) -> 51 | AE93: =IF(U93<>"Open",U93,IF(N93>=0.8,"Commit",IF(N93>=0.5,"Best Case","Pipeline"))) -> Lost
A94: L00093 | B94: 45701 | C94: Quynh Vu | D94: North | E94: email nurture | F94: CS-CLOUD | G94: Financial Services | H94: Mid-Market | I94: Closed Won | J94: 45722 | K94: 45722 | L94: 32900 | M94: 0.03 | N94: 1 | P94: 6 | Q94: =IFERROR(VLOOKUP(E94,Lookups!$A$5:$B$24,2,FALSE),"Other") -> Email | R94: =IFERROR(VLOOKUP(F94,Lookups!$D$5:$F$10,2,FALSE),"Unknown Product") -> Service Cloud | S94: =IFERROR(VLOOKUP(F94,Lookups!$D$5:$F$10,3,FALSE),"Unknown") -> Customer Service | T94: =IF(L94>=50000,"Enterprise",IF(L94>=20000,"Mid-Market","SMB")) -> Mid-Market | U94: =IF(I94="Closed Won","Won",IF(I94="Closed Lost","Lost","Open")) -> Won | V94: =IF(U94="Won",L94*(1-M94),0) -> 31913 | W94: =IF(U94="Open",L94*N94,0) -> 0 | X94: =IF(U94="Open","",IFERROR(K94-B94,"")) -> 21 | Y94: =IF(U94="Open",Lookups!$B$2-B94,X94) -> 21 | Z94: =IF(AND(U94="Open",Y94>30),"STALE","OK") -> OK | AA94: =TEXT(B94,"yyyy-mm") -> 2025-02 | AB94: =IF(K94="","",TEXT(K94,"yyyy-mm")) -> 2025-03 | AC94: ="Q"&ROUNDUP(MONTH(B94)/3,0)&"-"&YEAR(B94) -> Q1-2025 | AD94: =MIN(100,IF(H94="Enterprise",30,IF(H94="Mid-Market",22,14))+IF(T94="Enterprise",25,IF(T94="Mid-Market",18,10))+IF(Q94="Referral",25,IF(Q94="Organic Search",20,IF(Q94="Email",18,14)))+IF(G94="Technology",10,5)) -> 63 | AE94: =IF(U94<>"Open",U94,IF(N94>=0.8,"Commit",IF(N94>=0.5,"Best Case","Pipeline"))) -> Won
A95: L00094 | B95: 45689 | C95: An Nguyen | D95: South | E95: SEO | F95: CRM-CORE | G95: Retail | H95: Enterprise | I95: Closed Won | J95: 45774 | K95: 45774 | L95: 17600 | M95: 0.05 | N95: 1 | P95: 6 | Q95: =IFERROR(VLOOKUP(E95,Lookups!$A$5:$B$24,2,FALSE),"Other") -> Organic Search | R95: =IFERROR(VLOOKUP(F95,Lookups!$D$5:$F$10,2,FALSE),"Unknown Product") -> NexaCRM Core | S95: =IFERROR(VLOOKUP(F95,Lookups!$D$5:$F$10,3,FALSE),"Unknown") -> CRM | T95: =IF(L95>=50000,"Enterprise",IF(L95>=20000,"Mid-Market","SMB")) -> SMB | U95: =IF(I95="Closed Won","Won",IF(I95="Closed Lost","Lost","Open")) -> Won | V95: =IF(U95="Won",L95*(1-M95),0) -> 16720 | W95: =IF(U95="Open",L95*N95,0) -> 0 | X95: =IF(U95="Open","",IFERROR(K95-B95,"")) -> 85 | Y95: =IF(U95="Open",Lookups!$B$2-B95,X95) -> 85 | Z95: =IF(AND(U95="Open",Y95>30),"STALE","OK") -> OK | AA95: =TEXT(B95,"yyyy-mm") -> 2025-02 | AB95: =IF(K95="","",TEXT(K95,"yyyy-mm")) -> 2025-04 | AC95: ="Q"&ROUNDUP(MONTH(B95)/3,0)&"-"&YEAR(B95) -> Q1-2025 | AD95: =MIN(100,IF(H95="Enterprise",30,IF(H95="Mid-Market",22,14))+IF(T95="Enterprise",25,IF(T95="Mid-Market",18,10))+IF(Q95="Referral",25,IF(Q95="Organic Search",20,IF(Q95="Email",18,14)))+IF(G95="Technology",10,5)) -> 65 | AE95: =IF(U95<>"Open",U95,IF(N95>=0.8,"Commit",IF(N95>=0.5,"Best Case","Pipeline"))) -> Won
A96: L00095 | B96: 45683 | C96: Tuan Bui | D96: Central | E96: LI Ads | F96: CRM-CORE | G96: Professional Services | H96: SMB | I96: Closed Lost | J96: 45762 | K96: 45762 | L96: 9600 | M96: 0 | N96: 0 | O96: Price | P96: 4 | Q96: =IFERROR(VLOOKUP(E96,Lookups!$A$5:$B$24,2,FALSE),"Other") -> LinkedIn | R96: =IFERROR(VLOOKUP(F96,Lookups!$D$5:$F$10,2,FALSE),"Unknown Product") -> NexaCRM Core | S96: =IFERROR(VLOOKUP(F96,Lookups!$D$5:$F$10,3,FALSE),"Unknown") -> CRM | T96: =IF(L96>=50000,"Enterprise",IF(L96>=20000,"Mid-Market","SMB")) -> SMB | U96: =IF(I96="Closed Won","Won",IF(I96="Closed Lost","Lost","Open")) -> Lost | V96: =IF(U96="Won",L96*(1-M96),0) -> 0 | W96: =IF(U96="Open",L96*N96,0) -> 0 | X96: =IF(U96="Open","",IFERROR(K96-B96,"")) -> 79 | Y96: =IF(U96="Open",Lookups!$B$2-B96,X96) -> 79 | Z96: =IF(AND(U96="Open",Y96>30),"STALE","OK") -> OK | AA96: =TEXT(B96,"yyyy-mm") -> 2025-01 | AB96: =IF(K96="","",TEXT(K96,"yyyy-mm")) -> 2025-04 | AC96: ="Q"&ROUNDUP(MONTH(B96)/3,0)&"-"&YEAR(B96) -> Q1-2025 | AD96: =MIN(100,IF(H96="Enterprise",30,IF(H96="Mid-Market",22,14))+IF(T96="Enterprise",25,IF(T96="Mid-Market",18,10))+IF(Q96="Referral",25,IF(Q96="Organic Search",20,IF(Q96="Email",18,14)))+IF(G96="Technology",10,5)) -> 43 | AE96: =IF(U96<>"Open",U96,IF(N96>=0.8,"Commit",IF(N96>=0.5,"Best Case","Pipeline"))) -> Lost
A97: L00096 | B97: 46101 | C97: Chi Le | D97: South | E97: Unknown Event | F97: BI-PLUS | G97: Financial Services | H97: Enterprise | I97: Closed Won | J97: 46200 | K97: 46200 | L97: 86700 | M97: 0.08 | N97: 1 | P97: 6 | Q97: =IFERROR(VLOOKUP(E97,Lookups!$A$5:$B$24,2,FALSE),"Other") -> Other | R97: =IFERROR(VLOOKUP(F97,Lookups!$D$5:$F$10,2,FALSE),"Unknown Product") -> Analytics Plus | S97: =IFERROR(VLOOKUP(F97,Lookups!$D$5:$F$10,3,FALSE),"Unknown") -> Analytics | T97: =IF(L97>=50000,"Enterprise",IF(L97>=20000,"Mid-Market","SMB")) -> Enterprise | U97: =IF(I97="Closed Won","Won",IF(I97="Closed Lost","Lost","Open")) -> Won | V97: =IF(U97="Won",L97*(1-M97),0) -> 79764 | W97: =IF(U97="Open",L97*N97,0) -> 0 | X97: =IF(U97="Open","",IFERROR(K97-B97,"")) -> 99 | Y97: =IF(U97="Open",Lookups!$B$2-B97,X97) -> 99 | Z97: =IF(AND(U97="Open",Y97>30),"STALE","OK") -> OK | AA97: =TEXT(B97,"yyyy-mm") -> 2026-03 | AB97: =IF(K97="","",TEXT(K97,"yyyy-mm")) -> 2026-06 | AC97: ="Q"&ROUNDUP(MONTH(B97)/3,0)&"-"&YEAR(B97) -> Q1-2026 | AD97: =MIN(100,IF(H97="Enterprise",30,IF(H97="Mid-Market",22,14))+IF(T97="Enterprise",25,IF(T97="Mid-Market",18,10))+IF(Q97="Referral",25,IF(Q97="Organic Search",20,IF(Q97="Email",18,14)))+IF(G97="Technology",10,5)) -> 74 | AE97: =IF(U97<>"Open",U97,IF(N97>=0.8,"Commit",IF(N97>=0.5,"Best Case","Pipeline"))) -> Won
A98: L00097 | B98: 45939 | C98: Minh Do | D98: North | E98: Webinar | F98: MKT-AUTO | G98: Retail | H98: Enterprise | I98: Closed Lost | J98: 46025 | K98: 46025 | L98: 33500 | M98: 0 | N98: 0 | O98: Budget | P98: 3 | Q98: =IFERROR(VLOOKUP(E98,Lookups!$A$5:$B$24,2,FALSE),"Other") -> Webinar | R98: =IFERROR(VLOOKUP(F98,Lookups!$D$5:$F$10,2,FALSE),"Unknown Product") -> Marketing Automation | S98: =IFERROR(VLOOKUP(F98,Lookups!$D$5:$F$10,3,FALSE),"Unknown") -> Marketing | T98: =IF(L98>=50000,"Enterprise",IF(L98>=20000,"Mid-Market","SMB")) -> Mid-Market | U98: =IF(I98="Closed Won","Won",IF(I98="Closed Lost","Lost","Open")) -> Lost | V98: =IF(U98="Won",L98*(1-M98),0) -> 0 | W98: =IF(U98="Open",L98*N98,0) -> 0 | X98: =IF(U98="Open","",IFERROR(K98-B98,"")) -> 86 | Y98: =IF(U98="Open",Lookups!$B$2-B98,X98) -> 86 | Z98: =IF(AND(U98="Open",Y98>30),"STALE","OK") -> OK | AA98: =TEXT(B98,"yyyy-mm") -> 2025-10 | AB98: =IF(K98="","",TEXT(K98,"yyyy-mm")) -> 2026-01 | AC98: ="Q"&ROUNDUP(MONTH(B98)/3,0)&"-"&YEAR(B98) -> Q4-2025 | AD98: =MIN(100,IF(H98="Enterprise",30,IF(H98="Mid-Market",22,14))+IF(T98="Enterprise",25,IF(T98="Mid-Market",18,10))+IF(Q98="Referral",25,IF(Q98="Organic Search",20,IF(Q98="Email",18,14)))+IF(G98="Technology",10,5)) -> 67 | AE98: =IF(U98<>"Open",U98,IF(N98>=0.8,"Commit",IF(N98>=0.5,"Best Case","Pipeline"))) -> Lost
A99: L00098 | B99: 46025 | C99: Quynh Vu | D99: North | E99: SEO | F99: MKT-AUTO | G99: Manufacturing | H99: SMB | I99: Closed Lost | J99: 46077 | K99: 46077 | L99: 15900 | M99: 0 | N99: 0 | O99: Timing | P99: 2 | Q99: =IFERROR(VLOOKUP(E99,Lookups!$A$5:$B$24,2,FALSE),"Other") -> Organic Search | R99: =IFERROR(VLOOKUP(F99,Lookups!$D$5:$F$10,2,FALSE),"Unknown Product") -> Marketing Automation | S99: =IFERROR(VLOOKUP(F99,Lookups!$D$5:$F$10,3,FALSE),"Unknown") -> Marketing | T99: =IF(L99>=50000,"Enterprise",IF(L99>=20000,"Mid-Market","SMB")) -> SMB | U99: =IF(I99="Closed Won","Won",IF(I99="Closed Lost","Lost","Open")) -> Lost | V99: =IF(U99="Won",L99*(1-M99),0) -> 0 | W99: =IF(U99="Open",L99*N99,0) -> 0 | X99: =IF(U99="Open","",IFERROR(K99-B99,"")) -> 52 | Y99: =IF(U99="Open",Lookups!$B$2-B99,X99) -> 52 | Z99: =IF(AND(U99="Open",Y99>30),"STALE","OK") -> OK | AA99: =TEXT(B99,"yyyy-mm") -> 2026-01 | AB99: =IF(K99="","",TEXT(K99,"yyyy-mm")) -> 2026-02 | AC99: ="Q"&ROUNDUP(MONTH(B99)/3,0)&"-"&YEAR(B99) -> Q1-2026 | AD99: =MIN(100,IF(H99="Enterprise",30,IF(H99="Mid-Market",22,14))+IF(T99="Enterprise",25,IF(T99="Mid-Market",18,10))+IF(Q99="Referral",25,IF(Q99="Organic Search",20,IF(Q99="Email",18,14)))+IF(G99="Technology",10,5)) -> 49 | AE99: =IF(U99<>"Open",U99,IF(N99>=0.8,"Commit",IF(N99>=0.5,"Best Case","Pipeline"))) -> Lost
A100: L00099 | B100: 45735 | C100: Quynh Vu | D100: North | E100: Outbound | F100: MKT-AUTO | G100: Manufacturing | H100: Enterprise | I100: Closed Lost | J100: 45762 | K100: 45762 | L100: 65100 | M100: 0 | N100: 0 | O100: Price | P100: 3 | Q100: =IFERROR(VLOOKUP(E100,Lookups!$A$5:$B$24,2,FALSE),"Other") -> Outbound | R100: =IFERROR(VLOOKUP(F100,Lookups!$D$5:$F$10,2,FALSE),"Unknown Product") -> Marketing Automation | S100: =IFERROR(VLOOKUP(F100,Lookups!$D$5:$F$10,3,FALSE),"Unknown") -> Marketing | T100: =IF(L100>=50000,"Enterprise",IF(L100>=20000,"Mid-Market","SMB")) -> Enterprise | U100: =IF(I100="Closed Won","Won",IF(I100="Closed Lost","Lost","Open")) -> Lost | V100: =IF(U100="Won",L100*(1-M100),0) -> 0 | W100: =IF(U100="Open",L100*N100,0) -> 0 | X100: =IF(U100="Open","",IFERROR(K100-B100,"")) -> 27 | Y100: =IF(U100="Open",Lookups!$B$2-B100,X100) -> 27 | Z100: =IF(AND(U100="Open",Y100>30),"STALE","OK") -> OK | AA100: =TEXT(B100,"yyyy-mm") -> 2025-03 | AB100: =IF(K100="","",TEXT(K100,"yyyy-mm")) -> 2025-04 | AC100: ="Q"&ROUNDUP(MONTH(B100)/3,0)&"-"&YEAR(B100) -> Q1-2025 | AD100: =MIN(100,IF(H100="Enterprise",30,IF(H100="Mid-Market",22,14))+IF(T100="Enterprise",25,IF(T100="Mid-Market",18,10))+IF(Q100="Referral",25,IF(Q100="Organic Search",20,IF(Q100="Email",18,14)))+IF(G100="Technology",10,5)) -> 74 | AE100: =IF(U100<>"Open",U100,IF(N100>=0.8,"Commit",IF(N100>=0.5,"Best Case","Pipeline"))) -> Lost
...

Sheet Rep_Performance
A1: Rep | B1: Region | C1: Team | D1: Total Leads | E1: Won Deals | F1: Lost Deals | G1: Win Rate | H1: Won Revenue | I1: Open Pipeline | J1: Weighted Pipeline | K1: Avg Sales Cycle | L1: Revenue Target | M1: Target Attainment
A2: An Nguyen | B2: =IFERROR(VLOOKUP(A2,Lookups!$I$5:$L$12,2,FALSE),"") -> South | C2: =IFERROR(VLOOKUP(A2,Lookups!$I$5:$L$12,3,FALSE),"") -> Growth | D2: =COUNTIF(CRM_Data!$C$2:$C$1801,A2) -> 218 | E2: =COUNTIFS(CRM_Data!$C$2:$C$1801,A2,CRM_Data!$U$2:$U$1801,"Won") -> 41 | F2: =COUNTIFS(CRM_Data!$C$2:$C$1801,A2,CRM_Data!$U$2:$U$1801,"Lost") -> 125 | G2: =IFERROR(E2/(E2+F2),0) -> 0.24698795 | H2: =SUMIFS(CRM_Data!$V$2:$V$1801,CRM_Data!$C$2:$C$1801,A2) -> 1014864 | I2: =SUMIFS(CRM_Data!$L$2:$L$1801,CRM_Data!$C$2:$C$1801,A2,CRM_Data!$U$2:$U$1801,"Open") -> 1690200 | J2: =SUMIFS(CRM_Data!$W$2:$W$1801,CRM_Data!$C$2:$C$1801,A2) -> 1077505 | K2: =IFERROR(SUMIFS(CRM_Data!$X$2:$X$1801,CRM_Data!$C$2:$C$1801,A2,CRM_Data!$U$2:$U$1801,"Won")/E2,0) -> 51.97561 | L2: =IFERROR(VLOOKUP(A2,Lookups!$I$5:$L$12,4,FALSE),0) -> 1035000 | M2: =IFERROR(H2/L2,0) -> 0.98054493
A3: Bao Tran | B3: =IFERROR(VLOOKUP(A3,Lookups!$I$5:$L$12,2,FALSE),"") -> South | C3: =IFERROR(VLOOKUP(A3,Lookups!$I$5:$L$12,3,FALSE),"") -> Growth | D3: =COUNTIF(CRM_Data!$C$2:$C$1801,A3) -> 237 | E3: =COUNTIFS(CRM_Data!$C$2:$C$1801,A3,CRM_Data!$U$2:$U$1801,"Won") -> 56 | F3: =COUNTIFS(CRM_Data!$C$2:$C$1801,A3,CRM_Data!$U$2:$U$1801,"Lost") -> 131 | G3: =IFERROR(E3/(E3+F3),0) -> 0.29946524 | H3: =SUMIFS(CRM_Data!$V$2:$V$1801,CRM_Data!$C$2:$C$1801,A3) -> 1296394 | I3: =SUMIFS(CRM_Data!$L$2:$L$1801,CRM_Data!$C$2:$C$1801,A3,CRM_Data!$U$2:$U$1801,"Open") -> 1582300 | J3: =SUMIFS(CRM_Data!$W$2:$W$1801,CRM_Data!$C$2:$C$1801,A3) -> 907010 | K3: =IFERROR(SUMIFS(CRM_Data!$X$2:$X$1801,CRM_Data!$C$2:$C$1801,A3,CRM_Data!$U$2:$U$1801,"Won")/E3,0) -> 52.339286 | L3: =IFERROR(VLOOKUP(A3,Lookups!$I$5:$L$12,4,FALSE),0) -> 1232000 | M3: =IFERROR(H3/L3,0) -> 1.0522679
A4: Chi Le | B4: =IFERROR(VLOOKUP(A4,Lookups!$I$5:$L$12,2,FALSE),"") -> South | C4: =IFERROR(VLOOKUP(A4,Lookups!$I$5:$L$12,3,FALSE),"") -> Commercial | D4: =COUNTIF(CRM_Data!$C$2:$C$1801,A4) -> 203 | E4: =COUNTIFS(CRM_Data!$C$2:$C$1801,A4,CRM_Data!$U$2:$U$1801,"Won") -> 38 | F4: =COUNTIFS(CRM_Data!$C$2:$C$1801,A4,CRM_Data!$U$2:$U$1801,"Lost") -> 109 | G4: =IFERROR(E4/(E4+F4),0) -> 0.2585034 | H4: =SUMIFS(CRM_Data!$V$2:$V$1801,CRM_Data!$C$2:$C$1801,A4) -> 1164807 | I4: =SUMIFS(CRM_Data!$L$2:$L$1801,CRM_Data!$C$2:$C$1801,A4,CRM_Data!$U$2:$U$1801,"Open") -> 1881700 | J4: =SUMIFS(CRM_Data!$W$2:$W$1801,CRM_Data!$C$2:$C$1801,A4) -> 1247955 | K4: =IFERROR(SUMIFS(CRM_Data!$X$2:$X$1801,CRM_Data!$C$2:$C$1801,A4,CRM_Data!$U$2:$U$1801,"Won")/E4,0) -> 55.026316 | L4: =IFERROR(VLOOKUP(A4,Lookups!$I$5:$L$12,4,FALSE),0) -> 1258000 | M4: =IFERROR(H4/L4,0) -> 0.92591971
A5: Duy Pham | B5: =IFERROR(VLOOKUP(A5,Lookups!$I$5:$L$12,2,FALSE),"") -> South | C5: =IFERROR(VLOOKUP(A5,Lookups!$I$5:$L$12,3,FALSE),"") -> Commercial | D5: =COUNTIF(CRM_Data!$C$2:$C$1801,A5) -> 222 | E5: =COUNTIFS(CRM_Data!$C$2:$C$1801,A5,CRM_Data!$U$2:$U$1801,"Won") -> 40 | F5: =COUNTIFS(CRM_Data!$C$2:$C$1801,A5,CRM_Data!$U$2:$U$1801,"Lost") -> 131 | G5: =IFERROR(E5/(E5+F5),0) -> 0.23391813 | H5: =SUMIFS(CRM_Data!$V$2:$V$1801,CRM_Data!$C$2:$C$1801,A5) -> 1187010 | I5: =SUMIFS(CRM_Data!$L$2:$L$1801,CRM_Data!$C$2:$C$1801,A5,CRM_Data!$U$2:$U$1801,"Open") -> 1879500 | J5: =SUMIFS(CRM_Data!$W$2:$W$1801,CRM_Data!$C$2:$C$1801,A5) -> 1178695 | K5: =IFERROR(SUMIFS(CRM_Data!$X$2:$X$1801,CRM_Data!$C$2:$C$1801,A5,CRM_Data!$U$2:$U$1801,"Won")/E5,0) -> 57.975 | L5: =IFERROR(VLOOKUP(A5,Lookups!$I$5:$L$12,4,FALSE),0) -> 1163000 | M5: =IFERROR(H5/L5,0) -> 1.0206449
A6: Ha Vo | B6: =IFERROR(VLOOKUP(A6,Lookups!$I$5:$L$12,2,FALSE),"") -> North | C6: =IFERROR(VLOOKUP(A6,Lookups!$I$5:$L$12,3,FALSE),"") -> Growth | D6: =COUNTIF(CRM_Data!$C$2:$C$1801,A6) -> 223 | E6: =COUNTIFS(CRM_Data!$C$2:$C$1801,A6,CRM_Data!$U$2:$U$1801,"Won") -> 42 | F6: =COUNTIFS(CRM_Data!$C$2:$C$1801,A6,CRM_Data!$U$2:$U$1801,"Lost") -> 130 | G6: =IFERROR(E6/(E6+F6),0) -> 0.24418605 | H6: =SUMIFS(CRM_Data!$V$2:$V$1801,CRM_Data!$C$2:$C$1801,A6) -> 1007131 | I6: =SUMIFS(CRM_Data!$L$2:$L$1801,CRM_Data!$C$2:$C$1801,A6,CRM_Data!$U$2:$U$1801,"Open") -> 1397100 | J6: =SUMIFS(CRM_Data!$W$2:$W$1801,CRM_Data!$C$2:$C$1801,A6) -> 747545 | K6: =IFERROR(SUMIFS(CRM_Data!$X$2:$X$1801,CRM_Data!$C$2:$C$1801,A6,CRM_Data!$U$2:$U$1801,"Won")/E6,0) -> 60.166667 | L6: =IFERROR(VLOOKUP(A6,Lookups!$I$5:$L$12,4,FALSE),0) -> 1057000 | M6: =IFERROR(H6/L6,0) -> 0.95282025
A7: Minh Do | B7: =IFERROR(VLOOKUP(A7,Lookups!$I$5:$L$12,2,FALSE),"") -> North | C7: =IFERROR(VLOOKUP(A7,Lookups!$I$5:$L$12,3,FALSE),"") -> Commercial | D7: =COUNTIF(CRM_Data!$C$2:$C$1801,A7) -> 236 | E7: =COUNTIFS(CRM_Data!$C$2:$C$1801,A7,CRM_Data!$U$2:$U$1801,"Won") -> 45 | F7: =COUNTIFS(CRM_Data!$C$2:$C$1801,A7,CRM_Data!$U$2:$U$1801,"Lost") -> 146 | G7: =IFERROR(E7/(E7+F7),0) -> 0.23560209 | H7: =SUMIFS(CRM_Data!$V$2:$V$1801,CRM_Data!$C$2:$C$1801,A7) -> 1168309 | I7: =SUMIFS(CRM_Data!$L$2:$L$1801,CRM_Data!$C$2:$C$1801,A7,CRM_Data!$U$2:$U$1801,"Open") -> 1454400 | J7: =SUMIFS(CRM_Data!$W$2:$W$1801,CRM_Data!$C$2:$C$1801,A7) -> 926075 | K7: =IFERROR(SUMIFS(CRM_Data!$X$2:$X$1801,CRM_Data!$C$2:$C$1801,A7,CRM_Data!$U$2:$U$1801,"Won")/E7,0) -> 49.066667 | L7: =IFERROR(VLOOKUP(A7,Lookups!$I$5:$L$12,4,FALSE),0) -> 1075000 | M7: =IFERROR(H7/L7,0) -> 1.0867991
A8: Quynh Vu | B8: =IFERROR(VLOOKUP(A8,Lookups!$I$5:$L$12,2,FALSE),"") -> North | C8: =IFERROR(VLOOKUP(A8,Lookups!$I$5:$L$12,3,FALSE),"") -> Growth | D8: =COUNTIF(CRM_Data!$C$2:$C$1801,A8) -> 226 | E8: =COUNTIFS(CRM_Data!$C$2:$C$1801,A8,CRM_Data!$U$2:$U$1801,"Won") -> 49 | F8: =COUNTIFS(CRM_Data!$C$2:$C$1801,A8,CRM_Data!$U$2:$U$1801,"Lost") -> 117 | G8: =IFERROR(E8/(E8+F8),0) -> 0.29518072 | H8: =SUMIFS(CRM_Data!$V$2:$V$1801,CRM_Data!$C$2:$C$1801,A8) -> 1594527 | I8: =SUMIFS(CRM_Data!$L$2:$L$1801,CRM_Data!$C$2:$C$1801,A8,CRM_Data!$U$2:$U$1801,"Open") -> 1614800 | J8: =SUMIFS(CRM_Data!$W$2:$W$1801,CRM_Data!$C$2:$C$1801,A8) -> 884890 | K8: =IFERROR(SUMIFS(CRM_Data!$X$2:$X$1801,CRM_Data!$C$2:$C$1801,A8,CRM_Data!$U$2:$U$1801,"Won")/E8,0) -> 60.285714 | L8: =IFERROR(VLOOKUP(A8,Lookups!$I$5:$L$12,4,FALSE),0) -> 1754000 | M8: =IFERROR(H8/L8,0) -> 0.90908039
A9: Tuan Bui | B9: =IFERROR(VLOOKUP(A9,Lookups!$I$5:$L$12,2,FALSE),"") -> Central | C9: =IFERROR(VLOOKUP(A9,Lookups!$I$5:$L$12,3,FALSE),"") -> Commercial | D9: =COUNTIF(CRM_Data!$C$2:$C$1801,A9) -> 235 | E9: =COUNTIFS(CRM_Data!$C$2:$C$1801,A9,CRM_Data!$U$2:$U$1801,"Won") -> 50 | F9: =COUNTIFS(CRM_Data!$C$2:$C$1801,A9,CRM_Data!$U$2:$U$1801,"Lost") -> 136 | G9: =IFERROR(E9/(E9+F9),0) -> 0.2688172 | H9: =SUMIFS(CRM_Data!$V$2:$V$1801,CRM_Data!$C$2:$C$1801,A9) -> 1342588 | I9: =SUMIFS(CRM_Data!$L$2:$L$1801,CRM_Data!$C$2:$C$1801,A9,CRM_Data!$U$2:$U$1801,"Open") -> 1511200 | J9: =SUMIFS(CRM_Data!$W$2:$W$1801,CRM_Data!$C$2:$C$1801,A9) -> 860340 | K9: =IFERROR(SUMIFS(CRM_Data!$X$2:$X$1801,CRM_Data!$C$2:$C$1801,A9,CRM_Data!$U$2:$U$1801,"Won")/E9,0) -> 55.02 | L9: =IFERROR(VLOOKUP(A9,Lookups!$I$5:$L$12,4,FALSE),0) -> 1289000 | M9: =IFERROR(H9/L9,0) -> 1.0415733

Sheet Channel_Performance
A1: Channel | B1: Leads | C1: Won | D1: Lost | E1: Win Rate | F1: Won Revenue | G1: Revenue / Lead | H1: Open Pipeline | I1: Weighted Pipeline | J1: Avg Won Deal
A2: Paid Search | B2: =COUNTIF(CRM_Data!$Q:$Q,$A2) -> 346 | C2: =COUNTIFS(CRM_Data!$Q:$Q,$A2,CRM_Data!$U:$U,"Won") -> 55 | D2: =COUNTIFS(CRM_Data!$Q$2:$Q$1801,A2,CRM_Data!$U$2:$U$1801,"Lost") -> 208 | E2: =IFERROR(C2/(C2+D2),0) -> 0.20912548 | F2: =SUMIFS(CRM_Data!$V$2:$V$1801,CRM_Data!$Q$2:$Q$1801,A2) -> 1255405 | G2: =IFERROR(F2/B2,0) -> 3628.3382 | H2: =SUMIFS(CRM_Data!$L$2:$L$1801,CRM_Data!$Q$2:$Q$1801,A2,CRM_Data!$U$2:$U$1801,"Open") -> 2729200 | I2: =SUMIFS(CRM_Data!$W$2:$W$1801,CRM_Data!$Q$2:$Q$1801,A2) -> 1554865 | J2: =IFERROR(F2/C2,0) -> 22825.545
A3: Organic Search | B3: =COUNTIF(CRM_Data!$Q:$Q,$A3) -> 335 | C3: =COUNTIFS(CRM_Data!$Q:$Q,$A3,CRM_Data!$U:$U,"Won") -> 73 | D3: =COUNTIFS(CRM_Data!$Q$2:$Q$1801,A3,CRM_Data!$U$2:$U$1801,"Lost") -> 181 | E3: =IFERROR(C3/(C3+D3),0) -> 0.28740157 | F3: =SUMIFS(CRM_Data!$V$2:$V$1801,CRM_Data!$Q$2:$Q$1801,A3) -> 1821606 | G3: =IFERROR(F3/B3,0) -> 5437.6299 | H3: =SUMIFS(CRM_Data!$L$2:$L$1801,CRM_Data!$Q$2:$Q$1801,A3,CRM_Data!$U$2:$U$1801,"Open") -> 2484300 | I3: =SUMIFS(CRM_Data!$W$2:$W$1801,CRM_Data!$Q$2:$Q$1801,A3) -> 1288290 | J3: =IFERROR(F3/C3,0) -> 24953.507
A4: LinkedIn | B4: =COUNTIF(CRM_Data!$Q:$Q,$A4) -> 271 | C4: =COUNTIFS(CRM_Data!$Q:$Q,$A4,CRM_Data!$U:$U,"Won") -> 58 | D4: =COUNTIFS(CRM_Data!$Q$2:$Q$1801,A4,CRM_Data!$U$2:$U$1801,"Lost") -> 161 | E4: =IFERROR(C4/(C4+D4),0) -> 0.26484018 | F4: =SUMIFS(CRM_Data!$V$2:$V$1801,CRM_Data!$Q$2:$Q$1801,A4) -> 1633109 | G4: =IFERROR(F4/B4,0) -> 6026.2325 | H4: =SUMIFS(CRM_Data!$L$2:$L$1801,CRM_Data!$Q$2:$Q$1801,A4,CRM_Data!$U$2:$U$1801,"Open") -> 1580500 | I4: =SUMIFS(CRM_Data!$W$2:$W$1801,CRM_Data!$Q$2:$Q$1801,A4) -> 865925 | J4: =IFERROR(F4/C4,0) -> 28157.052
A5: Referral | B5: =COUNTIF(CRM_Data!$Q:$Q,$A5) -> 225 | C5: =COUNTIFS(CRM_Data!$Q:$Q,$A5,CRM_Data!$U:$U,"Won") -> 51 | D5: =COUNTIFS(CRM_Data!$Q$2:$Q$1801,A5,CRM_Data!$U$2:$U$1801,"Lost") -> 121 | E5: =IFERROR(C5/(C5+D5),0) -> 0.29651163 | F5: =SUMIFS(CRM_Data!$V$2:$V$1801,CRM_Data!$Q$2:$Q$1801,A5) -> 1518294 | G5: =IFERROR(F5/B5,0) -> 6747.9733 | H5: =SUMIFS(CRM_Data!$L$2:$L$1801,CRM_Data!$Q$2:$Q$1801,A5,CRM_Data!$U$2:$U$1801,"Open") -> 1649400 | I5: =SUMIFS(CRM_Data!$W$2:$W$1801,CRM_Data!$Q$2:$Q$1801,A5) -> 1065240 | J5: =IFERROR(F5/C5,0) -> 29770.471
A6: Email | B6: =COUNTIF(CRM_Data!$Q:$Q,$A6) -> 215 | C6: =COUNTIFS(CRM_Data!$Q:$Q,$A6,CRM_Data!$U:$U,"Won") -> 55 | D6: =COUNTIFS(CRM_Data!$Q$2:$Q$1801,A6,CRM_Data!$U$2:$U$1801,"Lost") -> 117 | E6: =IFERROR(C6/(C6+D6),0) -> 0.31976744 | F6: =SUMIFS(CRM_Data!$V$2:$V$1801,CRM_Data!$Q$2:$Q$1801,A6) -> 1656502 | G6: =IFERROR(F6/B6,0) -> 7704.6605 | H6: =SUMIFS(CRM_Data!$L$2:$L$1801,CRM_Data!$Q$2:$Q$1801,A6,CRM_Data!$U$2:$U$1801,"Open") -> 1520700 | I6: =SUMIFS(CRM_Data!$W$2:$W$1801,CRM_Data!$Q$2:$Q$1801,A6) -> 997695 | J6: =IFERROR(F6/C6,0) -> 30118.218
A7: Webinar | B7: =COUNTIF(CRM_Data!$Q:$Q,$A7) -> 138 | C7: =COUNTIFS(CRM_Data!$Q:$Q,$A7,CRM_Data!$U:$U,"Won") -> 27 | D7: =COUNTIFS(CRM_Data!$Q$2:$Q$1801,A7,CRM_Data!$U$2:$U$1801,"Lost") -> 84 | E7: =IFERROR(C7/(C7+D7),0) -> 0.24324324 | F7: =SUMIFS(CRM_Data!$V$2:$V$1801,CRM_Data!$Q$2:$Q$1801,A7) -> 679313 | G7: =IFERROR(F7/B7,0) -> 4922.558 | H7: =SUMIFS(CRM_Data!$L$2:$L$1801,CRM_Data!$Q$2:$Q$1801,A7,CRM_Data!$U$2:$U$1801,"Open") -> 745100 | I7: =SUMIFS(CRM_Data!$W$2:$W$1801,CRM_Data!$Q$2:$Q$1801,A7) -> 492915 | J7: =IFERROR(F7/C7,0) -> 25159.741
A8: Outbound | B8: =COUNTIF(CRM_Data!$Q:$Q,$A8) -> 217 | C8: =COUNTIFS(CRM_Data!$Q:$Q,$A8,CRM_Data!$U:$U,"Won") -> 33 | D8: =COUNTIFS(CRM_Data!$Q$2:$Q$1801,A8,CRM_Data!$U$2:$U$1801,"Lost") -> 124 | E8: =IFERROR(C8/(C8+D8),0) -> 0.21019108 | F8: =SUMIFS(CRM_Data!$V$2:$V$1801,CRM_Data!$Q$2:$Q$1801,A8) -> 921554 | G8: =IFERROR(F8/B8,0) -> 4246.7926 | H8: =SUMIFS(CRM_Data!$L$2:$L$1801,CRM_Data!$Q$2:$Q$1801,A8,CRM_Data!$U$2:$U$1801,"Open") -> 1788300 | I8: =SUMIFS(CRM_Data!$W$2:$W$1801,CRM_Data!$Q$2:$Q$1801,A8) -> 1233070 | J8: =IFERROR(F8/C8,0) -> 27925.879
A9: Other | B9: =COUNTIF(CRM_Data!$Q:$Q,$A9) -> 53 | C9: =COUNTIFS(CRM_Data!$Q:$Q,$A9,CRM_Data!$U:$U,"Won") -> 9 | D9: =COUNTIFS(CRM_Data!$Q$2:$Q$1801,A9,CRM_Data!$U$2:$U$1801,"Lost") -> 29 | E9: =IFERROR(C9/(C9+D9),0) -> 0.23684211 | F9: =SUMIFS(CRM_Data!$V$2:$V$1801,CRM_Data!$Q$2:$Q$1801,A9) -> 289847 | G9: =IFERROR(F9/B9,0) -> 5468.8113 | H9: =SUMIFS(CRM_Data!$L$2:$L$1801,CRM_Data!$Q$2:$Q$1801,A9,CRM_Data!$U$2:$U$1801,"Open") -> 513700 | I9: =SUMIFS(CRM_Data!$W$2:$W$1801,CRM_Data!$Q$2:$Q$1801,A9) -> 332015 | J9: =IFERROR(F9/C9,0) -> 32205.222

Sheet Funnel_Analysis
A1: Funnel Stage | B1: Reached Stage | C1: Conversion from Previous | D1: Drop-off from Previous
A2: Lead Created | B2: =COUNTA(CRM_Data!$A$2:$A$1801) -> 1800 | C2: =1 -> 1 | D2: =0 -> 0
A3: Qualified | B3: =COUNTIF(CRM_Data!$P$2:$P$1801,">=2") -> 1757 | C3: =IFERROR(B3/B2,0) -> 0.97611111 | D3: =1-C3 -> 0.023888889
A4: Demo / Meeting | B4: =COUNTIF(CRM_Data!$P$2:$P$1801,">=3") -> 1481 | C4: =IFERROR(B4/B3,0) -> 0.84291406 | D4: =1-C4 -> 0.15708594
A5: Proposal | B5: =COUNTIF(CRM_Data!$P$2:$P$1801,">=4") -> 1142 | C5: =IFERROR(B5/B4,0) -> 0.77110061 | D5: =1-C5 -> 0.22889939
A6: Negotiation | B6: =COUNTIF(CRM_Data!$P$2:$P$1801,">=5") -> 792 | C6: =IFERROR(B6/B5,0) -> 0.69352014 | D6: =1-C6 -> 0.30647986
A7: Closed Won | B7: =COUNTIF(CRM_Data!$U$2:$U$1801,"Won") -> 361 | C7: =IFERROR(B7/B6,0) -> 0.45580808 | D7: =1-C7 -> 0.54419192

Sheet Monthly_Trend
A1: Month | B1: Created Leads | C1: Won Deals | D1: Won Revenue | E1: Avg Won Deal | F1: Win Rate
A2: 2025-01 | B2: =COUNTIF(CRM_Data!$AA$2:$AA$1801,A2) -> 88 | C2: =COUNTIFS(CRM_Data!$AB$2:$AB$1801,A2,CRM_Data!$U$2:$U$1801,"Won") -> 0 | D2: =SUMIFS(CRM_Data!$V$2:$V$1801,CRM_Data!$AB$2:$AB$1801,A2,CRM_Data!$U$2:$U$1801,"Won") -> 0 | E2: =IFERROR(D2/C2,0) -> 0 | F2: =IFERROR(C2/COUNTIFS(CRM_Data!$AB$2:$AB$1801,A2,CRM_Data!$U$2:$U$1801,"<>Open"),0) -> 0
A3: 2025-02 | B3: =COUNTIF(CRM_Data!$AA$2:$AA$1801,A3) -> 98 | C3: =COUNTIFS(CRM_Data!$AB$2:$AB$1801,A3,CRM_Data!$U$2:$U$1801,"Won") -> 3 | D3: =SUMIFS(CRM_Data!$V$2:$V$1801,CRM_Data!$AB$2:$AB$1801,A3,CRM_Data!$U$2:$U$1801,"Won") -> 60812 | E3: =IFERROR(D3/C3,0) -> 20270.667 | F3: =IFERROR(C3/COUNTIFS(CRM_Data!$AB$2:$AB$1801,A3,CRM_Data!$U$2:$U$1801,"<>Open"),0) -> 0.10344828
A4: 2025-03 | B4: =COUNTIF(CRM_Data!$AA$2:$AA$1801,A4) -> 99 | C4: =COUNTIFS(CRM_Data!$AB$2:$AB$1801,A4,CRM_Data!$U$2:$U$1801,"Won") -> 14 | D4: =SUMIFS(CRM_Data!$V$2:$V$1801,CRM_Data!$AB$2:$AB$1801,A4,CRM_Data!$U$2:$U$1801,"Won") -> 337413 | E4: =IFERROR(D4/C4,0) -> 24100.929 | F4: =IFERROR(C4/COUNTIFS(CRM_Data!$AB$2:$AB$1801,A4,CRM_Data!$U$2:$U$1801,"<>Open"),0) -> 0.16666667
A5: 2025-04 | B5: =COUNTIF(CRM_Data!$AA$2:$AA$1801,A5) -> 100 | C5: =COUNTIFS(CRM_Data!$AB$2:$AB$1801,A5,CRM_Data!$U$2:$U$1801,"Won") -> 24 | D5: =SUMIFS(CRM_Data!$V$2:$V$1801,CRM_Data!$AB$2:$AB$1801,A5,CRM_Data!$U$2:$U$1801,"Won") -> 646155 | E5: =IFERROR(D5/C5,0) -> 26923.125 | F5: =IFERROR(C5/COUNTIFS(CRM_Data!$AB$2:$AB$1801,A5,CRM_Data!$U$2:$U$1801,"<>Open"),0) -> 0.26966292
A6: 2025-05 | B6: =COUNTIF(CRM_Data!$AA$2:$AA$1801,A6) -> 108 | C6: =COUNTIFS(CRM_Data!$AB$2:$AB$1801,A6,CRM_Data!$U$2:$U$1801,"Won") -> 27 | D6: =SUMIFS(CRM_Data!$V$2:$V$1801,CRM_Data!$AB$2:$AB$1801,A6,CRM_Data!$U$2:$U$1801,"Won") -> 725995 | E6: =IFERROR(D6/C6,0) -> 26888.704 | F6: =IFERROR(C6/COUNTIFS(CRM_Data!$AB$2:$AB$1801,A6,CRM_Data!$U$2:$U$1801,"<>Open"),0) -> 0.32142857
A7: 2025-06 | B7: =COUNTIF(CRM_Data!$AA$2:$AA$1801,A7) -> 76 | C7: =COUNTIFS(CRM_Data!$AB$2:$AB$1801,A7,CRM_Data!$U$2:$U$1801,"Won") -> 16 | D7: =SUMIFS(CRM_Data!$V$2:$V$1801,CRM_Data!$AB$2:$AB$1801,A7,CRM_Data!$U$2:$U$1801,"Won") -> 501960 | E7: =IFERROR(D7/C7,0) -> 31372.5 | F7: =IFERROR(C7/COUNTIFS(CRM_Data!$AB$2:$AB$1801,A7,CRM_Data!$U$2:$U$1801,"<>Open"),0) -> 0.20512821
A8: 2025-07 | B8: =COUNTIF(CRM_Data!$AA$2:$AA$1801,A8) -> 87 | C8: =COUNTIFS(CRM_Data!$AB$2:$AB$1801,A8,CRM_Data!$U$2:$U$1801,"Won") -> 17 | D8: =SUMIFS(CRM_Data!$V$2:$V$1801,CRM_Data!$AB$2:$AB$1801,A8,CRM_Data!$U$2:$U$1801,"Won") -> 393784 | E8: =IFERROR(D8/C8,0) -> 23163.765 | F8: =IFERROR(C8/COUNTIFS(CRM_Data!$AB$2:$AB$1801,A8,CRM_Data!$U$2:$U$1801,"<>Open"),0) -> 0.20238095
A9: 2025-08 | B9: =COUNTIF(CRM_Data!$AA$2:$AA$1801,A9) -> 81 | C9: =COUNTIFS(CRM_Data!$AB$2:$AB$1801,A9,CRM_Data!$U$2:$U$1801,"Won") -> 15 | D9: =SUMIFS(CRM_Data!$V$2:$V$1801,CRM_Data!$AB$2:$AB$1801,A9,CRM_Data!$U$2:$U$1801,"Won") -> 346790 | E9: =IFERROR(D9/C9,0) -> 23119.333 | F9: =IFERROR(C9/COUNTIFS(CRM_Data!$AB$2:$AB$1801,A9,CRM_Data!$U$2:$U$1801,"<>Open"),0) -> 0.22058824
A10: 2025-09 | B10: =COUNTIF(CRM_Data!$AA$2:$AA$1801,A10) -> 94 | C10: =COUNTIFS(CRM_Data!$AB$2:$AB$1801,A10,CRM_Data!$U$2:$U$1801,"Won") -> 18 | D10: =SUMIFS(CRM_Data!$V$2:$V$1801,CRM_Data!$AB$2:$AB$1801,A10,CRM_Data!$U$2:$U$1801,"Won") -> 547893 | E10: =IFERROR(D10/C10,0) -> 30438.5 | F10: =IFERROR(C10/COUNTIFS(CRM_Data!$AB$2:$AB$1801,A10,CRM_Data!$U$2:$U$1801,"<>Open"),0) -> 0.30508475
A11: 2025-10 | B11: =COUNTIF(CRM_Data!$AA$2:$AA$1801,A11) -> 95 | C11: =COUNTIFS(CRM_Data!$AB$2:$AB$1801,A11,CRM_Data!$U$2:$U$1801,"Won") -> 14 | D11: =SUMIFS(CRM_Data!$V$2:$V$1801,CRM_Data!$AB$2:$AB$1801,A11,CRM_Data!$U$2:$U$1801,"Won") -> 496510 | E11: =IFERROR(D11/C11,0) -> 35465 | F11: =IFERROR(C11/COUNTIFS(CRM_Data!$AB$2:$AB$1801,A11,CRM_Data!$U$2:$U$1801,"<>Open"),0) -> 0.19444444
A12: 2025-11 | B12: =COUNTIF(CRM_Data!$AA$2:$AA$1801,A12) -> 83 | C12: =COUNTIFS(CRM_Data!$AB$2:$AB$1801,A12,CRM_Data!$U$2:$U$1801,"Won") -> 27 | D12: =SUMIFS(CRM_Data!$V$2:$V$1801,CRM_Data!$AB$2:$AB$1801,A12,CRM_Data!$U$2:$U$1801,"Won") -> 669378 | E12: =IFERROR(D12/C12,0) -> 24791.778 | F12: =IFERROR(C12/COUNTIFS(CRM_Data!$AB$2:$AB$1801,A12,CRM_Data!$U$2:$U$1801,"<>Open"),0) -> 0.31764706
A13: 2025-12 | B13: =COUNTIF(CRM_Data!$AA$2:$AA$1801,A13) -> 85 | C13: =COUNTIFS(CRM_Data!$AB$2:$AB$1801,A13,CRM_Data!$U$2:$U$1801,"Won") -> 17 | D13: =SUMIFS(CRM_Data!$V$2:$V$1801,CRM_Data!$AB$2:$AB$1801,A13,CRM_Data!$U$2:$U$1801,"Won") -> 358193 | E13: =IFERROR(D13/C13,0) -> 21070.176 | F13: =IFERROR(C13/COUNTIFS(CRM_Data!$AB$2:$AB$1801,A13,CRM_Data!$U$2:$U$1801,"<>Open"),0) -> 0.22666667
... A21: 2026-08 | B21: =COUNTIF(CRM_Data!$AA$2:$AA$1801,A21) -> 80 | C21: =COUNTIFS(CRM_Data!$AB$2:$AB$1801,A21,CRM_Data!$U$2:$U$1801,"Won") -> 13 | D21: =SUMIFS(CRM_Data!$V$2:$V$1801,CRM_Data!$AB$2:$AB$1801,A21,CRM_Data!$U$2:$U$1801,"Won") -> 348890 | E21: =IFERROR(D21/C21,0) -> 26837.692 | F21: =IFERROR(C21/COUNTIFS(CRM_Data!$AB$2:$AB$1801,A21,CRM_Data!$U$2:$U$1801,"<>Open"),0) -> 0.30232558

Sheet Action_List
A1: Priority | B1: Management Finding | C1: Evidence | D1: Recommended Action | E1: Owner
A2: High | B2: Late-funnel conversion is the biggest leakage point | C2: Negotiation → Closed Won conversion = 45.6%; drop-off = 54.4% | D2: Review negotiation objections, pricing approval, proposal quality and follow-up cadence; track loss reason by rep and product. | E2: Sales Ops
A3: High | B3: Open pipeline contains a material stale-lead backlog | C3: 358 open leads are older than 30 days | D3: Run a weekly aging review; requalify, progress or close stale opportunities so pipeline coverage is not overstated. | E3: Sales Managers
A4: High | B4: Paid Search delivers volume but weak commercial efficiency | C4: 346 leads (largest channel) but 20.9% win rate and $3,628 revenue per lead | D4: Tighten keyword/landing-page alignment and qualification criteria before increasing acquisition volume. | E4: Growth + Sales
A5: Medium | B5: Email produces the strongest channel efficiency | C5: 32.0% win rate and $7,705 revenue per lead | D5: Expand nurture and lifecycle programs carefully; protect list quality and separate owned-channel efficiency from paid acquisition economics. | E5: CRM / Growth
A6: Medium | B6: Rep performance should be read using both absolute revenue and target attainment | C6: Quynh Vu generated $1.59M revenue but reached 90.9% of target; Minh Do reached 108.7% | D6: Use revenue, attainment, win rate, and pipeline coverage together for coaching rather than ranking reps on one metric. | E6: Commercial Lead

Sheet Lookups
A1: Lookup Tables & Control Values
A2: Data Snapshot Date | B2: 46266
A4: Raw Source | B4: Clean Channel | D4: Product Code | E4: Product Name | F4: Product Category | G4: List Price | I4: Rep | J4: Region | K4: Team | L4: Revenue Target | N4: Clean Channels
A5: Google Ads | B5: Paid Search | D5: CRM-CORE | E5: NexaCRM Core | F5: CRM | G5: 9000 | I5: An Nguyen | J5: South | K5: Growth | L5: 1035000 | N5: Paid Search
A6: google cpc | B6: Paid Search | D6: CRM-PRO | E6: NexaCRM Pro | F6: CRM | G6: 22000 | I6: Bao Tran | J6: South | K6: Growth | L6: 1232000 | N6: Organic Search
A7: SEM - Google | B7: Paid Search | D7: MKT-AUTO | E7: Marketing Automation | F7: Marketing | G7: 18000 | I7: Chi Le | J7: South | K7: Commercial | L7: 1258000 | N7: LinkedIn
A8: Google Organic | B8: Organic Search | D8: BI-PLUS | E8: Analytics Plus | F8: Analytics | G8: 26000 | I8: Duy Pham | J8: South | K8: Commercial | L8: 1163000 | N8: Referral
A9: SEO | B9: Organic Search | D9: CS-CLOUD | E9: Service Cloud | F9: Customer Service | G9: 24000 | I9: Ha Vo | J9: North | K9: Growth | L9: 1057000 | N9: Email
A10: organic search | B10: Organic Search | D10: REV-OPS | E10: Revenue Operations Suite | F10: Revenue Ops | G10: 42000 | I10: Minh Do | J10: North | K10: Commercial | L10: 1075000 | N10: Webinar
A11: LinkedIn Ads | B11: LinkedIn | I11: Quynh Vu | J11: North | K11: Growth | L11: 1754000 | N11: Outbound
A12: linkedin | B12: LinkedIn | I12: Tuan Bui | J12: Central | K12: Commercial | L12: 1289000 | N12: Other
A13: LI Ads | B13: LinkedIn
A14: Referral | B14: Referral
A15: Partner Referral | B15: Referral
A16: customer referral | B16: Referral
A17: Email Campaign | B17: Email
A18: newsletter | B18: Email
A19: email nurture | B19: Email
A20: Webinar | B20: Webinar
A21: virtual event | B21: Webinar
A22: Outbound | B22: Outbound
A23: Cold Email | B23: Outbound
A24: SDR Outreach | B24: Outbound

Sheet Data_Dictionary
A1: Field | B1: Type | C1: Source / Formula | D1: Business meaning
A2: Lead_ID | B2: Text | C2: Raw | D2: Unique CRM lead identifier
A3: Created_Date | B3: Date | C3: Raw | D3: Lead creation date
A4: Owner | B4: Text | C4: Raw | D4: Sales owner
A5: Raw_Source | B5: Text | C5: Raw | D5: Unstandardized acquisition source
A6: Source_Clean | B6: Text | C6: VLOOKUP + IFERROR | D6: Standardized acquisition channel
A7: Product_Name | B7: Text | C7: VLOOKUP + IFERROR | D7: Product mapped from Product_Code
A8: Deal_Segment | B8: Text | C8: IF | D8: Segment derived from expected value
A9: Outcome | B9: Text | C9: IF | D9: Won / Lost / Open
A10: Actual_Revenue_USD | B10: Currency | C10: IF | D10: Closed-won value after discount
A11: Weighted_Pipeline_USD | B11: Currency | C11: IF | D11: Open expected value × stage probability
A12: Sales_Cycle_Days | B12: Whole number | C12: IF + IFERROR | D12: Days from creation to close
... A18: Forecast_Category | B18: Text | C18: Nested IF | D18: Pipeline / Best Case / Commit / Closed outcome

Sheet Project_Overview
A1: Commercial & CRM Operations Analysis | Excel
A3: Business Problem | B3: Turn CRM pipeline data into management-ready insight on funnel leakage, channel quality, rep performance, pipeline health and stale opportunities.
A4: Dataset | B4: 1,800 synthetic CRM leads covering Jan 2025 to Aug 2026.
A5: Core Excel Skills | B5: VLOOKUP, SUMIFS, COUNTIFS, IF, IFERROR, TEXT, ROUNDUP, conditional formatting, tables, data validation, charts.
A6: Key Deliverable | B6: Executive dashboard plus formula-driven rep, channel, funnel and monthly performance analysis.
A7: Data Ethics | B7: Synthetic portfolio data; no claim that records belong to a real company.
A8: HR Positioning | B8: Commercial Analytics / CRM Analytics / Growth Analytics / Business Analyst / Junior Data Analyst.
A10: Excel Formula Evidence
A11: VLOOKUP + IFERROR | B11: Standardizes raw acquisition sources and maps product names/categories.
A12: SUMIFS | B12: Revenue, open pipeline, weighted pipeline by rep/channel/month.
A13: COUNTIFS | B13: Won/lost deals, win rates, monthly deal counts and funnel analysis.
A14: IF / Nested IF | B14: Outcome, segmentation, SLA status, lead score, forecast category.
A15: TEXT / MONTH / YEAR / ROUNDUP | B15: Monthly and quarterly reporting keys.
A16: Conditional Formatting | B16: Stale opportunities, lead score, target attainment and pipeline emphasis.
A17: Excel Tables + Validation | B17: Filterable CRM table, clean input controls and structured analysis sheets.
A18: Charts | B18: Funnel, channel revenue, monthly revenue trend, rep revenue vs target.
